Workbook

Sheet Bugs
A1: FutureNow Ticket | B1: ID | C1: Recurrent Issue (tech) | D1: Recurrent Issue (Business)
A2: INC42077895 | B2: 6000128546
B3: 6000139374
A4: INC42788004 | B4: 6000140063
A5: INC42930584 | B5: 6000142441
A6: INC42930203 | B6: 6000142434
B7: 6000142896
A8: INC43019830 | D8: x
A9: INC43035790
A10: INC43117032
A11: INC43149903
A12: INC43163860 | D12: x
A13: INC43215416 | D13: x
A14: INC43249416 | D14: x
A15: INC43255046 | D15: x
A16: INC43259250 | D16: x
A17: INC43287075 | B17: 6000147166
A18: INC43302173 | D18: x
A19: INC43332346
A20: INC43334219 | D20: x
A21: INC43344804 | D21: x
A22: INC43356074
A23: INC43371571
A24: INC43399228 | B24: 6000147888
A25: INC43400197 | B25: 6000147912
A26: INC43433151
A27: INC43436495
A28: INC43465907
A29: INC43469397 | D29: x
A30: INC43469550 | D30: x
A31: INC43487284 | D31: x
A32: INC43498557
A33: INC43504801
A34: INC43508169
A35: INC43508280 | D35: x
A36: INC43508305 | D36: x
A37: INC43508194
A38: INC43508341 | D38: x
A39: INC43512839 | B39: 6000149049
A40: INC43503029
A41: INC43513783 | D41: x
A42: INC43538753
A43: INC43563280
A44: INC43576197 | D44: x
A45: INC43584221
A46: INC43595418 | D46: x
A47: INC43626801 | B47: 8500020414
A48: INC43639701 | D48: x
A49: INC43642208
A50: INC43607409 | D50: x
A51: INC43690708 | D51: X
A52: INC43720360 | D52: x
A53: INC43721827 | D53: x
A54: INC43724677 | D54: x
A55: INC43727632 | D55: x
A56: INC43737453 | D56: x
A57: INC43742772 | D57: x
A58: INC43743150
A59: INC43745390 | D59: x
A60: INC43748125 | D60: x
A61: INC43751646
A62: INC43753752 | D62: x
A63: INC43755284 | D63: x
A64: INC43756209 | D64: X
A65: INC43765407
A66: INC43765992 | D66: x
A67: INC43766812 | C67: x
A68: INC43768667 | C68: x
A69: INC43771246
A70: INC43771305
A71: INC43771434
A72: INC43772886
A73: INC43772965
A74: INC43773005
A75: INC43774476
A76: INC43775079
A77: INC43775669 | C77: x
A78: INC43775723 | D78: x
A79: INC43778039 | D79: x
A80: INC43822357 | C80: x
A81: INC43835191 | D81: x
A82: INC43836838 | D82: x
A83: INC43836990 | D83: x
A84: INC43881294
A85: INC43887207 | D85: x
A86: INC43896159
A87: INC43918755
A88: INC43926121
A89: INC43930182 | D89: x
A90: INC43930327 | D90: x
A91: INC43930951
A92: INC43940399
A93: INC43943430 | D93: x
A94: INC43943726
A95: INC43949745 | C95: x
A96: INC43956263 | C96: x
A97: INC43959121 | C97: x
A98: INC43959647
A99: INC43981419 | D99: X
A100: INC43982052 | C100: x
...

Sheet MasterData
B2: Open Status | C2: Transitional Status | D2: Closed Status | F2: Priority | I2: Starts | J2: Ends
B3: In Process | C3: Defect Correction in Process | D3: Closed | F3: *1* | H3: CW24 | I3: 45817 | J3: 45823
B4: Forwarded | C4: Proposed Solution | D4: Confirm_Closed | F4: *2* | H4: CW25 | I4: 45824 | J4: 45830
B5: Customer Action | C5: Solution Proposed | D5: Confirmed | F5: *3* | H5: CW26 | I5: 45831 | J5: 45837
B6: not in Scope | D6: Resolved | F6: *4* | H6: CW27 | I6: 45838 | J6: 45844
B7: Postponed | D7: Closed | H7: CW28 | I7: 45845 | J7: 45851
B8: In Progress | H8: CW29 | I8: 45852 | J8: 45858
B9: Pending | H9: CW30 | I9: 45859 | J9: 45865
H10: CW31 | I10: 45866 | J10: 45872
H11: CW32 | I11: 45873 | J11: 45879
H12: CW33 | I12: 45880 | J12: 45886
H13: CW34 | I13: 45887 | J13: 45893
H14: CW35 | I14: 45894 | J14: 45900
H15: CW36 | I15: 45901 | J15: 45907
H16: CW37 | I16: 45908 | J16: 45914
H17: CW38 | I17: 45915 | J17: 45921
H18: CW39 | I18: 45922 | J18: 45928
H19: CW40 | I19: 45929 | J19: 45935
B20: System Users | H20: CW41 | I20: 45936 | J20: 45942
B21: SAP SOLUTION MANAGER S1A | H21: CW42 | I21: 45943 | J21: 45949
H22: CW43 | I22: 45950 | J22: 45956
H23: CW44 | I23: 45957 | J23: 45963
H24: CW45 | I24: 45964 | J24: 45970
H25: CW46 | I25: 45971 | J25: 45977
H26: CW47 | I26: 45978 | J26: 45984
H27: CW48 | I27: 45985 | J27: 45991
H28: CW49 | I28: 45992 | J28: 45998
H29: CW50 | I29: 45999 | J29: 46005
H30: CW51 | I30: 46006 | J30: 46012
H31: CW52 | I31: 46013 | J31: 46019
H32: CW53 | I32: 46020 | J32: 46026

Sheet Comparator
A1: =IF('VIM-Incidents_20250724'!A1<>'VIM-Incidents_20250731'!A1,"Difference","OK") -> OK | B1: =IF('VIM-Incidents_20250724'!B1<>'VIM-Incidents_20250731'!B1,"Difference","OK") -> OK | C1: =IF('VIM-Incidents_20250724'!C1<>'VIM-Incidents_20250731'!C1,"Difference","OK") -> OK | D1: =IF('VIM-Incidents_20250724'!D1<>'VIM-Incidents_20250731'!D1,"Difference","OK") -> OK | E1: =IF('VIM-Incidents_20250724'!E1<>'VIM-Incidents_20250731'!E1,"Difference","OK") -> OK | F1: =IF('VIM-Incidents_20250724'!F1<>'VIM-Incidents_20250731'!F1,"Difference","OK") -> OK | G1: =IF('VIM-Incidents_20250724'!G1<>'VIM-Incidents_20250731'!G1,"Difference","OK") -> OK | H1: =IF('VIM-Incidents_20250724'!H1<>'VIM-Incidents_20250731'!H1,"Difference","OK") -> OK | ... S1: =IF('VIM-Incidents_20250724'!S1<>'VIM-Incidents_20250731'!S1,"Difference","OK") -> OK
A2: =IF('VIM-Incidents_20250724'!A2<>'VIM-Incidents_20250731'!A2,"Difference","OK") -> OK | B2: =IF('VIM-Incidents_20250724'!B2<>'VIM-Incidents_20250731'!B2,"Difference","OK") -> OK | C2: =IF('VIM-Incidents_20250724'!C2<>'VIM-Incidents_20250731'!C2,"Difference","OK") -> OK | D2: =IF('VIM-Incidents_20250724'!D2<>'VIM-Incidents_20250731'!D2,"Difference","OK") -> OK | E2: =IF('VIM-Incidents_20250724'!E2<>'VIM-Incidents_20250731'!E2,"Difference","OK") -> OK | F2: =IF('VIM-Incidents_20250724'!F2<>'VIM-Incidents_20250731'!F2,"Difference","OK") -> OK | G2: =IF('VIM-Incidents_20250724'!G2<>'VIM-Incidents_20250731'!G2,"Difference","OK") -> OK | H2: =IF('VIM-Incidents_20250724'!H2<>'VIM-Incidents_20250731'!H2,"Difference","OK") -> OK | ... S2: =IF('VIM-Incidents_20250724'!S2<>'VIM-Incidents_20250731'!S2,"Difference","OK") -> OK
A3: =IF('VIM-Incidents_20250724'!A3<>'VIM-Incidents_20250731'!A3,"Difference","OK") -> OK | B3: =IF('VIM-Incidents_20250724'!B3<>'VIM-Incidents_20250731'!B3,"Difference","OK") -> OK | C3: =IF('VIM-Incidents_20250724'!C3<>'VIM-Incidents_20250731'!C3,"Difference","OK") -> OK | D3: =IF('VIM-Incidents_20250724'!D3<>'VIM-Incidents_20250731'!D3,"Difference","OK") -> OK | E3: =IF('VIM-Incidents_20250724'!E3<>'VIM-Incidents_20250731'!E3,"Difference","OK") -> OK | F3: =IF('VIM-Incidents_20250724'!F3<>'VIM-Incidents_20250731'!F3,"Difference","OK") -> OK | G3: =IF('VIM-Incidents_20250724'!G3<>'VIM-Incidents_20250731'!G3,"Difference","OK") -> OK | H3: =IF('VIM-Incidents_20250724'!H3<>'VIM-Incidents_20250731'!H3,"Difference","OK") -> OK | ... S3: =IF('VIM-Incidents_20250724'!S3<>'VIM-Incidents_20250731'!S3,"Difference","OK") -> OK
A4: =IF('VIM-Incidents_20250724'!A4<>'VIM-Incidents_20250731'!A4,"Difference","OK") -> OK | B4: =IF('VIM-Incidents_20250724'!B4<>'VIM-Incidents_20250731'!B4,"Difference","OK") -> OK | C4: =IF('VIM-Incidents_20250724'!C4<>'VIM-Incidents_20250731'!C4,"Difference","OK") -> OK | D4: =IF('VIM-Incidents_20250724'!D4<>'VIM-Incidents_20250731'!D4,"Difference","OK") -> OK | E4: =IF('VIM-Incidents_20250724'!E4<>'VIM-Incidents_20250731'!E4,"Difference","OK") -> OK | F4: =IF('VIM-Incidents_20250724'!F4<>'VIM-Incidents_20250731'!F4,"Difference","OK") -> OK | G4: =IF('VIM-Incidents_20250724'!G4<>'VIM-Incidents_20250731'!G4,"Difference","OK") -> OK | H4: =IF('VIM-Incidents_20250724'!H4<>'VIM-Incidents_20250731'!H4,"Difference","OK") -> OK | ... S4: =IF('VIM-Incidents_20250724'!S4<>'VIM-Incidents_20250731'!S4,"Difference","OK") -> OK
A5: =IF('VIM-Incidents_20250724'!A5<>'VIM-Incidents_20250731'!A5,"Difference","OK") -> OK | B5: =IF('VIM-Incidents_20250724'!B5<>'VIM-Incidents_20250731'!B5,"Difference","OK") -> OK | C5: =IF('VIM-Incidents_20250724'!C5<>'VIM-Incidents_20250731'!C5,"Difference","OK") -> OK | D5: =IF('VIM-Incidents_20250724'!D5<>'VIM-Incidents_20250731'!D5,"Difference","OK") -> OK | E5: =IF('VIM-Incidents_20250724'!E5<>'VIM-Incidents_20250731'!E5,"Difference","OK") -> OK | F5: =IF('VIM-Incidents_20250724'!F5<>'VIM-Incidents_20250731'!F5,"Difference","OK") -> OK | G5: =IF('VIM-Incidents_20250724'!G5<>'VIM-Incidents_20250731'!G5,"Difference","OK") -> OK | H5: =IF('VIM-Incidents_20250724'!H5<>'VIM-Incidents_20250731'!H5,"Difference","OK") -> OK | ... S5: =IF('VIM-Incidents_20250724'!S5<>'VIM-Incidents_20250731'!S5,"Difference","OK") -> OK
A6: =IF('VIM-Incidents_20250724'!A6<>'VIM-Incidents_20250731'!A6,"Difference","OK") -> OK | B6: =IF('VIM-Incidents_20250724'!B6<>'VIM-Incidents_20250731'!B6,"Difference","OK") -> OK | C6: =IF('VIM-Incidents_20250724'!C6<>'VIM-Incidents_20250731'!C6,"Difference","OK") -> OK | D6: =IF('VIM-Incidents_20250724'!D6<>'VIM-Incidents_20250731'!D6,"Difference","OK") -> OK | E6: =IF('VIM-Incidents_20250724'!E6<>'VIM-Incidents_20250731'!E6,"Difference","OK") -> OK | F6: =IF('VIM-Incidents_20250724'!F6<>'VIM-Incidents_20250731'!F6,"Difference","OK") -> OK | G6: =IF('VIM-Incidents_20250724'!G6<>'VIM-Incidents_20250731'!G6,"Difference","OK") -> OK | H6: =IF('VIM-Incidents_20250724'!H6<>'VIM-Incidents_20250731'!H6,"Difference","OK") -> OK | ... S6: =IF('VIM-Incidents_20250724'!S6<>'VIM-Incidents_20250731'!S6,"Difference","OK") -> OK
A7: =IF('VIM-Incidents_20250724'!A7<>'VIM-Incidents_20250731'!A7,"Difference","OK") -> OK | B7: =IF('VIM-Incidents_20250724'!B7<>'VIM-Incidents_20250731'!B7,"Difference","OK") -> OK | C7: =IF('VIM-Incidents_20250724'!C7<>'VIM-Incidents_20250731'!C7,"Difference","OK") -> OK | D7: =IF('VIM-Incidents_20250724'!D7<>'VIM-Incidents_20250731'!D7,"Difference","OK") -> OK | E7: =IF('VIM-Incidents_20250724'!E7<>'VIM-Incidents_20250731'!E7,"Difference","OK") -> OK | F7: =IF('VIM-Incidents_20250724'!F7<>'VIM-Incidents_20250731'!F7,"Difference","OK") -> OK | G7: =IF('VIM-Incidents_20250724'!G7<>'VIM-Incidents_20250731'!G7,"Difference","OK") -> OK | H7: =IF('VIM-Incidents_20250724'!H7<>'VIM-Incidents_20250731'!H7,"Difference","OK") -> OK | ... S7: =IF('VIM-Incidents_20250724'!S7<>'VIM-Incidents_20250731'!S7,"Difference","OK") -> OK
A8: =IF('VIM-Incidents_20250724'!A8<>'VIM-Incidents_20250731'!A8,"Difference","OK") -> OK | B8: =IF('VIM-Incidents_20250724'!B8<>'VIM-Incidents_20250731'!B8,"Difference","OK") -> OK | C8: =IF('VIM-Incidents_20250724'!C8<>'VIM-Incidents_20250731'!C8,"Difference","OK") -> OK | D8: =IF('VIM-Incidents_20250724'!D8<>'VIM-Incidents_20250731'!D8,"Difference","OK") -> OK | E8: =IF('VIM-Incidents_20250724'!E8<>'VIM-Incidents_20250731'!E8,"Difference","OK") -> OK | F8: =IF('VIM-Incidents_20250724'!F8<>'VIM-Incidents_20250731'!F8,"Difference","OK") -> OK | G8: =IF('VIM-Incidents_20250724'!G8<>'VIM-Incidents_20250731'!G8,"Difference","OK") -> OK | H8: =IF('VIM-Incidents_20250724'!H8<>'VIM-Incidents_20250731'!H8,"Difference","OK") -> OK | ... S8: =IF('VIM-Incidents_20250724'!S8<>'VIM-Incidents_20250731'!S8,"Difference","OK") -> OK
A9: =IF('VIM-Incidents_20250724'!A9<>'VIM-Incidents_20250731'!A9,"Difference","OK") -> OK | B9: =IF('VIM-Incidents_20250724'!B9<>'VIM-Incidents_20250731'!B9,"Difference","OK") -> OK | C9: =IF('VIM-Incidents_20250724'!C9<>'VIM-Incidents_20250731'!C9,"Difference","OK") -> OK | D9: =IF('VIM-Incidents_20250724'!D9<>'VIM-Incidents_20250731'!D9,"Difference","OK") -> OK | E9: =IF('VIM-Incidents_20250724'!E9<>'VIM-Incidents_20250731'!E9,"Difference","OK") -> OK | F9: =IF('VIM-Incidents_20250724'!F9<>'VIM-Incidents_20250731'!F9,"Difference","OK") -> OK | G9: =IF('VIM-Incidents_20250724'!G9<>'VIM-Incidents_20250731'!G9,"Difference","OK") -> OK | H9: =IF('VIM-Incidents_20250724'!H9<>'VIM-Incidents_20250731'!H9,"Difference","OK") -> OK | ... S9: =IF('VIM-Incidents_20250724'!S9<>'VIM-Incidents_20250731'!S9,"Difference","OK") -> OK
A10: =IF('VIM-Incidents_20250724'!A10<>'VIM-Incidents_20250731'!A10,"Difference","OK") -> OK | B10: =IF('VIM-Incidents_20250724'!B10<>'VIM-Incidents_20250731'!B10,"Difference","OK") -> OK | C10: =IF('VIM-Incidents_20250724'!C10<>'VIM-Incidents_20250731'!C10,"Difference","OK") -> OK | D10: =IF('VIM-Incidents_20250724'!D10<>'VIM-Incidents_20250731'!D10,"Difference","OK") -> OK | E10: =IF('VIM-Incidents_20250724'!E10<>'VIM-Incidents_20250731'!E10,"Difference","OK") -> OK | F10: =IF('VIM-Incidents_20250724'!F10<>'VIM-Incidents_20250731'!F10,"Difference","OK") -> OK | G10: =IF('VIM-Incidents_20250724'!G10<>'VIM-Incidents_20250731'!G10,"Difference","OK") -> OK | H10: =IF('VIM-Incidents_20250724'!H10<>'VIM-Incidents_20250731'!H10,"Difference","OK") -> OK | ... S10: =IF('VIM-Incidents_20250724'!S10<>'VIM-Incidents_20250731'!S10,"Difference","OK") -> OK
A11: =IF('VIM-Incidents_20250724'!A11<>'VIM-Incidents_20250731'!A11,"Difference","OK") -> OK | B11: =IF('VIM-Incidents_20250724'!B11<>'VIM-Incidents_20250731'!B11,"Difference","OK") -> OK | C11: =IF('VIM-Incidents_20250724'!C11<>'VIM-Incidents_20250731'!C11,"Difference","OK") -> OK | D11: =IF('VIM-Incidents_20250724'!D11<>'VIM-Incidents_20250731'!D11,"Difference","OK") -> OK | E11: =IF('VIM-Incidents_20250724'!E11<>'VIM-Incidents_20250731'!E11,"Difference","OK") -> OK | F11: =IF('VIM-Incidents_20250724'!F11<>'VIM-Incidents_20250731'!F11,"Difference","OK") -> OK | G11: =IF('VIM-Incidents_20250724'!G11<>'VIM-Incidents_20250731'!G11,"Difference","OK") -> OK | H11: =IF('VIM-Incidents_20250724'!H11<>'VIM-Incidents_20250731'!H11,"Difference","OK") -> OK | ... S11: =IF('VIM-Incidents_20250724'!S11<>'VIM-Incidents_20250731'!S11,"Difference","OK") -> OK
A12: =IF('VIM-Incidents_20250724'!A12<>'VIM-Incidents_20250731'!A12,"Difference","OK") -> OK | B12: =IF('VIM-Incidents_20250724'!B12<>'VIM-Incidents_20250731'!B12,"Difference","OK") -> OK | C12: =IF('VIM-Incidents_20250724'!C12<>'VIM-Incidents_20250731'!C12,"Difference","OK") -> OK | D12: =IF('VIM-Incidents_20250724'!D12<>'VIM-Incidents_20250731'!D12,"Difference","OK") -> OK | E12: =IF('VIM-Incidents_20250724'!E12<>'VIM-Incidents_20250731'!E12,"Difference","OK") -> OK | F12: =IF('VIM-Incidents_20250724'!F12<>'VIM-Incidents_20250731'!F12,"Difference","OK") -> OK | G12: =IF('VIM-Incidents_20250724'!G12<>'VIM-Incidents_20250731'!G12,"Difference","OK") -> OK | H12: =IF('VIM-Incidents_20250724'!H12<>'VIM-Incidents_20250731'!H12,"Difference","OK") -> OK | ... S12: =IF('VIM-Incidents_20250724'!S12<>'VIM-Incidents_20250731'!S12,"Difference","OK") -> OK
... A210: =IF('VIM-Incidents_20250724'!A210<>'VIM-Incidents_20250731'!A210,"Difference","OK") -> OK | B210: =IF('VIM-Incidents_20250724'!B210<>'VIM-Incidents_20250731'!B210,"Difference","OK") -> OK | C210: =IF('VIM-Incidents_20250724'!C210<>'VIM-Incidents_20250731'!C210,"Difference","OK") -> OK | D210: =IF('VIM-Incidents_20250724'!D210<>'VIM-Incidents_20250731'!D210,"Difference","OK") -> OK | E210: =IF('VIM-Incidents_20250724'!E210<>'VIM-Incidents_20250731'!E210,"Difference","OK") -> OK | F210: =IF('VIM-Incidents_20250724'!F210<>'VIM-Incidents_20250731'!F210,"Difference","OK") -> OK | G210: =IF('VIM-Incidents_20250724'!G210<>'VIM-Incidents_20250731'!G210,"Difference","OK") -> OK | H210: =IF('VIM-Incidents_20250724'!H210<>'VIM-Incidents_20250731'!H210,"Difference","OK") -> OK | ... S210: =IF('VIM-Incidents_20250724'!S210<>'VIM-Incidents_20250731'!S210,"Difference","OK") -> OK

Sheet VIM-Incidents_W24
A1: ID | B1: FutureNow Ticket | C1: External ID | D1: ARE | E1: Created On | F1: Due by | G1: Reported By | H1: Message Processor | I1: Last Changed on | J1: Last Changed By | K1: Priority | L1: Status | M1: Description | N1: Support Team | O1: System ID | Q1: Open Days | R1: Open 7D+ | S1: Open 30D+
A2: 6000127070 | B2: INC41987224 | D2: 5975 | E2: 45663 | G2: Lenka Michalusova (GBS CEE P2P CZ AP 2 4 / Z002HBHR) | H2: Ulrich Rauch / 81739 Muenchen | I2: 45727 | J2: RFC_FITS | K2: 4: Low | L2: Confirm_Closed | M2: VIM- missing tax code | N2: SIE_S4P_RS Siemens S4P - Readsoft | Q2: =DATEDIF(E2,I2,"d") -> 64 | R2: =IF($Q2>7,1,0) -> 1 | S2: =IF($Q2>30,1,0) -> 1
A3: 6000127209 | B3: INC41997245 | D3: 5975 | E3: 45664 | G3: Simon Kostovski (GBS CEE P2P CZ AP 3 2 / Z003DW1N) | H3: Albert Galek | I3: 45673 | J3: RFC_FITS | K3: 3: Medium | L3: Confirm_Closed | M3: INC41861079 not solved but it was closed | N3: SIE_S4P_RS Siemens S4P - Readsoft | Q3: =DATEDIF(E3,I3,"d") -> 9 | R3: =IF($Q3>7,1,0) -> 1 | S3: =IF($Q3>30,1,0) -> 0
A4: 6000127632 | B4: INC42022656 | D4: 5975 | E4: 45667 | G4: Barbora Struskova (GBS CEE P2P CZ AP 2 4 / Z002HZ1U) | H4: Ilona Splichalova | I4: 45679 | J4: RFC_FITS | K4: 4: Low | L4: Confirm_Closed | M4: automatic text | N4: SIE_S4P_RS Siemens S4P - Readsoft | Q4: =DATEDIF(E4,I4,"d") -> 12 | R4: =IF($Q4>7,1,0) -> 1 | S4: =IF($Q4>30,1,0) -> 0
A5: 6000128352 | D5: 3003 | E5: 45674 | G5: Ilona Splichalova (DI IT ERP CZ FICO / Z002Z2VA) | H5: Albert Galek | I5: 45688 | J5: SAP SOLUTION MANAGER S1A | K5: 3: Medium | L5: Confirm_Closed | M5: DP 2807 in S4P: please check the status | N5: SIE_S4P_RS Siemens S4P - Readsoft | Q5: =DATEDIF(E5,I5,"d") -> 14 | R5: =IF($Q5>7,1,0) -> 1 | S5: =IF($Q5>30,1,0) -> 0
A6: 6000128500 | B6: INC42075263 | D6: 7092 | E6: 45677 | G6: Lena Osterhus (CE SEC TPC / Z001MA1B) | H6: Ilona Splichalova | I6: 45684 | J6: RFC_FITS | K6: 4: Low | L6: Confirm_Closed | M6: Falsche Emailadresse bei Readsoft/ WebCycle | N6: SIE_S4P_RS Siemens S4P - Readsoft | Q6: =DATEDIF(E6,I6,"d") -> 7 | R6: =IF($Q6>7,1,0) -> 0 | S6: =IF($Q6>30,1,0) -> 0
A7: 6000128546 | B7: INC42077895 | D7: SRE | E7: 45677 | G7: Zdenek Cifka (GBS CEE P2P CZ AP 2 3 / Z003JPCS) | H7: Ilona Splichalova | I7: 45805 | J7: Ulrich Rauch | K7: 3: Medium | L7: In Process | M7: VIM ID's 2391 and 2623 - after posting the payment block was'nt entered and approval workflow was'nt started | N7: SIE_S4P_RS Siemens S4P - Readsoft | Q7: =DATEDIF(E7,TODAY(),"d") -> 330 | R7: =IF($Q7>7,1,0) -> 1 | S7: =IF($Q7>30,1,0) -> 1
A8: 6000128759 | B8: INC42093959 | D8: 7092 | E8: 45679 | G8: Andreas Mengele (MAP DF&PCM PCM / Z001THRJ) | H8: Ilona Splichalova | I8: 45686 | J8: RFC_FITS | K8: 4: Low | L8: Confirm_Closed | M8: Umstellung der Rechte von Susanne Spiegl auf Philipp Rath | N8: SIE_S4P_RS Siemens S4P - Readsoft | Q8: =DATEDIF(E8,TODAY(),"d") -> 328 | R8: =IF($Q8>7,1,0) -> 1 | S8: =IF($Q8>30,1,0) -> 1
A9: 6000129022 | B9: INC42106952 | D9: 5975 | E9: 45680 | G9: Renata Staricna (GBS CEE P2P CZ AP 2 4 / Z0046K6B) | H9: Ilona Splichalova | I9: 45705 | J9: RFC_FITS | K9: 4: Low | L9: Confirm_Closed | M9: Reminder - automatic answers | N9: SIE_S4P_RS Siemens S4P - Readsoft | Q9: =DATEDIF(E9,TODAY(),"d") -> 327 | R9: =IF($Q9>7,1,0) -> 1 | S9: =IF($Q9>30,1,0) -> 1
A10: 6000129245 | B10: INC42120663 | D10: 7092 | E10: 45684 | G10: Veronika Andres (IT ECP FPS T&CS / Z0029JJZ) | H10: Ilona Splichalova | I10: 45691 | J10: RFC_FITS | K10: 4: Low | L10: Confirm_Closed | M10: WebCycle User locked | N10: SIE_S4P_RS Siemens S4P - Readsoft | Q10: =DATEDIF(E10,TODAY(),"d") -> 323 | R10: =IF($Q10>7,1,0) -> 1 | S10: =IF($Q10>30,1,0) -> 1
A11: 6000129304 | B11: INC42122188 | D11: SRE | E11: 45684 | G11: Tobias Moest (SRE FIN AR 2 / Z000F12V) | H11: Albert Galek | I11: 45693 | J11: RFC_FITS | K11: 4: Low | L11: Confirm_Closed | M11: S4P 100 - VIM: Vorgang aus Klärungs-WF nicht vorhanden | N11: SIE_S4P_RS Siemens S4P - Readsoft | Q11: =DATEDIF(E11,TODAY(),"d") -> 323 | R11: =IF($Q11>7,1,0) -> 1 | S11: =IF($Q11>30,1,0) -> 1
A12: 6000129653 | D12: 3003 | E12: 45686 | G12: Ilona Splichalova (DI IT ERP CZ FICO / Z002Z2VA) | H12: Ilona Splichalova | I12: 45782 | J12: SAP SOLUTION MANAGER S1A | K12: 3: Medium | L12: Confirm_Closed | M12: VIM 2756 und 2774 - Error by 3 step approval WF by Construction Invoices | N12: SIE_S4P_RS Siemens S4P - Readsoft | Q12: =DATEDIF(E12,TODAY(),"d") -> 321 | R12: =IF($Q12>7,1,0) -> 1 | S12: =IF($Q12>30,1,0) -> 1
A13: 6000129990 | B13: INC42154604 | D13: SRE | E13: 45688 | G13: Zdenek Cifka (GBS CEE P2P CZ AP 2 3 / Z003JPCS) | H13: Albert Galek | I13: 45699 | J13: RFC_FITS | K13: 3: Medium | L13: Confirm_Closed | M13: Is not possible to start the approval workflow for VIM ID 2515 | N13: SIE_S4P_RS Siemens S4P - Readsoft | Q13: =DATEDIF(E13,TODAY(),"d") -> 319 | R13: =IF($Q13>7,1,0) -> 1 | S13: =IF($Q13>30,1,0) -> 1
A14: 6000130122 | B14: INC42161605 | D14: 3014 | E14: 45691 | G14: Pompilia Bianca Trifa (DI MC GMC MF-EWN PU-BUZ FIN LOG 1-2 / | H14: Ulrich Rauch / 81739 Muenchen | I14: 45708 | J14: RFC_FITS | K14: 3: Medium | L14: Confirm_Closed | M14: S4P VIM - Invoices in Approval steps (direct materials) not visible to the approver | N14: SIE_S4P_RS Siemens S4P - Readsoft | Q14: 38 | R14: =IF($Q14>7,1,0) -> 1 | S14: =IF($Q14>30,1,0) -> 1
A15: 6000130131 | B15: INC42161726 | D15: 3014 | E15: 45691 | G15: Andreea Laura Boran (DI MC GMC MF-EWN PU-BUZ FIN LOG 1-2 / Z | H15: Ulrich Rauch / 81739 Muenchen | I15: 45708 | J15: RFC_FITS | K15: 3: Medium | L15: Confirm_Closed | M15: S4P - VIM error in invoice approval | N15: SIE_S4P_RS Siemens S4P - Readsoft | Q15: =DATEDIF(E15,TODAY(),"d") -> 316 | R15: =IF($Q15>7,1,0) -> 1 | S15: =IF($Q15>30,1,0) -> 1
A16: 6000130842 | B16: INC42203263 | D16: 3003 | E16: 45698 | G16: Helge Preiss (SRE DP PM EU / Z001WZ3K) | H16: Ulrich Rauch / 81739 Muenchen | I16: 45824 | J16: Ulrich Rauch | K16: 3: Medium | L16: Proposed Solution | M16: S4P VIM FIORI Approval Invoice Management Fehlermeldung | N16: SIE_S4P_RS Siemens S4P - Readsoft | Q16: =DATEDIF(E16,TODAY(),"d") -> 309 | R16: =IF($Q16>7,1,0) -> 1 | S16: =IF($Q16>30,1,0) -> 1
A17: 6000130889 | B17: INC42205466 | D17: 7092 | E17: 45698 | G17: Laura Hochwind (IT ECP FPS AP1 / Z003NVNW) | H17: Ulrich Rauch / 81739 Muenchen | I17: 45705 | J17: RFC_FITS | K17: 3: Medium | L17: Confirm_Closed | M17: Add Substitute for Webcycle Readsoft | N17: SIE_S4P_RS Siemens S4P - Readsoft | Q17: =DATEDIF(E17,TODAY(),"d") -> 309 | R17: =IF($Q17>7,1,0) -> 1 | S17: =IF($Q17>30,1,0) -> 1
A18: 6000131438 | B18: INC42234456 | D18: 3003 | E18: 45701 | G18: Mario Beck (SRE DP PM EU / Z00109RY) | H18: Mr. Ramesh Itamsetti | I18: 45824 | J18: Ulrich Rauch | K18: 3: Medium | L18: Proposed Solution | M18: S4P 100 VIM - Fehlermeldung bei WF-Freigabe | N18: SIE_S4P_RS Siemens S4P - Readsoft | Q18: =DATEDIF(E18,TODAY(),"d") -> 306 | R18: =IF($Q18>7,1,0) -> 1 | S18: =IF($Q18>30,1,0) -> 1
A19: 6000131514 | D19: 7092 | E19: 45702 | G19: Ulrich Rauch (IT ECP ERP-CP ARC2 / Z00060NO) | H19: Ulrich Rauch / 81739 Muenchen | I19: 45723 | J19: SAP SOLUTION MANAGER S1A | K19: 3: Medium | L19: Confirm_Closed | M19: VIM: VIM Authorization issue in Exceptions App (mid-term solution) | N19: SIE_S4P_RS Siemens S4P - Readsoft | Q19: =DATEDIF(E19,TODAY(),"d") -> 305 | R19: =IF($Q19>7,1,0) -> 1 | S19: =IF($Q19>30,1,0) -> 1
A20: 6000131715 | B20: INC42252236 | D20: 5975 | E20: 45705 | G20: Pavel Mego (GBS CEE P2P CZ AP 2 4 / Z001SCDJ) | H20: Ulrich Rauch / 81739 Muenchen | I20: 45713 | J20: RFC_FITS | K20: 4: Low | L20: Confirm_Closed | M20: duplicity check | N20: SIE_S4P_RS Siemens S4P - Readsoft | Q20: =DATEDIF(E20,TODAY(),"d") -> 302 | R20: =IF($Q20>7,1,0) -> 1 | S20: =IF($Q20>30,1,0) -> 1
A21: 6000132000 | B21: INC42270698 | D21: SRE | E21: 45707 | G21: Zdenek Cifka (GBS CEE P2P CZ AP 2 3 / Z003JPCS) | H21: Albert Galek | I21: 45735 | J21: RFC_FITS | K21: 3: Medium | L21: Confirm_Closed | M21: In VIM it is not possible to post the recurring documents, which contain multiple Profit Centers - VIM ID 3988 and 4340 | N21: SIE_S4P_RS Siemens S4P - Readsoft | Q21: =DATEDIF(E21,TODAY(),"d") -> 300 | R21: =IF($Q21>7,1,0) -> 1 | S21: =IF($Q21>30,1,0) -> 1
A22: 6000132651 | B22: INC42313692 | D22: 3003 | E22: 45714 | G22: Mario Beck (SRE DP PM EU / Z00109RY) | H22: Albert Galek | I22: 45723 | J22: RFC_FITS | K22: 4: Low | L22: Confirm_Closed | M22: S4P 100 VIM - #2777 can't be approved (new error message) | N22: SIE_S4P_RS Siemens S4P - Readsoft | Q22: =DATEDIF(E22,TODAY(),"d") -> 293 | R22: =IF($Q22>7,1,0) -> 1 | S22: =IF($Q22>30,1,0) -> 1
A23: 6000133013 | B23: INC42339428 | D23: 5975 | E23: 45719 | G23: Jitka Krnavkova (GBS CEE P2P CZ AP 2 4 / Z002HBHS) | H23: Ilona Splichalova | I23: 45734 | J23: RFC_FITS | K23: 4: Low | L23: Confirm_Closed | M23: Add user to ICFR group_READSOFT | N23: SIE_S4P_RS Siemens S4P - Readsoft | Q23: =DATEDIF(E23,TODAY(),"d") -> 288 | R23: =IF($Q23>7,1,0) -> 1 | S23: =IF($Q23>30,1,0) -> 1
A24: 6000133061 | B24: INC42342340 | D24: SRE | E24: 45719 | G24: Zdenek Cifka (GBS CEE P2P CZ AP 2 3 / Z003JPCS) | H24: Ilona Splichalova | I24: 45735 | J24: RFC_FITS | K24: 3: Medium | L24: Confirm_Closed | M24: VIM ID 1785 - approval workflow wasn't started but nevertheless is situated in VIM WP in My pending section | N24: SIE_S4P_RS Siemens S4P - Readsoft | Q24: =DATEDIF(E24,TODAY(),"d") -> 288 | R24: =IF($Q24>7,1,0) -> 1 | S24: =IF($Q24>30,1,0) -> 1
A25: 6000133063 | B25: INC42342645 | D25: 5220 | E25: 45719 | G25: Simona-Elena Kovar (CF R EEA PP PI / Z0046E1M) | H25: Ilona Splichalova | I25: 45778 | J25: RFC_FITS | K25: 4: Low | L25: Confirm_Closed | M25: GR posted, the payment block was removed in the background -> VIM workflow NOT completed | N25: SIE_S4P_RS Siemens S4P - Readsoft | Q25: =DATEDIF(E25,TODAY(),"d") -> 288 | R25: =IF($Q25>7,1,0) -> 1 | S25: =IF($Q25>30,1,0) -> 1
A26: 6000133075 | B26: INC42342669 | D26: 5220 | E26: 45719 | G26: Simona-Elena Kovar (CF R EEA PP PI / Z0046E1M) | H26: Albert Galek | I26: 45758 | J26: RFC_FITS | K26: 4: Low | L26: Confirm_Closed | M26: the document requires a technical approval although there is no price or quantity deviation | N26: SIE_S4P_RS Siemens S4P - Readsoft | Q26: =DATEDIF(E26,TODAY(),"d") -> 288 | R26: =IF($Q26>7,1,0) -> 1 | S26: =IF($Q26>30,1,0) -> 1
A27: 6000133085 | D27: 7092 | E27: 45719 | G27: Ulrich Rauch (IT ECP ERP-CP ARC2 / Z00060NO) | H27: Albert Galek | I27: 45731 | J27: SAP SOLUTION MANAGER S1A | K27: 3: Medium | L27: Confirm_Closed | M27: VIM: direct material PO: not able to choose non preferred approver | N27: SIE_S4P_RS Siemens S4P - Readsoft | Q27: =DATEDIF(E27,TODAY(),"d") -> 288 | R27: =IF($Q27>7,1,0) -> 1 | S27: =IF($Q27>30,1,0) -> 1
A28: 6000133086 | D28: 7092 | E28: 45719 | G28: Ulrich Rauch (IT ECP ERP-CP ARC2 / Z00060NO) | H28: Albert Galek | I28: 45773 | J28: SAP SOLUTION MANAGER S1A | K28: 3: Medium | L28: Confirm_Closed | M28: VIM ID 1785 and 5352 - approval workflow wasn't started but nevertheless is s | N28: SIE_S4P_RS Siemens S4P - Readsoft | Q28: =DATEDIF(E28,TODAY(),"d") -> 288 | R28: =IF($Q28>7,1,0) -> 1 | S28: =IF($Q28>30,1,0) -> 1
A29: 6000133087 | D29: 7092 | E29: 45719 | G29: Ulrich Rauch (IT ECP ERP-CP ARC2 / Z00060NO) | H29: Ilona Splichalova | I29: 45807 | J29: SAP SOLUTION MANAGER S1A | K29: 3: Medium | L29: Confirm_Closed | M29: VIM: different statuses in VIM Workplace and VIM Analytics | N29: SIE_S4P_RS Siemens S4P - Readsoft | Q29: =DATEDIF(E29,TODAY(),"d") -> 288 | R29: =IF($Q29>7,1,0) -> 1 | S29: =IF($Q29>30,1,0) -> 1
A30: 6000133442 | D30: 3003 | E30: 45722 | G30: Ilona Splichalova (DI IT ERP CZ FICO / Z002Z2VA) | H30: Ilona Splichalova | I30: 45786 | J30: SAP SOLUTION MANAGER S1A | K30: 3: Medium | L30: Confirm_Closed | M30: In VIM is not possible to cancel the invoice - DP 4288 | N30: SIE_S4P_RS Siemens S4P - Readsoft | Q30: =DATEDIF(E30,TODAY(),"d") -> 285 | R30: =IF($Q30>7,1,0) -> 1 | S30: =IF($Q30>30,1,0) -> 1
A31: 6000133644 | B31: INC42377517 | D31: 3014 | E31: 45723 | G31: Simon Kostovski (GBS CEE P2P CZ AP PE 2 / Z003DW1N) | H31: Albert Galek | I31: 45789 | J31: Ilona Splichalova | K31: 3: Medium | L31: In Process | M31: S4P Please adjust the VAT date to be identical with the invoice date for Company code 3014 | N31: SIE_S4P_RS Siemens S4P - Readsoft | Q31: =DATEDIF(E31,TODAY(),"d") -> 284 | R31: =IF($Q31>7,1,0) -> 1 | S31: =IF($Q31>30,1,0) -> 1
A32: 6000133647 | B32: INC42377569 | D32: 5975 | E32: 45723 | G32: Jan Binder (GBS CEE P2P CZ AP 2 2 / Z00435WC) | H32: Ilona Splichalova | I32: 45733 | J32: RFC_FITS | K32: 4: Low | L32: Confirm_Closed | M32: Receipt of invoices and posting in a different month/period. | N32: SIE_S4P_RS Siemens S4P - Readsoft | Q32: =DATEDIF(E32,TODAY(),"d") -> 284 | R32: =IF($Q32>7,1,0) -> 1 | S32: =IF($Q32>30,1,0) -> 1
A33: 6000133780 | B33: INC42386307 | D33: 3014 | E33: 45726 | G33: Andrei Vulpescu (DI MC GMC MF-EWN PU-BUZ FIN / Z00172BA) | H33: Albert Galek | I33: 45741 | J33: RFC_FITS | K33: 4: Low | L33: Confirm_Closed | M33: I cannot approve invoice release | N33: SIE_S4P_RS Siemens S4P - Readsoft | Q33: =DATEDIF(E33,TODAY(),"d") -> 281 | R33: =IF($Q33>7,1,0) -> 1 | S33: =IF($Q33>30,1,0) -> 1
A34: 6000133782 | B34: INC42386439 | D34: SRE | E34: 45726 | G34: Zdenek Cifka (GBS CEE P2P CZ AP 2 3 / Z003JPCS) | H34: Albert Galek | I34: 45735 | J34: RFC_FITS | K34: 3: Medium | L34: Confirm_Closed | M34: At VIM ID's 2977 and 1961 it's not possible to recall the approval workflow because they are situated in VIM WP in My co | N34: SIE_S4P_RS Siemens S4P - Readsoft | Q34: =DATEDIF(E34,TODAY(),"d") -> 281 | R34: =IF($Q34>7,1,0) -> 1 | S34: =IF($Q34>30,1,0) -> 1
A35: 6000133815 | B35: INC42387821 | D35: SRE | E35: 45726 | G35: Zdenek Cifka (GBS CEE P2P CZ AP 2 3 / Z003JPCS) | H35: Albert Galek | I35: 45748 | J35: RFC_FITS | K35: 3: Medium | L35: Confirm_Closed | M35: VIM ID 5033 - it's not possible to start the approval workflow manually for the specific person. | N35: SIE_S4P_RS Siemens S4P - Readsoft | Q35: =DATEDIF(E35,TODAY(),"d") -> 281 | R35: =IF($Q35>7,1,0) -> 1 | S35: =IF($Q35>30,1,0) -> 1
A36: 6000133897 | D36: 5975 | E36: 45727 | G36: Ilona Splichalova (DI IT ERP CZ FICO / Z002Z2VA) | H36: Albert Galek | I36: 45751 | J36: SAP SOLUTION MANAGER S1A | K36: 3: Medium | L36: Confirm_Closed | M36: VIM Table U-date Clarifications | N36: SIE_S4P_RS Siemens S4P - Readsoft | Q36: =DATEDIF(E36,TODAY(),"d") -> 280 | R36: =IF($Q36>7,1,0) -> 1 | S36: =IF($Q36>30,1,0) -> 1
A37: 6000134052 | B37: INC42401853 | D37: 3014 | E37: 45728 | G37: Ivana Tomisova (GBS CEE P2P CZ AP 3 2 / Z004PK7A) | H37: Mr. Silambarasan Vasu | I37: 45819 | K37: 4: Low | L37: Forwarded | M37: 3014 - ICC invoice not visible in VIM workplace | N37: MM - Materials Management | Q37: =DATEDIF(E37,TODAY(),"d") -> 279 | R37: =IF($Q37>7,1,0) -> 1 | S37: =IF($Q37>30,1,0) -> 1
A38: 6000134157 | B38: INC42406593 | D38: 5975 | E38: 45729 | G38: Pavel Mego (GBS CEE P2P CZ AP 2 4 / Z001SCDJ) | H38: Ilona Splichalova | I38: 45737 | J38: RFC_FITS | K38: 4: Low | L38: Confirm_Closed | M38: Stucked Webcycle | N38: SIE_S4P_RS Siemens S4P - Readsoft | Q38: =DATEDIF(E38,TODAY(),"d") -> 278 | R38: =IF($Q38>7,1,0) -> 1 | S38: =IF($Q38>30,1,0) -> 1
A39: 6000134167 | D39: 7092 | E39: 45729 | G39: Muskan Khanum Nagad (IT ECP ERP-CP / Z0053CPH) | H39: Albert Galek | I39: 45792 | J39: SAP SOLUTION MANAGER S1A | K39: 3: Medium | L39: Confirm_Closed | M39: Abap programming error in S4P | N39: SIE_S4P_RS Siemens S4P - Readsoft | Q39: =DATEDIF(E39,TODAY(),"d") -> 278 | R39: =IF($Q39>7,1,0) -> 1 | S39: =IF($Q39>30,1,0) -> 1
A40: 6000134304 | B40: INC42414880 | D40: 7011 | E40: 45729 | G40: Cosmin-Ovidiu Sarbu (DI MC GMC MF-EWN PU-BUZ FIN BC / Z0026A | H40: Ilona Splichalova | I40: 45782 | J40: RFC_FITS | K40: 4: Low | L40: Confirm_Closed | M40: Approval of invoices in VIM according to SAT | N40: SIE_S4P_RS Siemens S4P - Readsoft | Q40: =DATEDIF(E40,TODAY(),"d") -> 278 | R40: =IF($Q40>7,1,0) -> 1 | S40: =IF($Q40>30,1,0) -> 1
A41: 6000134423 | B41: INC42420961 | D41: 5975 | E41: 45730 | G41: Pavel Mego (GBS CEE P2P CZ AP 2 4 / Z001SCDJ) | H41: Ilona Splichalova | I41: 45748 | J41: RFC_FITS | K41: 4: Low | L41: Confirm_Closed | M41: readsoft messages | N41: SIE_S4P_RS Siemens S4P - Readsoft | Q41: =DATEDIF(E41,TODAY(),"d") -> 277 | R41: =IF($Q41>7,1,0) -> 1 | S41: =IF($Q41>30,1,0) -> 1
A42: 6000134460 | B42: INC42422286 | D42: 5975 | E42: 45730 | G42: Ivana Tomisova (GBS CEE P2P CZ AP 3 2 / Z004PK7A) | H42: Albert Galek | I42: 45748 | J42: RFC_FITS | K42: 4: Low | L42: Confirm_Closed | M42: 3014 - posting of inovices on mutiple POs | N42: SIE_S4P_RS Siemens S4P - Readsoft | Q42: =DATEDIF(E42,TODAY(),"d") -> 277 | R42: =IF($Q42>7,1,0) -> 1 | S42: =IF($Q42>30,1,0) -> 1
A43: 6000134543 | B43: INC42429350 | D43: 3014 | E43: 45733 | G43: Cristina Mariana Vega (DI MC GMC MF-EWN PU-BUZ FIN LOG / Z00 | H43: Albert Galek | I43: 45754 | J43: RFC_FITS | K43: 2: High | L43: Confirm_Closed | M43: Approval invoice not possible in Approval invoice Management app | N43: SIE_S4P_RS Siemens S4P - Readsoft | Q43: =DATEDIF(E43,TODAY(),"d") -> 274 | R43: =IF($Q43>7,1,0) -> 1 | S43: =IF($Q43>30,1,0) -> 1
A44: 6000134731 | B44: INC42441623 | D44: 5975 | E44: 45734 | G44: Pavel Mego (GBS CEE P2P CZ AP 2 4 / Z001SCDJ) | H44: Ilona Splichalova | I44: 45743 | J44: RFC_FITS | K44: 4: Low | L44: Confirm_Closed | M44: Webcycles with error | N44: SIE_S4P_RS Siemens S4P - Readsoft | Q44: =DATEDIF(E44,TODAY(),"d") -> 273 | R44: =IF($Q44>7,1,0) -> 1 | S44: =IF($Q44>30,1,0) -> 1
A45: 6000134816 | B45: INC42448216 | D45: 5220 | E45: 45735 | G45: Simona-Elena Kovar (CF R EEA PP PI / Z0046E1M) | H45: Ilona Splichalova | I45: 45762 | J45: RFC_FITS | K45: 4: Low | L45: Confirm_Closed | M45: Invoice in approval step but not visible in Approval Invoice Management application | N45: SIE_S4P_RS Siemens S4P - Readsoft | Q45: =DATEDIF(E45,TODAY(),"d") -> 272 | R45: =IF($Q45>7,1,0) -> 1 | S45: =IF($Q45>30,1,0) -> 1
A46: 6000134850 | B46: INC42449485 | D46: 3014 | E46: 45735 | G46: Juliana Batya Dora Ciupe (DI MC GMC MF-EWN PU-BUZ FIN BC / Z | H46: Albert Galek | I46: 45761 | J46: RFC_FITS | K46: 3: Medium | L46: Confirm_Closed | M46: Invoice with IDoc quantity incorect - issue in approval process | N46: SIE_S4P_RS Siemens S4P - Readsoft | Q46: =DATEDIF(E46,TODAY(),"d") -> 272 | R46: =IF($Q46>7,1,0) -> 1 | S46: =IF($Q46>30,1,0) -> 1
A47: 6000134958 | B47: INC42458439 | D47: 3003 | E47: 45736 | G47: Pavla Tothova (GBS CEE P2P CZ AP 2 3 / Z002NYHT) | H47: Ilona Splichalova | I47: 45750 | J47: RFC_FITS | K47: 3: Medium | L47: Confirm_Closed | M47: S4P/AUN 3003 VIM ID 5424 - the credit note was incorrectly booked as an invoice, nevertheless is situated in VIM WP in | N47: SIE_S4P_RS Siemens S4P - Readsoft | Q47: =DATEDIF(E47,TODAY(),"d") -> 271 | R47: =IF($Q47>7,1,0) -> 1 | S47: =IF($Q47>30,1,0) -> 1
A48: 6000135155 | B48: INC42469024 | D48: 7092 | E48: 45737 | G48: Dirk Eska (IT DF COL UC / Z0000X0D) | H48: Ilona Splichalova | I48: 45757 | J48: RFC_FITS | K48: 4: Low | L48: Confirm_Closed | M48: S4-line Service - Kein Zugang zum Webcycle Tool mehr | N48: SIE_S4P_RS Siemens S4P - Readsoft | Q48: =DATEDIF(E48,TODAY(),"d") -> 270 | R48: =IF($Q48>7,1,0) -> 1 | S48: =IF($Q48>30,1,0) -> 1
A49: 6000135247 | D49: SRE | E49: 45740 | G49: Ilona Splichalova (DI IT ERP CZ FICO / Z002Z2VA) | H49: Ilona Splichalova | I49: 45779 | J49: SAP SOLUTION MANAGER S1A | K49: 3: Medium | L49: Confirm_Closed | M49: VIM: Issue with items incorrectly placed in My Completed tab | N49: SIE_S4P_RS Siemens S4P - Readsoft | Q49: =DATEDIF(E49,TODAY(),"d") -> 267 | R49: =IF($Q49>7,1,0) -> 1 | S49: =IF($Q49>30,1,0) -> 1
A50: 6000135249 | B50: INC42467829 | D50: 3014 | E50: 45740 | G50: Andrei Vulpescu (DI MC GMC MF-EWN PU-BUZ FIN / Z00172BA) | H50: Ilona Splichalova | I50: 45782 | J50: RFC_FITS | K50: 3: Medium | L50: Confirm_Closed | M50: SAT / S4 approval step | N50: SIE_S4P_RS Siemens S4P - Readsoft | Q50: =DATEDIF(E50,TODAY(),"d") -> 267 | R50: =IF($Q50>7,1,0) -> 1 | S50: =IF($Q50>30,1,0) -> 1
A51: 6000135321 | B51: INC42480479 | D51: SRE | E51: 45740 | G51: Zdenek Cifka (GBS CEE P2P CZ AP 2 3 / Z003JPCS) | H51: Ilona Splichalova | I51: 45784 | J51: RFC_FITS | K51: 3: Medium | L51: Confirm_Closed | M51: it's not possible to post VIM ID 5242 on the account 65811000, because there an error is displayed | N51: SIE_S4P_RS Siemens S4P - Readsoft | Q51: =DATEDIF(E51,TODAY(),"d") -> 267 | R51: =IF($Q51>7,1,0) -> 1 | S51: =IF($Q51>30,1,0) -> 1
A52: 6000135513 | B52: INC42494408 | D52: 3003 | E52: 45742 | G52: Tobias Moest (SRE FIN AR 2 / Z000F12V) | I52: 45749 | J52: RFC_FITS | K52: 4: Low | L52: Confirm_Closed | M52: S4P VIM - Zahlungsbedingung falsch ermittelt? | N52: SIE_S4P_RS Siemens S4P - Readsoft | Q52: =DATEDIF(E52,TODAY(),"d") -> 265 | R52: =IF($Q52>7,1,0) -> 1 | S52: =IF($Q52>30,1,0) -> 1
A53: 6000135668 | B53: INC42504595 | D53: 5975 | E53: 45743 | G53: Simon Kostovski (GBS CEE P2P CZ AP PE 2 / Z003DW1N) | H53: Ulrich Rauch / 81739 Muenchen | I53: 45782 | J53: RFC_FITS | K53: 3: Medium | L53: Confirm_Closed | M53: S4P/3014- Invoices which have posted GR or adjusted prices and posted Invoices are stuck in approver’s workflow | N53: SIE_S4P_RS Siemens S4P - Readsoft | Q53: =DATEDIF(E53,TODAY(),"d") -> 264 | R53: =IF($Q53>7,1,0) -> 1 | S53: =IF($Q53>30,1,0) -> 1
A54: 6000135843 | D54: 7092 | E54: 45744 | G54: Ulrich Rauch (IT ECP ERP-CP ARC2 / Z00060NO) | H54: Ulrich Rauch / 81739 Muenchen | I54: 45759 | J54: SAP SOLUTION MANAGER S1A | K54: 3: Medium | L54: Confirm_Closed | M54: Fix missing purpose code JP in Readsoft GEN table | N54: SIE_S4P_RS Siemens S4P - Readsoft | Q54: =DATEDIF(E54,TODAY(),"d") -> 263 | R54: =IF($Q54>7,1,0) -> 1 | S54: =IF($Q54>30,1,0) -> 1
A55: 6000135916 | B55: INC42521355 | D55: 7092 | E55: 45747 | G55: Jonas Weber (IT DA DO PL / Z003DMKU) | H55: Ulrich Rauch / 81739 Muenchen | I55: 45754 | J55: RFC_FITS | K55: 4: Low | L55: Confirm_Closed | M55: Readsoft - Mailversand nach Query fehlt | N55: SIE_S4P_RS Siemens S4P - Readsoft | Q55: =DATEDIF(E55,TODAY(),"d") -> 260 | R55: =IF($Q55>7,1,0) -> 1 | S55: =IF($Q55>30,1,0) -> 1
A56: 6000135930 | B56: INC42521949 | D56: SRE | E56: 45747 | G56: Tobias Moest (SRE FIN AR 2 / Z000F12V) | H56: Ulrich Rauch / 81739 Muenchen | I56: 45758 | J56: RFC_FITS | K56: 4: Low | L56: Confirm_Closed | M56: S4P 100 - VIM: User erhält keine E-Mail zur Workflow Freigabe | N56: SIE_S4P_RS Siemens S4P - Readsoft | Q56: =DATEDIF(E56,TODAY(),"d") -> 260 | R56: =IF($Q56>7,1,0) -> 1 | S56: =IF($Q56>30,1,0) -> 1
A57: 6000136043 | D57: 7092 | E57: 45748 | G57: Ulrich Rauch (IT ECP ERP-CP ARC2 / Z00060NO) | H57: Kerstin Mueller / 81739 Muenchen | I57: 45786 | J57: SAP SOLUTION MANAGER S1A | K57: 3: Medium | L57: Confirm_Closed | M57: Readsoft: adaption tax code determination | N57: SIE_S4P_RS Siemens S4P - Readsoft | Q57: =DATEDIF(E57,TODAY(),"d") -> 259 | R57: =IF($Q57>7,1,0) -> 1 | S57: =IF($Q57>30,1,0) -> 1
A58: 6000136104 | B58: INC42532842 | D58: 3014 | E58: 45748 | G58: Alina Corina Maresi (DI MC GMC MF-EWN PU-BUZ FIN LOG 1-2 / Z | H58: Ulrich Rauch / 81739 Muenchen | I58: 45755 | J58: RFC_FITS | K58: 3: Medium | L58: Confirm_Closed | M58: No possible to approve the invoices because there is an error in determining the next approver | N58: SIE_S4P_RS Siemens S4P - Readsoft | Q58: =DATEDIF(E58,TODAY(),"d") -> 259 | R58: =IF($Q58>7,1,0) -> 1 | S58: =IF($Q58>30,1,0) -> 1
A59: 6000136206 | B59: INC42539676 | D59: 7411 | E59: 45749 | G59: Mona Sangl (DI MC GMC MF-EWN FIN LOG 1 2 / Z002Z0BD) | H59: Ilona Splichalova | I59: 45798 | J59: RFC_FITS | K59: 3: Medium | L59: Confirm_Closed | M59: Block reason "Over Limit" is not given | N59: SIE_S4P_RS Siemens S4P - Readsoft | Q59: =DATEDIF(E59,TODAY(),"d") -> 258 | R59: =IF($Q59>7,1,0) -> 1 | S59: =IF($Q59>30,1,0) -> 1
A60: 6000136305 | B60: INC42544021 | D60: 3011 | E60: 45749 | G60: Asma Meftah (DI SW EDA MNA / Z003U86H) | H60: Ulrich Rauch / 81739 Muenchen | I60: 45756 | J60: RFC_FITS | K60: 3: Medium | L60: Confirm_Closed | M60: KOFAX shows the following error: User Asma Meftah (Z003U86H) locked | N60: SIE_S4P_RS Siemens S4P - Readsoft | Q60: =DATEDIF(E60,TODAY(),"d") -> 258 | R60: =IF($Q60>7,1,0) -> 1 | S60: =IF($Q60>30,1,0) -> 1
A61: 6000136404 | B61: INC42552933 | D61: 3003 | E61: 45750 | G61: Pavla Tothova (GBS CEE P2P CZ AP 2 3 / Z002NYHT) | H61: Ilona Splichalova | I61: 45764 | J61: RFC_FITS | K61: 3: Medium | L61: Confirm_Closed | M61: S4P/AUN 3003 VIM ID 3471- the document cannot be cancelled | N61: SIE_S4P_RS Siemens S4P - Readsoft | Q61: =DATEDIF(E61,TODAY(),"d") -> 257 | R61: =IF($Q61>7,1,0) -> 1 | S61: =IF($Q61>30,1,0) -> 1
A62: 6000136413 | B62: INC42553406 | D62: SRE | E62: 45750 | G62: Pavla Tothova (GBS CEE P2P CZ AP 2 3 / Z002NYHT) | H62: Ilona Splichalova | I62: 45758 | J62: RFC_FITS | K62: 3: Medium | L62: Confirm_Closed | M62: S4P/7998 - DPs 2977 and 1961 - it's not possible to recall the approval workflows | N62: SIE_S4P_RS Siemens S4P - Readsoft | Q62: =DATEDIF(E62,TODAY(),"d") -> 257 | R62: =IF($Q62>7,1,0) -> 1 | S62: =IF($Q62>30,1,0) -> 1
A63: 6000136417 | B63: INC42553572 | D63: SRE | E63: 45750 | G63: Pavla Tothova (GBS CEE P2P CZ AP 2 3 / Z002NYHT) | H63: Albert Galek | I63: 45758 | J63: RFC_FITS | K63: 3: Medium | L63: Confirm_Closed | M63: S4P/7998 - VIM ID 5352 - approval workflow wasn't started. | N63: SIE_S4P_RS Siemens S4P - Readsoft | Q63: =DATEDIF(E63,TODAY(),"d") -> 257 | R63: =IF($Q63>7,1,0) -> 1 | S63: =IF($Q63>30,1,0) -> 1
A64: 6000136696 | B64: INC42571709 | D64: SRE | E64: 45755 | G64: Pavla Tothova (GBS CEE P2P CZ AP 2 3 / Z002NYHT) | H64: Ilona Splichalova | I64: 45763 | J64: RFC_FITS | K64: 3: Medium | L64: Confirm_Closed | M64: S4P/7998 - DP 2512 - it's not possible to recall the approval workflow | N64: SIE_S4P_RS Siemens S4P - Readsoft | Q64: =DATEDIF(E64,TODAY(),"d") -> 252 | R64: =IF($Q64>7,1,0) -> 1 | S64: =IF($Q64>30,1,0) -> 1
A65: 6000136707 | B65: INC42571588 | D65: SRE | E65: 45755 | G65: Pavla Tothova (GBS CEE P2P CZ AP 2 3 / Z002NYHT) | H65: Ilona Splichalova | I65: 45763 | J65: RFC_FITS | K65: 3: Medium | L65: Confirm_Closed | M65: S4P/7998 - DP 1032 - it's not possible to recall the approval workflow | N65: SIE_S4P_RS Siemens S4P - Readsoft | Q65: =DATEDIF(E65,TODAY(),"d") -> 252 | R65: =IF($Q65>7,1,0) -> 1 | S65: =IF($Q65>30,1,0) -> 1
A66: 6000136806 | D66: 7092 | E66: 45755 | G66: Ulrich Rauch (IT ECP FPS LV / Z00060NO) | H66: Ramesh Itamsetti | I66: 45789 | J66: SAP SOLUTION MANAGER S1A | K66: 3: Medium | L66: Confirm_Closed | M66: VIM: bugfix in GR Wait functionality | N66: SIE_S4P_RS Siemens S4P - Readsoft | Q66: =DATEDIF(E66,TODAY(),"d") -> 252 | R66: =IF($Q66>7,1,0) -> 1 | S66: =IF($Q66>30,1,0) -> 1
A67: 6000136916 | B67: INC42586578 | D67: SRE | E67: 45756 | G67: Pavla Tothova (GBS CEE P2P CZ AP 2 3 / Z002NYHT) | H67: Ilona Splichalova | I67: 45764 | J67: RFC_FITS | K67: 3: Medium | L67: Confirm_Closed | M67: S4P/7998 - problem with approval workflow - VIM ID 4984 und 4985 | N67: SIE_S4P_RS Siemens S4P - Readsoft | Q67: =DATEDIF(E67,TODAY(),"d") -> 251 | R67: =IF($Q67>7,1,0) -> 1 | S67: =IF($Q67>30,1,0) -> 1
A68: 6000137097 | B68: INC42596308 | D68: 7092 | E68: 45757 | G68: Nadine Huettl (LC IP LTA / Z0005Q3T) | H68: Ulrich Rauch / 81739 Muenchen | I68: 45765 | J68: RFC_FITS | K68: 4: Low | L68: Confirm_Closed | M68: Freigabe von Rechnungen nicht möglich (ARE 5811) | N68: SIE_S4P_RS Siemens S4P - Readsoft | Q68: =DATEDIF(E68,TODAY(),"d") -> 250 | R68: =IF($Q68>7,1,0) -> 1 | S68: =IF($Q68>30,1,0) -> 1
A69: 6000137324 | B69: INC42614440 | D69: 3014 | E69: 45761 | G69: Alina Corina Maresi (DI MC GMC MF-EWN PU-BUZ FIN LOG 1-2 / Z | H69: Ulrich Rauch / 81739 Muenchen | I69: 45771 | J69: RFC_FITS | K69: 2: High | L69: Confirm_Closed | M69: Error on approval invoices in "My inbox" VIM AUN 3014 | N69: SIE_S4P_RS Siemens S4P - Readsoft | Q69: =DATEDIF(E69,TODAY(),"d") -> 246 | R69: =IF($Q69>7,1,0) -> 1 | S69: =IF($Q69>30,1,0) -> 1
A70: 6000137341 | B70: INC42614781 | D70: 7092 | E70: 45761 | G70: Fabian Schmitzer (IT DA DO E / Z001WYFH) | H70: Ilona Splichalova | I70: 45768 | J70: RFC_FITS | K70: 4: Low | L70: Confirm_Closed | M70: No access to my S4P 100 / Webcycle list of documents | N70: SIE_S4P_RS Siemens S4P - Readsoft | Q70: =DATEDIF(E70,TODAY(),"d") -> 246 | R70: =IF($Q70>7,1,0) -> 1 | S70: =IF($Q70>30,1,0) -> 1
A71: 6000137533 | D71: 3008 | E71: 45762 | G71: Ulrich Rauch (IT ECP FPS LV / Z00060NO) | H71: Ilona Splichalova | I71: 45782 | J71: SAP SOLUTION MANAGER S1A | K71: 3: Medium | L71: Confirm_Closed | M71: VIM: DP 3924 block removed with single appr.step | N71: SIE_S4P_RS Siemens S4P - Readsoft | Q71: =DATEDIF(E71,TODAY(),"d") -> 245 | R71: =IF($Q71>7,1,0) -> 1 | S71: =IF($Q71>30,1,0) -> 1
A72: 6000137544 | B72: INC42625312 | D72: 3003 | E72: 45762 | G72: Tobias Moest (SRE FIN AR 2 / Z000F12V) | H72: Ulrich Rauch / 81739 Muenchen | I72: 45814 | J72: Ulrich Rauch | K72: 4: Low | L72: Proposed Solution | M72: S4P 100 VIM - Selektion in VIM Analytics fehlerhaft | N72: SIE_S4P_RS Siemens S4P - Readsoft | Q72: =DATEDIF(E72,TODAY(),"d") -> 245 | R72: =IF($Q72>7,1,0) -> 1 | S72: =IF($Q72>30,1,0) -> 1
A73: 6000137636 | B73: INC42632582 | D73: 3014 | E73: 45763 | G73: Andrei Vulpescu (DI MC GMC MF-EWN PU-BUZ FIN / Z00172BA) | H73: Albert Galek | I73: 45782 | J73: RFC_FITS | K73: 2: High | L73: Confirm_Closed | M73: I cannot approve invoice due to error | N73: SIE_S4P_RS Siemens S4P - Readsoft | Q73: =DATEDIF(E73,TODAY(),"d") -> 244 | R73: =IF($Q73>7,1,0) -> 1 | S73: =IF($Q73>30,1,0) -> 1
A74: 6000137924 | B74: INC42657410 | D74: 5975 | E74: 45769 | G74: Libor Pas (GBS CEE P2P CZ SC 2 8 / Z004VCDA) | H74: Albert Galek | I74: 45782 | J74: RFC_FITS | K74: 4: Low | L74: Confirm_Closed | M74: proces blocked | N74: SIE_S4P_RS Siemens S4P - Readsoft | Q74: =DATEDIF(E74,TODAY(),"d") -> 238 | R74: =IF($Q74>7,1,0) -> 1 | S74: =IF($Q74>30,1,0) -> 1
A75: 6000138263 | D75: 3014 | E75: 45771 | G75: Albert Galek (IT ECP FPS LV / Z004W53N) | H75: Ilona Splichalova | I75: 45820 | J75: Ramesh Itamsetti | K75: 3: Medium | L75: In Process | M75: Please check below DPs ald close approval WF if needed | N75: SIE_S4P_RS Siemens S4P - Readsoft | Q75: =DATEDIF(E75,TODAY(),"d") -> 236 | R75: =IF($Q75>7,1,0) -> 1 | S75: =IF($Q75>30,1,0) -> 1
A76: 6000138316 | B76: INC42678209 | D76: SRE | E76: 45772 | G76: Pavla Tothova (GBS CEE P2P CZ AP 2 3 / Z002NYHT) | H76: Ilona Splichalova | I76: 45779 | J76: RFC_FITS | K76: 3: Medium | L76: Confirm_Closed | M76: S4P/7998 - VIM 6944 - it's not possible to recall the approval workflow and send it to a specific person | N76: SIE_S4P_RS Siemens S4P - Readsoft | Q76: =DATEDIF(E76,TODAY(),"d") -> 235 | R76: =IF($Q76>7,1,0) -> 1 | S76: =IF($Q76>30,1,0) -> 1
A77: 6000138428 | B77: INC42684362 | D77: SRE | E77: 45772 | G77: Pavla Tothova (GBS CEE P2P CZ AP 2 3 / Z002NYHT) | H77: Ulrich Rauch / 81739 Muenchen | I77: 45820 | J77: Ramesh Itamsetti | K77: 4: Low | L77: In Process | M77: S4P/7998 - VIM ID 6783 - approval workflow wasn't started | N77: SIE_S4P_RS Siemens S4P - Readsoft | Q77: =DATEDIF(E77,TODAY(),"d") -> 235 | R77: =IF($Q77>7,1,0) -> 1 | S77: =IF($Q77>30,1,0) -> 1
A78: 6000138437 | B78: INC42684231 | D78: SRE | E78: 45772 | G78: Pavla Tothova (GBS CEE P2P CZ AP 2 3 / Z002NYHT) | H78: Ilona Splichalova | I78: 45807 | J78: Ilona Splichalova | K78: 3: Medium | L78: In Process | M78: S4P/7998 - VIM ID 6829 - approval workflow wasn't started | N78: SIE_S4P_RS Siemens S4P - Readsoft | Q78: =DATEDIF(E78,TODAY(),"d") -> 235 | R78: =IF($Q78>7,1,0) -> 1 | S78: =IF($Q78>30,1,0) -> 1
A79: 6000138440 | B79: INC42684494 | D79: SRE | E79: 45772 | G79: Pavla Tothova (GBS CEE P2P CZ AP 2 3 / Z002NYHT) | H79: Ilona Splichalova | I79: 45786 | J79: RFC_FITS | K79: 4: Low | L79: Confirm_Closed | M79: S4P/7998 - VIM ID 6579 - twice in the system, cleared, but situated in My inbox | N79: SIE_S4P_RS Siemens S4P - Readsoft | Q79: =DATEDIF(E79,TODAY(),"d") -> 235 | R79: =IF($Q79>7,1,0) -> 1 | S79: =IF($Q79>30,1,0) -> 1
A80: 6000138481 | B80: INC42689919 | D80: 5975 | E80: 45775 | G80: Jitka Krnavkova (GBS CEE P2P CZ AP 2 4 / Z002HBHS) | H80: Ilona Splichalova | I80: 45786 | J80: RFC_FITS | K80: 3: Medium | L80: Confirm_Closed | M80: Permissions to removing od payment block X from RS | N80: SIE_S4P_RS Siemens S4P - Readsoft | Q80: =DATEDIF(E80,TODAY(),"d") -> 232 | R80: =IF($Q80>7,1,0) -> 1 | S80: =IF($Q80>30,1,0) -> 1
A81: 6000138500 | B81: INC42690787 | D81: SRE | E81: 45775 | G81: Zdenek Cifka (GBS CEE P2P CZ AP 2 3 / Z003JPCS) | H81: Ulrich Rauch / 81739 Muenchen | I81: 45807 | J81: Ilona Splichalova | K81: 3: Medium | L81: In Process | M81: S4P / It's not possible to start approval workflow for VIM ID 6022 and 6129 (company code 3003) | N81: SIE_S4P_RS Siemens S4P - Readsoft | Q81: =DATEDIF(E81,TODAY(),"d") -> 232 | R81: =IF($Q81>7,1,0) -> 1 | S81: =IF($Q81>30,1,0) -> 1
A82: 6000138582 | B82: INC42694021 | D82: 5975 | E82: 45775 | G82: Pavel Mego (GBS CEE P2P CZ AP 2 4 / Z001SCDJ) | H82: Ilona Splichalova | I82: 45817 | J82: RFC_FITS | K82: 4: Low | L82: Proposed Solution | M82: not possible to post credit note | N82: SIE_S4P_RS Siemens S4P - Readsoft | Q82: =DATEDIF(E82,TODAY(),"d") -> 232 | R82: =IF($Q82>7,1,0) -> 1 | S82: =IF($Q82>30,1,0) -> 1
A83: 6000138600 | B83: INC42694920 | D83: 3014 | E83: 45775 | G83: Marcus Pfau (DI MC GMC MF-EWN PU-BUZ QM&EHS / Z004UA4Y) | H83: Ilona Splichalova | I83: 45812 | J83: RFC_FITS | K83: 3: Medium | L83: Confirm_Closed | M83: Invoice already approved by the user | N83: SIE_S4P_RS Siemens S4P - Readsoft | Q83: =DATEDIF(E83,TODAY(),"d") -> 232 | R83: =IF($Q83>7,1,0) -> 1 | S83: =IF($Q83>30,1,0) -> 1
A84: 6000138844 | B84: INC42711347 | D84: 5975 | E84: 45777 | G84: Jitka Krnavkova (GBS CEE P2P CZ AP 2 4 / Z002HBHS) | H84: Ilona Splichalova | I84: 45807 | J84: SAP SOLUTION MANAGER S1A | K84: 3: Medium | L84: Confirm_Closed | M84: Permission for removing payment block X | N84: SIE_S4P_RS Siemens S4P - Readsoft | Q84: =DATEDIF(E84,TODAY(),"d") -> 230 | R84: =IF($Q84>7,1,0) -> 1 | S84: =IF($Q84>30,1,0) -> 1
A85: 6000138916 | D85: 5975 | E85: 45779 | G85: Ilona Splichalova (DI IT ERP CZ FICO / Z002Z2VA) | H85: Ilona Splichalova | I85: 45817 | J85: SAP SOLUTION MANAGER S1A | K85: 3: Medium | L85: Confirm_Closed | M85: Reminders not generated for Approvers | N85: SIE_S4P_RS Siemens S4P - Readsoft | Q85: =DATEDIF(E85,TODAY(),"d") -> 228 | R85: =IF($Q85>7,1,0) -> 1 | S85: =IF($Q85>30,1,0) -> 1
A86: 6000139044 | B86: INC42725740 | D86: SRE | E86: 45782 | G86: Pavla Tothova (GBS CEE P2P CZ AP 2 3 / Z002NYHT) | H86: Ulrich Rauch / 81739 Muenchen | I86: 45805 | J86: RFC_FITS | K86: 3: Medium | L86: Confirm_Closed | M86: S4P/7998 - problem with approval workflow - VIM ID 4985 | N86: SIE_S4P_RS Siemens S4P - Readsoft | Q86: =DATEDIF(E86,TODAY(),"d") -> 225 | R86: =IF($Q86>7,1,0) -> 1 | S86: =IF($Q86>30,1,0) -> 1
A87: 6000139205 | B87: INC42735561 | D87: 5975 | E87: 45783 | G87: Ivana Tomisova (GBS CEE P2P CZ AP 3 2 / Z004PK7A) | H87: Ulrich Rauch / 81739 Muenchen | I87: 45812 | J87: RFC_FITS | K87: 4: Low | L87: Confirm_Closed | M87: 3014 – Freight order - Doc ID 6183 stucked and not possible to post it | N87: SIE_S4P_RS Siemens S4P - Readsoft | Q87: =DATEDIF(E87,TODAY(),"d") -> 224 | R87: =IF($Q87>7,1,0) -> 1 | S87: =IF($Q87>30,1,0) -> 1
A88: 6000139326 | B88: INC42743833 | D88: 7040 | E88: 45784 | G88: Nicole Oulik (SI S MK / Z0005O5V) | H88: Ilona Splichalova | I88: 45791 | J88: RFC_FITS | K88: 3: Medium | L88: Confirm_Closed | M88: Work cycle login not possible, | N88: SIE_S4P_RS Siemens S4P - Readsoft | Q88: =DATEDIF(E88,TODAY(),"d") -> 223 | R88: =IF($Q88>7,1,0) -> 1 | S88: =IF($Q88>30,1,0) -> 1
A89: 6000139329 | B89: INC42744162 | D89: 5975 | E89: 45784 | G89: Martina Cajtchamlova (GBS CEE P2P CZ AP PE 2 / Z002M3FD) | H89: Albert Galek | I89: 45812 | J89: RFC_FITS | K89: 4: Low | L89: Confirm_Closed | M89: Bug fix for OpenText development - activate SHKZG field for VX_PO documents for tab Line Items - G/L Account | N89: SIE_S4P_RS Siemens S4P - Readsoft | Q89: =DATEDIF(E89,TODAY(),"d") -> 223 | R89: =IF($Q89>7,1,0) -> 1 | S89: =IF($Q89>30,1,0) -> 1
A90: 6000139369 | B90: INC42747521 | D90: SRE | E90: 45785 | G90: Pavla Tothova (GBS CEE P2P CZ AP 2 3 / Z002NYHT) | H90: Mr. Mukthar Baig | I90: 45818 | J90: Mukthar Baig | K90: 3: Medium | L90: In Process | M90: S4P/7998 - VIM ID 3854 and VIM ID 7194 | N90: SIE_S4P_RS Siemens S4P - Readsoft | Q90: =DATEDIF(E90,TODAY(),"d") -> 222 | R90: =IF($Q90>7,1,0) -> 1 | S90: =IF($Q90>30,1,0) -> 1
A91: 6000139374 | D91: SRE | E91: 45784 | G91: Ulrich Rauch (IT ECP FPS LV / Z00060NO) | H91: Albert Galek | I91: 45807 | J91: Albert Galek | K91: 3: Medium | L91: In Process | M91: VIM: DP No. missing in My Approved Invoices App | N91: SIE_S4P_RS Siemens S4P - Readsoft | Q91: =DATEDIF(E91,TODAY(),"d") -> 223 | R91: =IF($Q91>7,1,0) -> 1 | S91: =IF($Q91>30,1,0) -> 1
A92: 6000139577 | B92: INC42760716 | D92: 7092 | E92: 45786 | G92: Judith Kraus (CF R 7 4 5 / Z004MKEC) | H92: Ulrich Rauch / 81739 Muenchen | I92: 45793 | J92: RFC_FITS | K92: 2: High | L92: Confirm_Closed | M92: ARE 7040 S4P Buchungsperiode 007 2025 noch nicht geöffnet | N92: SIE_S4P_RS Siemens S4P - Readsoft | Q92: =DATEDIF(E92,TODAY(),"d") -> 221 | R92: =IF($Q92>7,1,0) -> 1 | S92: =IF($Q92>30,1,0) -> 1
A93: 6000139584 | B93: INC42760154 | D93: SRE | E93: 45786 | G93: Pavla Tothova (GBS CEE P2P CZ AP 2 3 / Z002NYHT) | H93: Ulrich Rauch / 81739 Muenchen | I93: 45797 | J93: RFC_FITS | K93: 3: Medium | L93: Confirm_Closed | M93: S4P/7998 - VIM ID 2977 and VIM ID 1961 - the invoices in "VIM completed" without approval | N93: SIE_S4P_RS Siemens S4P - Readsoft | Q93: =DATEDIF(E93,TODAY(),"d") -> 221 | R93: =IF($Q93>7,1,0) -> 1 | S93: =IF($Q93>30,1,0) -> 1
A94: 6000139600 | B94: INC42760922 | D94: SRE | E94: 45786 | G94: Pavla Tothova (GBS CEE P2P CZ AP 2 3 / Z002NYHT) | H94: Albert Galek | I94: 45811 | J94: RFC_FITS | K94: 2: High | L94: Confirm_Closed | M94: S4P/7998 - approval workflows not started | N94: SIE_S4P_RS Siemens S4P - Readsoft | Q94: =DATEDIF(E94,TODAY(),"d") -> 221 | R94: =IF($Q94>7,1,0) -> 1 | S94: =IF($Q94>30,1,0) -> 1
A95: 6000139702 | D95: 7092 | E95: 45789 | G95: Ulrich Rauch (IT ECP FPS LV / Z00060NO) | H95: Albert Galek | I95: 45810 | J95: SAP SOLUTION MANAGER S1A | K95: 2: High | L95: Confirm_Closed | M95: VIM: receiver_function_module with outdated status in S4P | N95: SIE_S4P_RS Siemens S4P - Readsoft | Q95: =DATEDIF(E95,TODAY(),"d") -> 218 | R95: =IF($Q95>7,1,0) -> 1 | S95: =IF($Q95>30,1,0) -> 1
A96: 6000139704 | B96: INC42769267 | D96: 7092 | E96: 45789 | G96: Wolfgang Geitner (DI IT FA UIT / Z00213NZ) | H96: Ilona Splichalova | I96: 45797 | J96: RFC_FITS | K96: 4: Low | L96: Confirm_Closed | M96: Ich benötige Zugang zum S4-Line-Service. | N96: SIE_S4P_RS Siemens S4P - Readsoft | Q96: =DATEDIF(E96,TODAY(),"d") -> 218 | R96: =IF($Q96>7,1,0) -> 1 | S96: =IF($Q96>30,1,0) -> 1
A97: 6000139963 | B97: INC42783591 | D97: 3003 | E97: 45791 | G97: Tobias Moest (SRE FIN AR 2 / Z000F12V) | H97: Kerstin Mueller / 81739 Muenchen | I97: 45805 | J97: RFC_FITS | K97: 2: High | L97: Confirm_Closed | M97: S4P VIM - Fehlermeldung bei Aufruf der Approval App | N97: SIE_S4P_RS Siemens S4P - Readsoft | Q97: =DATEDIF(E97,TODAY(),"d") -> 216 | R97: =IF($Q97>7,1,0) -> 1 | S97: =IF($Q97>30,1,0) -> 1
A98: 6000139986 | B98: INC42784591 | D98: SRE | E98: 45791 | G98: Zdenek Cifka (GBS CEE P2P CZ AP 2 3 / Z003JPCS) | H98: Albert Galek | I98: 45805 | J98: RFC_FITS | K98: 2: High | L98: Confirm_Closed | M98: S4P / It's not possible to use VIM Workplace, because there an ABAP error occurs | N98: SIE_S4P_RS Siemens S4P - Readsoft | Q98: =DATEDIF(E98,TODAY(),"d") -> 216 | R98: =IF($Q98>7,1,0) -> 1 | S98: =IF($Q98>30,1,0) -> 1
A99: 6000140063 | B99: INC42788004 | D99: 5975 | E99: 45792 | G99: Jitka Krnavkova (GBS CEE P2P CZ AP 2 4 / Z002HBHS) | H99: Ilona Splichalova | I99: 45806 | J99: RFC_FITS | K99: 3: Medium | L99: In Process | M99: T-CODE /COCKPIT/WC | N99: SIE_S4P_RS Siemens S4P - Readsoft | Q99: =DATEDIF(E99,TODAY(),"d") -> 215 | R99: =IF($Q99>7,1,0) -> 1 | S99: =IF($Q99>30,1,0) -> 1
A100: 6000140103 | B100: INC42791427 | D100: 3014 | E100: 45792 | G100: Juliana Batya Dora Ciupe (DI MC GMC MF-EWN PU-BUZ FIN BC / Z | H100: Albert Galek | I100: 45800 | J100: RFC_FITS | K100: 2: High | L100: Confirm_Closed | M100: VIM and Invoice approval app errors | N100: SIE_S4P_RS Siemens S4P - Readsoft | Q100: =DATEDIF(E100,TODAY(),"d") -> 215 | R100: =IF($Q100>7,1,0) -> 1 | S100: =IF($Q100>30,1,0) -> 1
...

Sheet VIM-Incidents_W25
A1: ID | B1: FutureNow Ticket | C1: External ID | D1: ARE | E1: Created On | F1: Due by | G1: Reported By | H1: Message Processor | I1: Last Changed on | J1: Last Changed By | K1: Priority | L1: Status | M1: Description | N1: Support Team | O1: System ID | Q1: Open Days | R1: Open 7D+ | S1: Open 30D+
A2: 6000127070 | B2: INC41987224 | D2: 5975 | E2: 45663 | G2: Lenka Michalusova (GBS CEE P2P CZ AP 2 4 / Z002HBHR) | H2: Ulrich Rauch / 81739 Muenchen | I2: 45727 | J2: RFC_FITS | K2: 4: Low | L2: Confirm_Closed | M2: VIM- missing tax code | N2: SIE_S4P_RS Siemens S4P - Readsoft | Q2: =DATEDIF(E2,I2,"d") -> 64 | R2: =IF($Q2>7,1,0) -> 1 | S2: =IF($Q2>30,1,0) -> 1
A3: 6000127209 | B3: INC41997245 | D3: 5975 | E3: 45664 | G3: Simon Kostovski (GBS CEE P2P CZ AP 3 2 / Z003DW1N) | H3: Albert Galek | I3: 45673 | J3: RFC_FITS | K3: 3: Medium | L3: Confirm_Closed | M3: INC41861079 not solved but it was closed | N3: SIE_S4P_RS Siemens S4P - Readsoft | Q3: =DATEDIF(E3,I3,"d") -> 9 | R3: =IF($Q3>7,1,0) -> 1 | S3: =IF($Q3>30,1,0) -> 0
A4: 6000127632 | B4: INC42022656 | D4: 5975 | E4: 45667 | G4: Barbora Struskova (GBS CEE P2P CZ AP 2 4 / Z002HZ1U) | H4: Ilona Splichalova | I4: 45679 | J4: RFC_FITS | K4: 4: Low | L4: Confirm_Closed | M4: automatic text | N4: SIE_S4P_RS Siemens S4P - Readsoft | Q4: =DATEDIF(E4,I4,"d") -> 12 | R4: =IF($Q4>7,1,0) -> 1 | S4: =IF($Q4>30,1,0) -> 0
A5: 6000128352 | D5: 3003 | E5: 45674 | G5: Ilona Splichalova (DI IT ERP CZ FICO / Z002Z2VA) | H5: Albert Galek | I5: 45688 | J5: SAP SOLUTION MANAGER S1A | K5: 3: Medium | L5: Confirm_Closed | M5: DP 2807 in S4P: please check the status | N5: SIE_S4P_RS Siemens S4P - Readsoft | Q5: =DATEDIF(E5,I5,"d") -> 14 | R5: =IF($Q5>7,1,0) -> 1 | S5: =IF($Q5>30,1,0) -> 0
A6: 6000128500 | B6: INC42075263 | D6: 7092 | E6: 45677 | G6: Lena Osterhus (CE SEC TPC / Z001MA1B) | H6: Ilona Splichalova | I6: 45684 | J6: RFC_FITS | K6: 4: Low | L6: Confirm_Closed | M6: Falsche Emailadresse bei Readsoft/ WebCycle | N6: SIE_S4P_RS Siemens S4P - Readsoft | Q6: =DATEDIF(E6,I6,"d") -> 7 | R6: =IF($Q6>7,1,0) -> 0 | S6: =IF($Q6>30,1,0) -> 0
A7: 6000128546 | B7: INC42077895 | D7: SRE | E7: 45677 | G7: Zdenek Cifka (GBS CEE P2P CZ AP 2 3 / Z003JPCS) | H7: Ilona Splichalova | I7: 45805 | J7: Ulrich Rauch | K7: 3: Medium | L7: In Process | M7: VIM ID's 2391 and 2623 - after posting the payment block was'nt entered and approval workflow was'nt started | N7: SIE_S4P_RS Siemens S4P - Readsoft | Q7: =DATEDIF(E7,TODAY(),"d") -> 330 | R7: =IF($Q7>7,1,0) -> 1 | S7: =IF($Q7>30,1,0) -> 1
A8: 6000128759 | B8: INC42093959 | D8: 7092 | E8: 45679 | G8: Andreas Mengele (MAP DF&PCM PCM / Z001THRJ) | H8: Ilona Splichalova | I8: 45686 | J8: RFC_FITS | K8: 4: Low | L8: Confirm_Closed | M8: Umstellung der Rechte von Susanne Spiegl auf Philipp Rath | N8: SIE_S4P_RS Siemens S4P - Readsoft | Q8: =DATEDIF(E8,TODAY(),"d") -> 328 | R8: =IF($Q8>7,1,0) -> 1 | S8: =IF($Q8>30,1,0) -> 1
A9: 6000129022 | B9: INC42106952 | D9: 5975 | E9: 45680 | G9: Renata Staricna (GBS CEE P2P CZ AP 2 4 / Z0046K6B) | H9: Ilona Splichalova | I9: 45705 | J9: RFC_FITS | K9: 4: Low | L9: Confirm_Closed | M9: Reminder - automatic answers | N9: SIE_S4P_RS Siemens S4P - Readsoft | Q9: =DATEDIF(E9,TODAY(),"d") -> 327 | R9: =IF($Q9>7,1,0) -> 1 | S9: =IF($Q9>30,1,0) -> 1
A10: 6000129245 | B10: INC42120663 | D10: 7092 | E10: 45684 | G10: Veronika Andres (IT ECP FPS T&CS / Z0029JJZ) | H10: Ilona Splichalova | I10: 45691 | J10: RFC_FITS | K10: 4: Low | L10: Confirm_Closed | M10: WebCycle User locked | N10: SIE_S4P_RS Siemens S4P - Readsoft | Q10: =DATEDIF(E10,TODAY(),"d") -> 323 | R10: =IF($Q10>7,1,0) -> 1 | S10: =IF($Q10>30,1,0) -> 1
A11: 6000129304 | B11: INC42122188 | D11: SRE | E11: 45684 | G11: Tobias Moest (SRE FIN AR 2 / Z000F12V) | H11: Albert Galek | I11: 45693 | J11: RFC_FITS | K11: 4: Low | L11: Confirm_Closed | M11: S4P 100 - VIM: Vorgang aus Klärungs-WF nicht vorhanden | N11: SIE_S4P_RS Siemens S4P - Readsoft | Q11: =DATEDIF(E11,TODAY(),"d") -> 323 | R11: =IF($Q11>7,1,0) -> 1 | S11: =IF($Q11>30,1,0) -> 1
A12: 6000129653 | D12: 3003 | E12: 45686 | G12: Ilona Splichalova (DI IT ERP CZ FICO / Z002Z2VA) | H12: Ilona Splichalova | I12: 45782 | J12: SAP SOLUTION MANAGER S1A | K12: 3: Medium | L12: Confirm_Closed | M12: VIM 2756 und 2774 - Error by 3 step approval WF by Construction Invoices | N12: SIE_S4P_RS Siemens S4P - Readsoft | Q12: =DATEDIF(E12,TODAY(),"d") -> 321 | R12: =IF($Q12>7,1,0) -> 1 | S12: =IF($Q12>30,1,0) -> 1
A13: 6000129990 | B13: INC42154604 | D13: SRE | E13: 45688 | G13: Zdenek Cifka (GBS CEE P2P CZ AP 2 3 / Z003JPCS) | H13: Albert Galek | I13: 45699 | J13: RFC_FITS | K13: 3: Medium | L13: Confirm_Closed | M13: Is not possible to start the approval workflow for VIM ID 2515 | N13: SIE_S4P_RS Siemens S4P - Readsoft | Q13: =DATEDIF(E13,TODAY(),"d") -> 319 | R13: =IF($Q13>7,1,0) -> 1 | S13: =IF($Q13>30,1,0) -> 1
A14: 6000130122 | B14: INC42161605 | D14: 3014 | E14: 45691 | G14: Pompilia Bianca Trifa (DI MC GMC MF-EWN PU-BUZ FIN LOG 1-2 / | H14: Ulrich Rauch / 81739 Muenchen | I14: 45708 | J14: RFC_FITS | K14: 3: Medium | L14: Confirm_Closed | M14: S4P VIM - Invoices in Approval steps (direct materials) not visible to the approver | N14: SIE_S4P_RS Siemens S4P - Readsoft | Q14: 38 | R14: =IF($Q14>7,1,0) -> 1 | S14: =IF($Q14>30,1,0) -> 1
A15: 6000130131 | B15: INC42161726 | D15: 3014 | E15: 45691 | G15: Andreea Laura Boran (DI MC GMC MF-EWN PU-BUZ FIN LOG 1-2 / Z | H15: Ulrich Rauch / 81739 Muenchen | I15: 45708 | J15: RFC_FITS | K15: 3: Medium | L15: Confirm_Closed | M15: S4P - VIM error in invoice approval | N15: SIE_S4P_RS Siemens S4P - Readsoft | Q15: =DATEDIF(E15,TODAY(),"d") -> 316 | R15: =IF($Q15>7,1,0) -> 1 | S15: =IF($Q15>30,1,0) -> 1
A16: 6000130842 | B16: INC42203263 | D16: 3003 | E16: 45698 | G16: Helge Preiss (SRE DP PM EU / Z001WZ3K) | H16: Albert Galek | I16: 45824 | J16: Ulrich Rauch | K16: 3: Medium | L16: Proposed Solution | M16: S4P VIM FIORI Approval Invoice Management Fehlermeldung | N16: SIE_S4P_RS Siemens S4P - Readsoft | Q16: =DATEDIF(E16,I16,"d") -> 126 | R16: =IF($Q16>7,1,0) -> 1 | S16: =IF($Q16>30,1,0) -> 1
A17: 6000130889 | B17: INC42205466 | D17: 7092 | E17: 45698 | G17: Laura Hochwind (IT ECP FPS AP1 / Z003NVNW) | H17: Ulrich Rauch / 81739 Muenchen | I17: 45705 | J17: RFC_FITS | K17: 3: Medium | L17: Confirm_Closed | M17: Add Substitute for Webcycle Readsoft | N17: SIE_S4P_RS Siemens S4P - Readsoft | Q17: =DATEDIF(E17,TODAY(),"d") -> 309 | R17: =IF($Q17>7,1,0) -> 1 | S17: =IF($Q17>30,1,0) -> 1
A18: 6000131438 | B18: INC42234456 | D18: 3003 | E18: 45701 | G18: Mario Beck (SRE DP PM EU / Z00109RY) | H18: Ramesh Itamsetti | I18: 45824 | J18: Ulrich Rauch | K18: 3: Medium | L18: Proposed Solution | M18: S4P 100 VIM - Fehlermeldung bei WF-Freigabe | N18: SIE_S4P_RS Siemens S4P - Readsoft | Q18: =DATEDIF(E18,TODAY(),"d") -> 306 | R18: =IF($Q18>7,1,0) -> 1 | S18: =IF($Q18>30,1,0) -> 1
A19: 6000131514 | D19: 7092 | E19: 45702 | G19: Ulrich Rauch (IT ECP ERP-CP ARC2 / Z00060NO) | H19: Ulrich Rauch / 81739 Muenchen | I19: 45723 | J19: SAP SOLUTION MANAGER S1A | K19: 3: Medium | L19: Confirm_Closed | M19: VIM: VIM Authorization issue in Exceptions App (mid-term solution) | N19: SIE_S4P_RS Siemens S4P - Readsoft | Q19: =DATEDIF(E19,I19,"d") -> 21 | R19: =IF($Q19>7,1,0) -> 1 | S19: =IF($Q19>30,1,0) -> 0
A20: 6000131715 | B20: INC42252236 | D20: 5975 | E20: 45705 | G20: Pavel Mego (GBS CEE P2P CZ AP 2 4 / Z001SCDJ) | H20: Ulrich Rauch / 81739 Muenchen | I20: 45713 | J20: RFC_FITS | K20: 4: Low | L20: Confirm_Closed | M20: duplicity check | N20: SIE_S4P_RS Siemens S4P - Readsoft | Q20: =DATEDIF(E20,TODAY(),"d") -> 302 | R20: =IF($Q20>7,1,0) -> 1 | S20: =IF($Q20>30,1,0) -> 1
A21: 6000132000 | B21: INC42270698 | D21: SRE | E21: 45707 | G21: Zdenek Cifka (GBS CEE P2P CZ AP 2 3 / Z003JPCS) | H21: Albert Galek | I21: 45735 | J21: RFC_FITS | K21: 3: Medium | L21: Confirm_Closed | M21: In VIM it is not possible to post the recurring documents, which contain multiple Profit Centers - VIM ID 3988 and 4340 | N21: SIE_S4P_RS Siemens S4P - Readsoft | Q21: =DATEDIF(E21,TODAY(),"d") -> 300 | R21: =IF($Q21>7,1,0) -> 1 | S21: =IF($Q21>30,1,0) -> 1
A22: 6000132651 | B22: INC42313692 | D22: 3003 | E22: 45714 | G22: Mario Beck (SRE DP PM EU / Z00109RY) | H22: Albert Galek | I22: 45723 | J22: RFC_FITS | K22: 4: Low | L22: Confirm_Closed | M22: S4P 100 VIM - #2777 can't be approved (new error message) | N22: SIE_S4P_RS Siemens S4P - Readsoft | Q22: =DATEDIF(E22,TODAY(),"d") -> 293 | R22: =IF($Q22>7,1,0) -> 1 | S22: =IF($Q22>30,1,0) -> 1
A23: 6000133013 | B23: INC42339428 | D23: 5975 | E23: 45719 | G23: Jitka Krnavkova (GBS CEE P2P CZ AP 2 4 / Z002HBHS) | H23: Ilona Splichalova | I23: 45734 | J23: RFC_FITS | K23: 4: Low | L23: Confirm_Closed | M23: Add user to ICFR group_READSOFT | N23: SIE_S4P_RS Siemens S4P - Readsoft | Q23: =DATEDIF(E23,TODAY(),"d") -> 288 | R23: =IF($Q23>7,1,0) -> 1 | S23: =IF($Q23>30,1,0) -> 1
A24: 6000133061 | B24: INC42342340 | D24: SRE | E24: 45719 | G24: Zdenek Cifka (GBS CEE P2P CZ AP 2 3 / Z003JPCS) | H24: Ilona Splichalova | I24: 45735 | J24: RFC_FITS | K24: 3: Medium | L24: Confirm_Closed | M24: VIM ID 1785 - approval workflow wasn't started but nevertheless is situated in VIM WP in My pending section | N24: SIE_S4P_RS Siemens S4P - Readsoft | Q24: =DATEDIF(E24,TODAY(),"d") -> 288 | R24: =IF($Q24>7,1,0) -> 1 | S24: =IF($Q24>30,1,0) -> 1
A25: 6000133063 | B25: INC42342645 | D25: 5220 | E25: 45719 | G25: Simona-Elena Kovar (CF R EEA PP PI / Z0046E1M) | H25: Ilona Splichalova | I25: 45778 | J25: RFC_FITS | K25: 4: Low | L25: Confirm_Closed | M25: GR posted, the payment block was removed in the background -> VIM workflow NOT completed | N25: SIE_S4P_RS Siemens S4P - Readsoft | Q25: =DATEDIF(E25,TODAY(),"d") -> 288 | R25: =IF($Q25>7,1,0) -> 1 | S25: =IF($Q25>30,1,0) -> 1
A26: 6000133075 | B26: INC42342669 | D26: 5220 | E26: 45719 | G26: Simona-Elena Kovar (CF R EEA PP PI / Z0046E1M) | H26: Albert Galek | I26: 45758 | J26: RFC_FITS | K26: 4: Low | L26: Confirm_Closed | M26: the document requires a technical approval although there is no price or quantity deviation | N26: SIE_S4P_RS Siemens S4P - Readsoft | Q26: =DATEDIF(E26,TODAY(),"d") -> 288 | R26: =IF($Q26>7,1,0) -> 1 | S26: =IF($Q26>30,1,0) -> 1
A27: 6000133085 | D27: 7092 | E27: 45719 | G27: Ulrich Rauch (IT ECP ERP-CP ARC2 / Z00060NO) | H27: Albert Galek | I27: 45731 | J27: SAP SOLUTION MANAGER S1A | K27: 3: Medium | L27: Confirm_Closed | M27: VIM: direct material PO: not able to choose non preferred approver | N27: SIE_S4P_RS Siemens S4P - Readsoft | Q27: =DATEDIF(E27,TODAY(),"d") -> 288 | R27: =IF($Q27>7,1,0) -> 1 | S27: =IF($Q27>30,1,0) -> 1
A28: 6000133086 | D28: 7092 | E28: 45719 | G28: Ulrich Rauch (IT ECP ERP-CP ARC2 / Z00060NO) | H28: Albert Galek | I28: 45773 | J28: SAP SOLUTION MANAGER S1A | K28: 3: Medium | L28: Confirm_Closed | M28: VIM ID 1785 and 5352 - approval workflow wasn't started but nevertheless is s | N28: SIE_S4P_RS Siemens S4P - Readsoft | Q28: =DATEDIF(E28,TODAY(),"d") -> 288 | R28: =IF($Q28>7,1,0) -> 1 | S28: =IF($Q28>30,1,0) -> 1
A29: 6000133087 | D29: 7092 | E29: 45719 | G29: Ulrich Rauch (IT ECP ERP-CP ARC2 / Z00060NO) | H29: Ilona Splichalova | I29: 45807 | J29: SAP SOLUTION MANAGER S1A | K29: 3: Medium | L29: Confirm_Closed | M29: VIM: different statuses in VIM Workplace and VIM Analytics | N29: SIE_S4P_RS Siemens S4P - Readsoft | Q29: =DATEDIF(E29,TODAY(),"d") -> 288 | R29: =IF($Q29>7,1,0) -> 1 | S29: =IF($Q29>30,1,0) -> 1
A30: 6000133442 | D30: 3003 | E30: 45722 | G30: Ilona Splichalova (DI IT ERP CZ FICO / Z002Z2VA) | H30: Ilona Splichalova | I30: 45786 | J30: SAP SOLUTION MANAGER S1A | K30: 3: Medium | L30: Confirm_Closed | M30: In VIM is not possible to cancel the invoice - DP 4288 | N30: SIE_S4P_RS Siemens S4P - Readsoft | Q30: =DATEDIF(E30,TODAY(),"d") -> 285 | R30: =IF($Q30>7,1,0) -> 1 | S30: =IF($Q30>30,1,0) -> 1
A31: 6000133644 | B31: INC42377517 | D31: 3014 | E31: 45723 | G31: Simon Kostovski (GBS CEE P2P CZ AP PE 2 / Z003DW1N) | H31: Albert Galek | I31: 45789 | J31: Ilona Splichalova | K31: 3: Medium | L31: In Process | M31: S4P Please adjust the VAT date to be identical with the invoice date for Company code 3014 | N31: SIE_S4P_RS Siemens S4P - Readsoft | Q31: =DATEDIF(E31,TODAY(),"d") -> 284 | R31: =IF($Q31>7,1,0) -> 1 | S31: =IF($Q31>30,1,0) -> 1
A32: 6000133647 | B32: INC42377569 | D32: 5975 | E32: 45723 | G32: Jan Binder (GBS CEE P2P CZ AP 2 2 / Z00435WC) | H32: Ilona Splichalova | I32: 45733 | J32: RFC_FITS | K32: 4: Low | L32: Confirm_Closed | M32: Receipt of invoices and posting in a different month/period. | N32: SIE_S4P_RS Siemens S4P - Readsoft | Q32: =DATEDIF(E32,TODAY(),"d") -> 284 | R32: =IF($Q32>7,1,0) -> 1 | S32: =IF($Q32>30,1,0) -> 1
A33: 6000133780 | B33: INC42386307 | D33: 3014 | E33: 45726 | G33: Andrei Vulpescu (DI MC GMC MF-EWN PU-BUZ FIN / Z00172BA) | H33: Albert Galek | I33: 45741 | J33: RFC_FITS | K33: 4: Low | L33: Confirm_Closed | M33: I cannot approve invoice release | N33: SIE_S4P_RS Siemens S4P - Readsoft | Q33: =DATEDIF(E33,TODAY(),"d") -> 281 | R33: =IF($Q33>7,1,0) -> 1 | S33: =IF($Q33>30,1,0) -> 1
A34: 6000133782 | B34: INC42386439 | D34: SRE | E34: 45726 | G34: Zdenek Cifka (GBS CEE P2P CZ AP 2 3 / Z003JPCS) | H34: Albert Galek | I34: 45735 | J34: RFC_FITS | K34: 3: Medium | L34: Confirm_Closed | M34: At VIM ID's 2977 and 1961 it's not possible to recall the approval workflow because they are situated in VIM WP in My co | N34: SIE_S4P_RS Siemens S4P - Readsoft | Q34: =DATEDIF(E34,TODAY(),"d") -> 281 | R34: =IF($Q34>7,1,0) -> 1 | S34: =IF($Q34>30,1,0) -> 1
A35: 6000133815 | B35: INC42387821 | D35: SRE | E35: 45726 | G35: Zdenek Cifka (GBS CEE P2P CZ AP 2 3 / Z003JPCS) | H35: Albert Galek | I35: 45748 | J35: RFC_FITS | K35: 3: Medium | L35: Confirm_Closed | M35: VIM ID 5033 - it's not possible to start the approval workflow manually for the specific person. | N35: SIE_S4P_RS Siemens S4P - Readsoft | Q35: =DATEDIF(E35,TODAY(),"d") -> 281 | R35: =IF($Q35>7,1,0) -> 1 | S35: =IF($Q35>30,1,0) -> 1
A36: 6000133897 | D36: 5975 | E36: 45727 | G36: Ilona Splichalova (DI IT ERP CZ FICO / Z002Z2VA) | H36: Albert Galek | I36: 45751 | J36: SAP SOLUTION MANAGER S1A | K36: 3: Medium | L36: Confirm_Closed | M36: VIM Table U-date Clarifications | N36: SIE_S4P_RS Siemens S4P - Readsoft | Q36: =DATEDIF(E36,TODAY(),"d") -> 280 | R36: =IF($Q36>7,1,0) -> 1 | S36: =IF($Q36>30,1,0) -> 1
A37: 6000134052 | B37: INC42401853 | D37: 3014 | E37: 45728 | G37: Ivana Tomisova (GBS CEE P2P CZ AP 3 2 / Z004PK7A) | H37: Mr. Silambarasan Vasu | I37: 45819 | K37: 4: Low | L37: Forwarded | M37: 3014 - ICC invoice not visible in VIM workplace | N37: MM - Materials Management | Q37: =DATEDIF(E37,TODAY(),"d") -> 279 | R37: =IF($Q37>7,1,0) -> 1 | S37: =IF($Q37>30,1,0) -> 1
A38: 6000134157 | B38: INC42406593 | D38: 5975 | E38: 45729 | G38: Pavel Mego (GBS CEE P2P CZ AP 2 4 / Z001SCDJ) | H38: Ilona Splichalova | I38: 45737 | J38: RFC_FITS | K38: 4: Low | L38: Confirm_Closed | M38: Stucked Webcycle | N38: SIE_S4P_RS Siemens S4P - Readsoft | Q38: =DATEDIF(E38,TODAY(),"d") -> 278 | R38: =IF($Q38>7,1,0) -> 1 | S38: =IF($Q38>30,1,0) -> 1
A39: 6000134167 | D39: 7092 | E39: 45729 | G39: Muskan Khanum Nagad (IT ECP ERP-CP / Z0053CPH) | H39: Albert Galek | I39: 45792 | J39: SAP SOLUTION MANAGER S1A | K39: 3: Medium | L39: Confirm_Closed | M39: Abap programming error in S4P | N39: SIE_S4P_RS Siemens S4P - Readsoft | Q39: =DATEDIF(E39,TODAY(),"d") -> 278 | R39: =IF($Q39>7,1,0) -> 1 | S39: =IF($Q39>30,1,0) -> 1
A40: 6000134304 | B40: INC42414880 | D40: 7011 | E40: 45729 | G40: Cosmin-Ovidiu Sarbu (DI MC GMC MF-EWN PU-BUZ FIN BC / Z0026A | H40: Ilona Splichalova | I40: 45782 | J40: RFC_FITS | K40: 4: Low | L40: Confirm_Closed | M40: Approval of invoices in VIM according to SAT | N40: SIE_S4P_RS Siemens S4P - Readsoft | Q40: =DATEDIF(E40,TODAY(),"d") -> 278 | R40: =IF($Q40>7,1,0) -> 1 | S40: =IF($Q40>30,1,0) -> 1
A41: 6000134423 | B41: INC42420961 | D41: 5975 | E41: 45730 | G41: Pavel Mego (GBS CEE P2P CZ AP 2 4 / Z001SCDJ) | H41: Ilona Splichalova | I41: 45748 | J41: RFC_FITS | K41: 4: Low | L41: Confirm_Closed | M41: readsoft messages | N41: SIE_S4P_RS Siemens S4P - Readsoft | Q41: =DATEDIF(E41,TODAY(),"d") -> 277 | R41: =IF($Q41>7,1,0) -> 1 | S41: =IF($Q41>30,1,0) -> 1
A42: 6000134460 | B42: INC42422286 | D42: 5975 | E42: 45730 | G42: Ivana Tomisova (GBS CEE P2P CZ AP 3 2 / Z004PK7A) | H42: Albert Galek | I42: 45748 | J42: RFC_FITS | K42: 4: Low | L42: Confirm_Closed | M42: 3014 - posting of inovices on mutiple POs | N42: SIE_S4P_RS Siemens S4P - Readsoft | Q42: =DATEDIF(E42,TODAY(),"d") -> 277 | R42: =IF($Q42>7,1,0) -> 1 | S42: =IF($Q42>30,1,0) -> 1
A43: 6000134543 | B43: INC42429350 | D43: 3014 | E43: 45733 | G43: Cristina Mariana Vega (DI MC GMC MF-EWN PU-BUZ FIN LOG / Z00 | H43: Albert Galek | I43: 45754 | J43: RFC_FITS | K43: 2: High | L43: Confirm_Closed | M43: Approval invoice not possible in Approval invoice Management app | N43: SIE_S4P_RS Siemens S4P - Readsoft | Q43: =DATEDIF(E43,TODAY(),"d") -> 274 | R43: =IF($Q43>7,1,0) -> 1 | S43: =IF($Q43>30,1,0) -> 1
A44: 6000134731 | B44: INC42441623 | D44: 5975 | E44: 45734 | G44: Pavel Mego (GBS CEE P2P CZ AP 2 4 / Z001SCDJ) | H44: Ilona Splichalova | I44: 45743 | J44: RFC_FITS | K44: 4: Low | L44: Confirm_Closed | M44: Webcycles with error | N44: SIE_S4P_RS Siemens S4P - Readsoft | Q44: =DATEDIF(E44,TODAY(),"d") -> 273 | R44: =IF($Q44>7,1,0) -> 1 | S44: =IF($Q44>30,1,0) -> 1
A45: 6000134816 | B45: INC42448216 | D45: 5220 | E45: 45735 | G45: Simona-Elena Kovar (CF R EEA PP PI / Z0046E1M) | H45: Ilona Splichalova | I45: 45762 | J45: RFC_FITS | K45: 4: Low | L45: Confirm_Closed | M45: Invoice in approval step but not visible in Approval Invoice Management application | N45: SIE_S4P_RS Siemens S4P - Readsoft | Q45: =DATEDIF(E45,TODAY(),"d") -> 272 | R45: =IF($Q45>7,1,0) -> 1 | S45: =IF($Q45>30,1,0) -> 1
A46: 6000134850 | B46: INC42449485 | D46: 3014 | E46: 45735 | G46: Juliana Batya Dora Ciupe (DI MC GMC MF-EWN PU-BUZ FIN BC / Z | H46: Albert Galek | I46: 45761 | J46: RFC_FITS | K46: 3: Medium | L46: Confirm_Closed | M46: Invoice with IDoc quantity incorect - issue in approval process | N46: SIE_S4P_RS Siemens S4P - Readsoft | Q46: =DATEDIF(E46,TODAY(),"d") -> 272 | R46: =IF($Q46>7,1,0) -> 1 | S46: =IF($Q46>30,1,0) -> 1
A47: 6000134958 | B47: INC42458439 | D47: 3003 | E47: 45736 | G47: Pavla Tothova (GBS CEE P2P CZ AP 2 3 / Z002NYHT) | H47: Ilona Splichalova | I47: 45750 | J47: RFC_FITS | K47: 3: Medium | L47: Confirm_Closed | M47: S4P/AUN 3003 VIM ID 5424 - the credit note was incorrectly booked as an invoice, nevertheless is situated in VIM WP in | N47: SIE_S4P_RS Siemens S4P - Readsoft | Q47: =DATEDIF(E47,TODAY(),"d") -> 271 | R47: =IF($Q47>7,1,0) -> 1 | S47: =IF($Q47>30,1,0) -> 1
A48: 6000135155 | B48: INC42469024 | D48: 7092 | E48: 45737 | G48: Dirk Eska (IT DF COL UC / Z0000X0D) | H48: Ilona Splichalova | I48: 45757 | J48: RFC_FITS | K48: 4: Low | L48: Confirm_Closed | M48: S4-line Service - Kein Zugang zum Webcycle Tool mehr | N48: SIE_S4P_RS Siemens S4P - Readsoft | Q48: =DATEDIF(E48,TODAY(),"d") -> 270 | R48: =IF($Q48>7,1,0) -> 1 | S48: =IF($Q48>30,1,0) -> 1
A49: 6000135247 | D49: SRE | E49: 45740 | G49: Ilona Splichalova (DI IT ERP CZ FICO / Z002Z2VA) | H49: Ilona Splichalova | I49: 45779 | J49: SAP SOLUTION MANAGER S1A | K49: 3: Medium | L49: Confirm_Closed | M49: VIM: Issue with items incorrectly placed in My Completed tab | N49: SIE_S4P_RS Siemens S4P - Readsoft | Q49: =DATEDIF(E49,TODAY(),"d") -> 267 | R49: =IF($Q49>7,1,0) -> 1 | S49: =IF($Q49>30,1,0) -> 1
A50: 6000135249 | B50: INC42467829 | D50: 3014 | E50: 45740 | G50: Andrei Vulpescu (DI MC GMC MF-EWN PU-BUZ FIN / Z00172BA) | H50: Ilona Splichalova | I50: 45782 | J50: RFC_FITS | K50: 3: Medium | L50: Confirm_Closed | M50: SAT / S4 approval step | N50: SIE_S4P_RS Siemens S4P - Readsoft | Q50: =DATEDIF(E50,TODAY(),"d") -> 267 | R50: =IF($Q50>7,1,0) -> 1 | S50: =IF($Q50>30,1,0) -> 1
A51: 6000135321 | B51: INC42480479 | D51: SRE | E51: 45740 | G51: Zdenek Cifka (GBS CEE P2P CZ AP 2 3 / Z003JPCS) | H51: Ilona Splichalova | I51: 45784 | J51: RFC_FITS | K51: 3: Medium | L51: Confirm_Closed | M51: it's not possible to post VIM ID 5242 on the account 65811000, because there an error is displayed | N51: SIE_S4P_RS Siemens S4P - Readsoft | Q51: =DATEDIF(E51,TODAY(),"d") -> 267 | R51: =IF($Q51>7,1,0) -> 1 | S51: =IF($Q51>30,1,0) -> 1
A52: 6000135513 | B52: INC42494408 | D52: 3003 | E52: 45742 | G52: Tobias Moest (SRE FIN AR 2 / Z000F12V) | I52: 45749 | J52: RFC_FITS | K52: 4: Low | L52: Confirm_Closed | M52: S4P VIM - Zahlungsbedingung falsch ermittelt? | N52: SIE_S4P_RS Siemens S4P - Readsoft | Q52: =DATEDIF(E52,TODAY(),"d") -> 265 | R52: =IF($Q52>7,1,0) -> 1 | S52: =IF($Q52>30,1,0) -> 1
A53: 6000135668 | B53: INC42504595 | D53: 5975 | E53: 45743 | G53: Simon Kostovski (GBS CEE P2P CZ AP PE 2 / Z003DW1N) | H53: Ulrich Rauch / 81739 Muenchen | I53: 45782 | J53: RFC_FITS | K53: 3: Medium | L53: Confirm_Closed | M53: S4P/3014- Invoices which have posted GR or adjusted prices and posted Invoices are stuck in approver’s workflow | N53: SIE_S4P_RS Siemens S4P - Readsoft | Q53: =DATEDIF(E53,TODAY(),"d") -> 264 | R53: =IF($Q53>7,1,0) -> 1 | S53: =IF($Q53>30,1,0) -> 1
A54: 6000135843 | D54: 7092 | E54: 45744 | G54: Ulrich Rauch (IT ECP ERP-CP ARC2 / Z00060NO) | H54: Ulrich Rauch / 81739 Muenchen | I54: 45759 | J54: SAP SOLUTION MANAGER S1A | K54: 3: Medium | L54: Confirm_Closed | M54: Fix missing purpose code JP in Readsoft GEN table | N54: SIE_S4P_RS Siemens S4P - Readsoft | Q54: =DATEDIF(E54,TODAY(),"d") -> 263 | R54: =IF($Q54>7,1,0) -> 1 | S54: =IF($Q54>30,1,0) -> 1
A55: 6000135916 | B55: INC42521355 | D55: 7092 | E55: 45747 | G55: Jonas Weber (IT DA DO PL / Z003DMKU) | H55: Ulrich Rauch / 81739 Muenchen | I55: 45754 | J55: RFC_FITS | K55: 4: Low | L55: Confirm_Closed | M55: Readsoft - Mailversand nach Query fehlt | N55: SIE_S4P_RS Siemens S4P - Readsoft | Q55: =DATEDIF(E55,TODAY(),"d") -> 260 | R55: =IF($Q55>7,1,0) -> 1 | S55: =IF($Q55>30,1,0) -> 1
A56: 6000135930 | B56: INC42521949 | D56: SRE | E56: 45747 | G56: Tobias Moest (SRE FIN AR 2 / Z000F12V) | H56: Ulrich Rauch / 81739 Muenchen | I56: 45758 | J56: RFC_FITS | K56: 4: Low | L56: Confirm_Closed | M56: S4P 100 - VIM: User erhält keine E-Mail zur Workflow Freigabe | N56: SIE_S4P_RS Siemens S4P - Readsoft | Q56: =DATEDIF(E56,TODAY(),"d") -> 260 | R56: =IF($Q56>7,1,0) -> 1 | S56: =IF($Q56>30,1,0) -> 1
A57: 6000136043 | D57: 7092 | E57: 45748 | G57: Ulrich Rauch (IT ECP ERP-CP ARC2 / Z00060NO) | H57: Kerstin Mueller / 81739 Muenchen | I57: 45786 | J57: SAP SOLUTION MANAGER S1A | K57: 3: Medium | L57: Confirm_Closed | M57: Readsoft: adaption tax code determination | N57: SIE_S4P_RS Siemens S4P - Readsoft | Q57: =DATEDIF(E57,TODAY(),"d") -> 259 | R57: =IF($Q57>7,1,0) -> 1 | S57: =IF($Q57>30,1,0) -> 1
A58: 6000136104 | B58: INC42532842 | D58: 3014 | E58: 45748 | G58: Alina Corina Maresi (DI MC GMC MF-EWN PU-BUZ FIN LOG 1-2 / Z | H58: Ulrich Rauch / 81739 Muenchen | I58: 45755 | J58: RFC_FITS | K58: 3: Medium | L58: Confirm_Closed | M58: No possible to approve the invoices because there is an error in determining the next approver | N58: SIE_S4P_RS Siemens S4P - Readsoft | Q58: =DATEDIF(E58,TODAY(),"d") -> 259 | R58: =IF($Q58>7,1,0) -> 1 | S58: =IF($Q58>30,1,0) -> 1
A59: 6000136206 | B59: INC42539676 | D59: 7411 | E59: 45749 | G59: Mona Sangl (DI MC GMC MF-EWN FIN LOG 1 2 / Z002Z0BD) | H59: Ilona Splichalova | I59: 45798 | J59: RFC_FITS | K59: 3: Medium | L59: Confirm_Closed | M59: Block reason "Over Limit" is not given | N59: SIE_S4P_RS Siemens S4P - Readsoft | Q59: =DATEDIF(E59,TODAY(),"d") -> 258 | R59: =IF($Q59>7,1,0) -> 1 | S59: =IF($Q59>30,1,0) -> 1
A60: 6000136305 | B60: INC42544021 | D60: 3011 | E60: 45749 | G60: Asma Meftah (DI SW EDA MNA / Z003U86H) | H60: Ulrich Rauch / 81739 Muenchen | I60: 45756 | J60: RFC_FITS | K60: 3: Medium | L60: Confirm_Closed | M60: KOFAX shows the following error: User Asma Meftah (Z003U86H) locked | N60: SIE_S4P_RS Siemens S4P - Readsoft | Q60: =DATEDIF(E60,TODAY(),"d") -> 258 | R60: =IF($Q60>7,1,0) -> 1 | S60: =IF($Q60>30,1,0) -> 1
A61: 6000136404 | B61: INC42552933 | D61: 3003 | E61: 45750 | G61: Pavla Tothova (GBS CEE P2P CZ AP 2 3 / Z002NYHT) | H61: Ilona Splichalova | I61: 45764 | J61: RFC_FITS | K61: 3: Medium | L61: Confirm_Closed | M61: S4P/AUN 3003 VIM ID 3471- the document cannot be cancelled | N61: SIE_S4P_RS Siemens S4P - Readsoft | Q61: =DATEDIF(E61,TODAY(),"d") -> 257 | R61: =IF($Q61>7,1,0) -> 1 | S61: =IF($Q61>30,1,0) -> 1
A62: 6000136413 | B62: INC42553406 | D62: SRE | E62: 45750 | G62: Pavla Tothova (GBS CEE P2P CZ AP 2 3 / Z002NYHT) | H62: Ilona Splichalova | I62: 45758 | J62: RFC_FITS | K62: 3: Medium | L62: Confirm_Closed | M62: S4P/7998 - DPs 2977 and 1961 - it's not possible to recall the approval workflows | N62: SIE_S4P_RS Siemens S4P - Readsoft | Q62: =DATEDIF(E62,TODAY(),"d") -> 257 | R62: =IF($Q62>7,1,0) -> 1 | S62: =IF($Q62>30,1,0) -> 1
A63: 6000136417 | B63: INC42553572 | D63: SRE | E63: 45750 | G63: Pavla Tothova (GBS CEE P2P CZ AP 2 3 / Z002NYHT) | H63: Albert Galek | I63: 45758 | J63: RFC_FITS | K63: 3: Medium | L63: Confirm_Closed | M63: S4P/7998 - VIM ID 5352 - approval workflow wasn't started. | N63: SIE_S4P_RS Siemens S4P - Readsoft | Q63: =DATEDIF(E63,TODAY(),"d") -> 257 | R63: =IF($Q63>7,1,0) -> 1 | S63: =IF($Q63>30,1,0) -> 1
A64: 6000136696 | B64: INC42571709 | D64: SRE | E64: 45755 | G64: Pavla Tothova (GBS CEE P2P CZ AP 2 3 / Z002NYHT) | H64: Ilona Splichalova | I64: 45763 | J64: RFC_FITS | K64: 3: Medium | L64: Confirm_Closed | M64: S4P/7998 - DP 2512 - it's not possible to recall the approval workflow | N64: SIE_S4P_RS Siemens S4P - Readsoft | Q64: =DATEDIF(E64,TODAY(),"d") -> 252 | R64: =IF($Q64>7,1,0) -> 1 | S64: =IF($Q64>30,1,0) -> 1
A65: 6000136707 | B65: INC42571588 | D65: SRE | E65: 45755 | G65: Pavla Tothova (GBS CEE P2P CZ AP 2 3 / Z002NYHT) | H65: Ilona Splichalova | I65: 45763 | J65: RFC_FITS | K65: 3: Medium | L65: Confirm_Closed | M65: S4P/7998 - DP 1032 - it's not possible to recall the approval workflow | N65: SIE_S4P_RS Siemens S4P - Readsoft | Q65: =DATEDIF(E65,TODAY(),"d") -> 252 | R65: =IF($Q65>7,1,0) -> 1 | S65: =IF($Q65>30,1,0) -> 1
A66: 6000136806 | D66: 7092 | E66: 45755 | G66: Ulrich Rauch (IT ECP FPS LV / Z00060NO) | H66: Ramesh Itamsetti | I66: 45789 | J66: SAP SOLUTION MANAGER S1A | K66: 3: Medium | L66: Confirm_Closed | M66: VIM: bugfix in GR Wait functionality | N66: SIE_S4P_RS Siemens S4P - Readsoft | Q66: =DATEDIF(E66,TODAY(),"d") -> 252 | R66: =IF($Q66>7,1,0) -> 1 | S66: =IF($Q66>30,1,0) -> 1
A67: 6000136916 | B67: INC42586578 | D67: SRE | E67: 45756 | G67: Pavla Tothova (GBS CEE P2P CZ AP 2 3 / Z002NYHT) | H67: Ilona Splichalova | I67: 45764 | J67: RFC_FITS | K67: 3: Medium | L67: Confirm_Closed | M67: S4P/7998 - problem with approval workflow - VIM ID 4984 und 4985 | N67: SIE_S4P_RS Siemens S4P - Readsoft | Q67: =DATEDIF(E67,TODAY(),"d") -> 251 | R67: =IF($Q67>7,1,0) -> 1 | S67: =IF($Q67>30,1,0) -> 1
A68: 6000137097 | B68: INC42596308 | D68: 7092 | E68: 45757 | G68: Nadine Huettl (LC IP LTA / Z0005Q3T) | H68: Ulrich Rauch / 81739 Muenchen | I68: 45765 | J68: RFC_FITS | K68: 4: Low | L68: Confirm_Closed | M68: Freigabe von Rechnungen nicht möglich (ARE 5811) | N68: SIE_S4P_RS Siemens S4P - Readsoft | Q68: =DATEDIF(E68,TODAY(),"d") -> 250 | R68: =IF($Q68>7,1,0) -> 1 | S68: =IF($Q68>30,1,0) -> 1
A69: 6000137324 | B69: INC42614440 | D69: 3014 | E69: 45761 | G69: Alina Corina Maresi (DI MC GMC MF-EWN PU-BUZ FIN LOG 1-2 / Z | H69: Ulrich Rauch / 81739 Muenchen | I69: 45771 | J69: RFC_FITS | K69: 2: High | L69: Confirm_Closed | M69: Error on approval invoices in "My inbox" VIM AUN 3014 | N69: SIE_S4P_RS Siemens S4P - Readsoft | Q69: =DATEDIF(E69,TODAY(),"d") -> 246 | R69: =IF($Q69>7,1,0) -> 1 | S69: =IF($Q69>30,1,0) -> 1
A70: 6000137341 | B70: INC42614781 | D70: 7092 | E70: 45761 | G70: Fabian Schmitzer (IT DA DO E / Z001WYFH) | H70: Ilona Splichalova | I70: 45768 | J70: RFC_FITS | K70: 4: Low | L70: Confirm_Closed | M70: No access to my S4P 100 / Webcycle list of documents | N70: SIE_S4P_RS Siemens S4P - Readsoft | Q70: =DATEDIF(E70,TODAY(),"d") -> 246 | R70: =IF($Q70>7,1,0) -> 1 | S70: =IF($Q70>30,1,0) -> 1
A71: 6000137533 | D71: 3008 | E71: 45762 | G71: Ulrich Rauch (IT ECP FPS LV / Z00060NO) | H71: Ilona Splichalova | I71: 45782 | J71: SAP SOLUTION MANAGER S1A | K71: 3: Medium | L71: Confirm_Closed | M71: VIM: DP 3924 block removed with single appr.step | N71: SIE_S4P_RS Siemens S4P - Readsoft | Q71: =DATEDIF(E71,TODAY(),"d") -> 245 | R71: =IF($Q71>7,1,0) -> 1 | S71: =IF($Q71>30,1,0) -> 1
A72: 6000137544 | B72: INC42625312 | D72: 3003 | E72: 45762 | G72: Tobias Moest (SRE FIN AR 2 / Z000F12V) | H72: Ulrich Rauch / 81739 Muenchen | I72: 45821 | J72: RFC_FITS | K72: 4: Low | L72: Confirm_Closed | M72: S4P 100 VIM - Selektion in VIM Analytics fehlerhaft | N72: SIE_S4P_RS Siemens S4P - Readsoft | Q72: =DATEDIF(E72,TODAY(),"d") -> 245 | R72: =IF($Q72>7,1,0) -> 1 | S72: =IF($Q72>30,1,0) -> 1
A73: 6000137636 | B73: INC42632582 | D73: 3014 | E73: 45763 | G73: Andrei Vulpescu (DI MC GMC MF-EWN PU-BUZ FIN / Z00172BA) | H73: Albert Galek | I73: 45782 | J73: RFC_FITS | K73: 2: High | L73: Confirm_Closed | M73: I cannot approve invoice due to error | N73: SIE_S4P_RS Siemens S4P - Readsoft | Q73: =DATEDIF(E73,TODAY(),"d") -> 244 | R73: =IF($Q73>7,1,0) -> 1 | S73: =IF($Q73>30,1,0) -> 1
A74: 6000137924 | B74: INC42657410 | D74: 5975 | E74: 45769 | G74: Libor Pas (GBS CEE P2P CZ SC 2 8 / Z004VCDA) | H74: Albert Galek | I74: 45782 | J74: RFC_FITS | K74: 4: Low | L74: Confirm_Closed | M74: proces blocked | N74: SIE_S4P_RS Siemens S4P - Readsoft | Q74: =DATEDIF(E74,TODAY(),"d") -> 238 | R74: =IF($Q74>7,1,0) -> 1 | S74: =IF($Q74>30,1,0) -> 1
A75: 6000138263 | D75: 3014 | E75: 45771 | G75: Albert Galek (IT ECP FPS LV / Z004W53N) | H75: Ilona Splichalova | I75: 45820 | J75: Ramesh Itamsetti | K75: 3: Medium | L75: In Process | M75: Please check below DPs ald close approval WF if needed | N75: SIE_S4P_RS Siemens S4P - Readsoft | Q75: =DATEDIF(E75,TODAY(),"d") -> 236 | R75: =IF($Q75>7,1,0) -> 1 | S75: =IF($Q75>30,1,0) -> 1
A76: 6000138316 | B76: INC42678209 | D76: SRE | E76: 45772 | G76: Pavla Tothova (GBS CEE P2P CZ AP 2 3 / Z002NYHT) | H76: Ilona Splichalova | I76: 45779 | J76: RFC_FITS | K76: 3: Medium | L76: Confirm_Closed | M76: S4P/7998 - VIM 6944 - it's not possible to recall the approval workflow and send it to a specific person | N76: SIE_S4P_RS Siemens S4P - Readsoft | Q76: =DATEDIF(E76,TODAY(),"d") -> 235 | R76: =IF($Q76>7,1,0) -> 1 | S76: =IF($Q76>30,1,0) -> 1
A77: 6000138428 | B77: INC42684362 | D77: SRE | E77: 45772 | G77: Pavla Tothova (GBS CEE P2P CZ AP 2 3 / Z002NYHT) | H77: Ulrich Rauch / 81739 Muenchen | I77: 45820 | J77: Ramesh Itamsetti | K77: 4: Low | L77: In Process | M77: S4P/7998 - VIM ID 6783 - approval workflow wasn't started | N77: SIE_S4P_RS Siemens S4P - Readsoft | Q77: =DATEDIF(E77,TODAY(),"d") -> 235 | R77: =IF($Q77>7,1,0) -> 1 | S77: =IF($Q77>30,1,0) -> 1
A78: 6000138437 | B78: INC42684231 | D78: SRE | E78: 45772 | G78: Pavla Tothova (GBS CEE P2P CZ AP 2 3 / Z002NYHT) | H78: Ilona Splichalova | I78: 45807 | J78: Ilona Splichalova | K78: 3: Medium | L78: In Process | M78: S4P/7998 - VIM ID 6829 - approval workflow wasn't started | N78: SIE_S4P_RS Siemens S4P - Readsoft | Q78: =DATEDIF(E78,TODAY(),"d") -> 235 | R78: =IF($Q78>7,1,0) -> 1 | S78: =IF($Q78>30,1,0) -> 1
A79: 6000138440 | B79: INC42684494 | D79: SRE | E79: 45772 | G79: Pavla Tothova (GBS CEE P2P CZ AP 2 3 / Z002NYHT) | H79: Ilona Splichalova | I79: 45786 | J79: RFC_FITS | K79: 4: Low | L79: Confirm_Closed | M79: S4P/7998 - VIM ID 6579 - twice in the system, cleared, but situated in My inbox | N79: SIE_S4P_RS Siemens S4P - Readsoft | Q79: =DATEDIF(E79,TODAY(),"d") -> 235 | R79: =IF($Q79>7,1,0) -> 1 | S79: =IF($Q79>30,1,0) -> 1
A80: 6000138481 | B80: INC42689919 | D80: 5975 | E80: 45775 | G80: Jitka Krnavkova (GBS CEE P2P CZ AP 2 4 / Z002HBHS) | H80: Ilona Splichalova | I80: 45786 | J80: RFC_FITS | K80: 3: Medium | L80: Confirm_Closed | M80: Permissions to removing od payment block X from RS | N80: SIE_S4P_RS Siemens S4P - Readsoft | Q80: =DATEDIF(E80,TODAY(),"d") -> 232 | R80: =IF($Q80>7,1,0) -> 1 | S80: =IF($Q80>30,1,0) -> 1
A81: 6000138500 | B81: INC42690787 | D81: SRE | E81: 45775 | G81: Zdenek Cifka (GBS CEE P2P CZ AP 2 3 / Z003JPCS) | H81: Ulrich Rauch / 81739 Muenchen | I81: 45825 | J81: Ulrich Rauch | K81: 3: Medium | L81: Proposed Solution | M81: S4P / It's not possible to start approval workflow for VIM ID 6022 and 6129 (company code 3003) | N81: SIE_S4P_RS Siemens S4P - Readsoft | Q81: =DATEDIF(E81,I81,"d") -> 50 | R81: =IF($Q81>7,1,0) -> 1 | S81: =IF($Q81>30,1,0) -> 1
A82: 6000138582 | B82: INC42694021 | D82: 5975 | E82: 45775 | G82: Pavel Mego (GBS CEE P2P CZ AP 2 4 / Z001SCDJ) | H82: Ilona Splichalova | I82: 45824 | J82: RFC_FITS | K82: 4: Low | L82: Confirm_Closed | M82: not possible to post credit note | N82: SIE_S4P_RS Siemens S4P - Readsoft | Q82: =DATEDIF(E82,TODAY(),"d") -> 232 | R82: =IF($Q82>7,1,0) -> 1 | S82: =IF($Q82>30,1,0) -> 1
A83: 6000138600 | B83: INC42694920 | D83: 3014 | E83: 45775 | G83: Marcus Pfau (DI MC GMC MF-EWN PU-BUZ QM&EHS / Z004UA4Y) | H83: Ilona Splichalova | I83: 45812 | J83: RFC_FITS | K83: 3: Medium | L83: Confirm_Closed | M83: Invoice already approved by the user | N83: SIE_S4P_RS Siemens S4P - Readsoft | Q83: =DATEDIF(E83,TODAY(),"d") -> 232 | R83: =IF($Q83>7,1,0) -> 1 | S83: =IF($Q83>30,1,0) -> 1
A84: 6000138844 | B84: INC42711347 | D84: 5975 | E84: 45777 | G84: Jitka Krnavkova (GBS CEE P2P CZ AP 2 4 / Z002HBHS) | H84: Ilona Splichalova | I84: 45807 | J84: SAP SOLUTION MANAGER S1A | K84: 3: Medium | L84: Confirm_Closed | M84: Permission for removing payment block X | N84: SIE_S4P_RS Siemens S4P - Readsoft | Q84: =DATEDIF(E84,TODAY(),"d") -> 230 | R84: =IF($Q84>7,1,0) -> 1 | S84: =IF($Q84>30,1,0) -> 1
A85: 6000138916 | D85: 5975 | E85: 45779 | G85: Ilona Splichalova (DI IT ERP CZ FICO / Z002Z2VA) | H85: Ilona Splichalova | I85: 45817 | J85: SAP SOLUTION MANAGER S1A | K85: 3: Medium | L85: Confirm_Closed | M85: Reminders not generated for Approvers | N85: SIE_S4P_RS Siemens S4P - Readsoft | Q85: =DATEDIF(E85,TODAY(),"d") -> 228 | R85: =IF($Q85>7,1,0) -> 1 | S85: =IF($Q85>30,1,0) -> 1
A86: 6000139044 | B86: INC42725740 | D86: SRE | E86: 45782 | G86: Pavla Tothova (GBS CEE P2P CZ AP 2 3 / Z002NYHT) | H86: Ulrich Rauch / 81739 Muenchen | I86: 45805 | J86: RFC_FITS | K86: 3: Medium | L86: Confirm_Closed | M86: S4P/7998 - problem with approval workflow - VIM ID 4985 | N86: SIE_S4P_RS Siemens S4P - Readsoft | Q86: =DATEDIF(E86,TODAY(),"d") -> 225 | R86: =IF($Q86>7,1,0) -> 1 | S86: =IF($Q86>30,1,0) -> 1
A87: 6000139205 | B87: INC42735561 | D87: 5975 | E87: 45783 | G87: Ivana Tomisova (GBS CEE P2P CZ AP 3 2 / Z004PK7A) | H87: Ulrich Rauch / 81739 Muenchen | I87: 45812 | J87: RFC_FITS | K87: 4: Low | L87: Confirm_Closed | M87: 3014 – Freight order - Doc ID 6183 stucked and not possible to post it | N87: SIE_S4P_RS Siemens S4P - Readsoft | Q87: =DATEDIF(E87,TODAY(),"d") -> 224 | R87: =IF($Q87>7,1,0) -> 1 | S87: =IF($Q87>30,1,0) -> 1
A88: 6000139326 | B88: INC42743833 | D88: 7040 | E88: 45784 | G88: Nicole Oulik (SI S MK / Z0005O5V) | H88: Ilona Splichalova | I88: 45791 | J88: RFC_FITS | K88: 3: Medium | L88: Confirm_Closed | M88: Work cycle login not possible, | N88: SIE_S4P_RS Siemens S4P - Readsoft | Q88: =DATEDIF(E88,TODAY(),"d") -> 223 | R88: =IF($Q88>7,1,0) -> 1 | S88: =IF($Q88>30,1,0) -> 1
A89: 6000139329 | B89: INC42744162 | D89: 5975 | E89: 45784 | G89: Martina Cajtchamlova (GBS CEE P2P CZ AP PE 2 / Z002M3FD) | H89: Albert Galek | I89: 45812 | J89: RFC_FITS | K89: 4: Low | L89: Confirm_Closed | M89: Bug fix for OpenText development - activate SHKZG field for VX_PO documents for tab Line Items - G/L Account | N89: SIE_S4P_RS Siemens S4P - Readsoft | Q89: =DATEDIF(E89,TODAY(),"d") -> 223 | R89: =IF($Q89>7,1,0) -> 1 | S89: =IF($Q89>30,1,0) -> 1
A90: 6000139369 | B90: INC42747521 | D90: SRE | E90: 45785 | G90: Pavla Tothova (GBS CEE P2P CZ AP 2 3 / Z002NYHT) | H90: Mr. Mukthar Baig | I90: 45818 | J90: Mukthar Baig | K90: 3: Medium | L90: In Process | M90: S4P/7998 - VIM ID 3854 and VIM ID 7194 | N90: SIE_S4P_RS Siemens S4P - Readsoft | Q90: =DATEDIF(E90,TODAY(),"d") -> 222 | R90: =IF($Q90>7,1,0) -> 1 | S90: =IF($Q90>30,1,0) -> 1
A91: 6000139374 | D91: SRE | E91: 45784 | G91: Ulrich Rauch (IT ECP FPS LV / Z00060NO) | H91: Albert Galek | I91: 45807 | J91: Albert Galek | K91: 3: Medium | L91: In Process | M91: VIM: DP No. missing in My Approved Invoices App | N91: SIE_S4P_RS Siemens S4P - Readsoft | Q91: =DATEDIF(E91,TODAY(),"d") -> 223 | R91: =IF($Q91>7,1,0) -> 1 | S91: =IF($Q91>30,1,0) -> 1
A92: 6000139577 | B92: INC42760716 | D92: 7092 | E92: 45786 | G92: Judith Kraus (CF R 7 4 5 / Z004MKEC) | H92: Ulrich Rauch / 81739 Muenchen | I92: 45793 | J92: RFC_FITS | K92: 2: High | L92: Confirm_Closed | M92: ARE 7040 S4P Buchungsperiode 007 2025 noch nicht geöffnet | N92: SIE_S4P_RS Siemens S4P - Readsoft | Q92: =DATEDIF(E92,TODAY(),"d") -> 221 | R92: =IF($Q92>7,1,0) -> 1 | S92: =IF($Q92>30,1,0) -> 1
A93: 6000139584 | B93: INC42760154 | D93: SRE | E93: 45786 | G93: Pavla Tothova (GBS CEE P2P CZ AP 2 3 / Z002NYHT) | H93: Ulrich Rauch / 81739 Muenchen | I93: 45797 | J93: RFC_FITS | K93: 3: Medium | L93: Confirm_Closed | M93: S4P/7998 - VIM ID 2977 and VIM ID 1961 - the invoices in "VIM completed" without approval | N93: SIE_S4P_RS Siemens S4P - Readsoft | Q93: =DATEDIF(E93,TODAY(),"d") -> 221 | R93: =IF($Q93>7,1,0) -> 1 | S93: =IF($Q93>30,1,0) -> 1
A94: 6000139600 | B94: INC42760922 | D94: SRE | E94: 45786 | G94: Pavla Tothova (GBS CEE P2P CZ AP 2 3 / Z002NYHT) | H94: Albert Galek | I94: 45811 | J94: RFC_FITS | K94: 2: High | L94: Confirm_Closed | M94: S4P/7998 - approval workflows not started | N94: SIE_S4P_RS Siemens S4P - Readsoft | Q94: =DATEDIF(E94,TODAY(),"d") -> 221 | R94: =IF($Q94>7,1,0) -> 1 | S94: =IF($Q94>30,1,0) -> 1
A95: 6000139702 | D95: 7092 | E95: 45789 | G95: Ulrich Rauch (IT ECP FPS LV / Z00060NO) | H95: Albert Galek | I95: 45810 | J95: SAP SOLUTION MANAGER S1A | K95: 2: High | L95: Confirm_Closed | M95: VIM: receiver_function_module with outdated status in S4P | N95: SIE_S4P_RS Siemens S4P - Readsoft | Q95: =DATEDIF(E95,TODAY(),"d") -> 218 | R95: =IF($Q95>7,1,0) -> 1 | S95: =IF($Q95>30,1,0) -> 1
A96: 6000139704 | B96: INC42769267 | D96: 7092 | E96: 45789 | G96: Wolfgang Geitner (DI IT FA UIT / Z00213NZ) | H96: Ilona Splichalova | I96: 45797 | J96: RFC_FITS | K96: 4: Low | L96: Confirm_Closed | M96: Ich benötige Zugang zum S4-Line-Service. | N96: SIE_S4P_RS Siemens S4P - Readsoft | Q96: =DATEDIF(E96,TODAY(),"d") -> 218 | R96: =IF($Q96>7,1,0) -> 1 | S96: =IF($Q96>30,1,0) -> 1
A97: 6000139963 | B97: INC42783591 | D97: 3003 | E97: 45791 | G97: Tobias Moest (SRE FIN AR 2 / Z000F12V) | H97: Kerstin Mueller / 81739 Muenchen | I97: 45805 | J97: RFC_FITS | K97: 2: High | L97: Confirm_Closed | M97: S4P VIM - Fehlermeldung bei Aufruf der Approval App | N97: SIE_S4P_RS Siemens S4P - Readsoft | Q97: =DATEDIF(E97,TODAY(),"d") -> 216 | R97: =IF($Q97>7,1,0) -> 1 | S97: =IF($Q97>30,1,0) -> 1
A98: 6000139986 | B98: INC42784591 | D98: SRE | E98: 45791 | G98: Zdenek Cifka (GBS CEE P2P CZ AP 2 3 / Z003JPCS) | H98: Albert Galek | I98: 45805 | J98: RFC_FITS | K98: 2: High | L98: Confirm_Closed | M98: S4P / It's not possible to use VIM Workplace, because there an ABAP error occurs | N98: SIE_S4P_RS Siemens S4P - Readsoft | Q98: =DATEDIF(E98,TODAY(),"d") -> 216 | R98: =IF($Q98>7,1,0) -> 1 | S98: =IF($Q98>30,1,0) -> 1
A99: 6000140063 | B99: INC42788004 | D99: 5975 | E99: 45792 | G99: Jitka Krnavkova (GBS CEE P2P CZ AP 2 4 / Z002HBHS) | H99: Ilona Splichalova | I99: 45806 | J99: RFC_FITS | K99: 3: Medium | L99: In Process | M99: T-CODE /COCKPIT/WC | N99: SIE_S4P_RS Siemens S4P - Readsoft | Q99: =DATEDIF(E99,TODAY(),"d") -> 215 | R99: =IF($Q99>7,1,0) -> 1 | S99: =IF($Q99>30,1,0) -> 1
A100: 6000140103 | B100: INC42791427 | D100: 3014 | E100: 45792 | G100: Juliana Batya Dora Ciupe (DI MC GMC MF-EWN PU-BUZ FIN BC / Z | H100: Albert Galek | I100: 45800 | J100: RFC_FITS | K100: 2: High | L100: Confirm_Closed | M100: VIM and Invoice approval app errors | N100: SIE_S4P_RS Siemens S4P - Readsoft | Q100: =DATEDIF(E100,TODAY(),"d") -> 215 | R100: =IF($Q100>7,1,0) -> 1 | S100: =IF($Q100>30,1,0) -> 1
...

Sheet VIM-Incidents_W26(June26)
A1: ID | B1: FutureNow Ticket | C1: External ID | D1: ARE | E1: Created On | F1: Due by | G1: Reported By | H1: Message Processor | I1: Last Changed on | J1: Last Changed By | K1: Priority | L1: Status | M1: Description | N1: Support Team | O1: System ID | Q1: Open Days | R1: Open 7D+ | S1: Open 15D+ | T1: Open 30D+ | U1: Open 60D+
A2: 6000127070 | B2: INC41987224 | D2: 5975 | E2: 45663 | G2: Lenka Michalusova (GBS CEE P2P CZ AP 2 4 / Z002HBHR) | H2: Ulrich Rauch / 81739 Muenchen | I2: 45727 | J2: RFC_FITS | K2: 4: Low | L2: Confirm_Closed | M2: VIM- missing tax code | N2: SIE_S4P_RS Siemens S4P - Readsoft | Q2: =IF(OR(ISNUMBER(MATCH(L2,MasterData!$D$3:$D$18,0)),ISNUMBER(MATCH(L2,MasterData!$C$3:$C$18,0))), DATEDIF(E2,I2,"d"), DATEDIF(E2,TODAY(),"d")) -> 64 | R2: =IF($Q2>7,1,0) -> 1 | S2: =IF($Q2>15,1,0) -> 1 | T2: =IF($Q2>30,1,0) -> 1 | U2: =IF($Q2>60,1,0) -> 1
A3: 6000127209 | B3: INC41997245 | D3: 5975 | E3: 45664 | G3: Simon Kostovski (GBS CEE P2P CZ AP 3 2 / Z003DW1N) | H3: Albert Galek | I3: 45673 | J3: RFC_FITS | K3: 3: Medium | L3: Confirm_Closed | M3: INC41861079 not solved but it was closed | N3: SIE_S4P_RS Siemens S4P - Readsoft | Q3: =IF(OR(ISNUMBER(MATCH(L3,MasterData!$D$3:$D$18,0)),ISNUMBER(MATCH(L3,MasterData!$C$3:$C$18,0))), DATEDIF(E3,I3,"d"), DATEDIF(E3,TODAY(),"d")) -> 9 | R3: =IF($Q3>7,1,0) -> 1 | S3: =IF($Q3>15,1,0) -> 0 | T3: =IF($Q3>30,1,0) -> 0 | U3: =IF($Q3>60,1,0) -> 0
A4: 6000127632 | B4: INC42022656 | D4: 5975 | E4: 45667 | G4: Barbora Struskova (GBS CEE P2P CZ AP 2 4 / Z002HZ1U) | H4: Ilona Splichalova | I4: 45679 | J4: RFC_FITS | K4: 4: Low | L4: Confirm_Closed | M4: automatic text | N4: SIE_S4P_RS Siemens S4P - Readsoft | Q4: =IF(OR(ISNUMBER(MATCH(L4,MasterData!$D$3:$D$18,0)),ISNUMBER(MATCH(L4,MasterData!$C$3:$C$18,0))), DATEDIF(E4,I4,"d"), DATEDIF(E4,TODAY(),"d")) -> 12 | R4: =IF($Q4>7,1,0) -> 1 | S4: =IF($Q4>15,1,0) -> 0 | T4: =IF($Q4>30,1,0) -> 0 | U4: =IF($Q4>60,1,0) -> 0
A5: 6000128352 | D5: 3003 | E5: 45674 | G5: Ilona Splichalova (DI IT ERP CZ FICO / Z002Z2VA) | H5: Albert Galek | I5: 45688 | J5: SAP SOLUTION MANAGER S1A | K5: 3: Medium | L5: Confirm_Closed | M5: DP 2807 in S4P: please check the status | N5: SIE_S4P_RS Siemens S4P - Readsoft | Q5: =IF(OR(ISNUMBER(MATCH(L5,MasterData!$D$3:$D$18,0)),ISNUMBER(MATCH(L5,MasterData!$C$3:$C$18,0))), DATEDIF(E5,I5,"d"), DATEDIF(E5,TODAY(),"d")) -> 14 | R5: =IF($Q5>7,1,0) -> 1 | S5: =IF($Q5>15,1,0) -> 0 | T5: =IF($Q5>30,1,0) -> 0 | U5: =IF($Q5>60,1,0) -> 0
A6: 6000128500 | B6: INC42075263 | D6: 7092 | E6: 45677 | G6: Lena Osterhus (CE SEC TPC / Z001MA1B) | H6: Ilona Splichalova | I6: 45684 | J6: RFC_FITS | K6: 4: Low | L6: Confirm_Closed | M6: Falsche Emailadresse bei Readsoft/ WebCycle | N6: SIE_S4P_RS Siemens S4P - Readsoft | Q6: =IF(OR(ISNUMBER(MATCH(L6,MasterData!$D$3:$D$18,0)),ISNUMBER(MATCH(L6,MasterData!$C$3:$C$18,0))), DATEDIF(E6,I6,"d"), DATEDIF(E6,TODAY(),"d")) -> 7 | R6: =IF($Q6>7,1,0) -> 0 | S6: =IF($Q6>15,1,0) -> 0 | T6: =IF($Q6>30,1,0) -> 0 | U6: =IF($Q6>60,1,0) -> 0
A7: 6000128546 | B7: INC42077895 | D7: SRE | E7: 45677 | G7: Zdenek Cifka (GBS CEE P2P CZ AP 2 3 / Z003JPCS) | H7: Ilona Splichalova | I7: 45833 | J7: Ulrich Rauch | K7: 3: Medium | L7: Postponed | M7: VIM ID's 2391 and 2623 - after posting the payment block was'nt entered and approval workflow was'nt started | N7: SIE_S4P_RS Siemens S4P - Readsoft | Q7: =IF(OR(ISNUMBER(MATCH(L7,MasterData!$D$3:$D$18,0)),ISNUMBER(MATCH(L7,MasterData!$C$3:$C$18,0))), DATEDIF(E7,I7,"d"), DATEDIF(E7,TODAY(),"d")) -> 330 | R7: =IF($Q7>7,1,0) -> 1 | S7: =IF($Q7>15,1,0) -> 1 | T7: =IF($Q7>30,1,0) -> 1 | U7: =IF($Q7>60,1,0) -> 1
A8: 6000128759 | B8: INC42093959 | D8: 7092 | E8: 45679 | G8: Andreas Mengele (MAP DF&PCM PCM / Z001THRJ) | H8: Ilona Splichalova | I8: 45686 | J8: RFC_FITS | K8: 4: Low | L8: Confirm_Closed | M8: Umstellung der Rechte von Susanne Spiegl auf Philipp Rath | N8: SIE_S4P_RS Siemens S4P - Readsoft | Q8: =IF(OR(ISNUMBER(MATCH(L8,MasterData!$D$3:$D$18,0)),ISNUMBER(MATCH(L8,MasterData!$C$3:$C$18,0))), DATEDIF(E8,I8,"d"), DATEDIF(E8,TODAY(),"d")) -> 7 | R8: =IF($Q8>7,1,0) -> 0 | S8: =IF($Q8>15,1,0) -> 0 | T8: =IF($Q8>30,1,0) -> 0 | U8: =IF($Q8>60,1,0) -> 0
A9: 6000129022 | B9: INC42106952 | D9: 5975 | E9: 45680 | G9: Renata Staricna (GBS CEE P2P CZ AP 2 4 / Z0046K6B) | H9: Ilona Splichalova | I9: 45705 | J9: RFC_FITS | K9: 4: Low | L9: Confirm_Closed | M9: Reminder - automatic answers | N9: SIE_S4P_RS Siemens S4P - Readsoft | Q9: =IF(OR(ISNUMBER(MATCH(L9,MasterData!$D$3:$D$18,0)),ISNUMBER(MATCH(L9,MasterData!$C$3:$C$18,0))), DATEDIF(E9,I9,"d"), DATEDIF(E9,TODAY(),"d")) -> 25 | R9: =IF($Q9>7,1,0) -> 1 | S9: =IF($Q9>15,1,0) -> 1 | T9: =IF($Q9>30,1,0) -> 0 | U9: =IF($Q9>60,1,0) -> 0
A10: 6000129245 | B10: INC42120663 | D10: 7092 | E10: 45684 | G10: Veronika Andres (IT ECP FPS T&CS / Z0029JJZ) | H10: Ilona Splichalova | I10: 45691 | J10: RFC_FITS | K10: 4: Low | L10: Confirm_Closed | M10: WebCycle User locked | N10: SIE_S4P_RS Siemens S4P - Readsoft | Q10: =IF(OR(ISNUMBER(MATCH(L10,MasterData!$D$3:$D$18,0)),ISNUMBER(MATCH(L10,MasterData!$C$3:$C$18,0))), DATEDIF(E10,I10,"d"), DATEDIF(E10,TODAY(),"d")) -> 7 | R10: =IF($Q10>7,1,0) -> 0 | S10: =IF($Q10>15,1,0) -> 0 | T10: =IF($Q10>30,1,0) -> 0 | U10: =IF($Q10>60,1,0) -> 0
A11: 6000129304 | B11: INC42122188 | D11: SRE | E11: 45684 | G11: Tobias Moest (SRE FIN AR 2 / Z000F12V) | H11: Albert Galek | I11: 45693 | J11: RFC_FITS | K11: 4: Low | L11: Confirm_Closed | M11: S4P 100 - VIM: Vorgang aus Klärungs-WF nicht vorhanden | N11: SIE_S4P_RS Siemens S4P - Readsoft | Q11: =IF(OR(ISNUMBER(MATCH(L11,MasterData!$D$3:$D$18,0)),ISNUMBER(MATCH(L11,MasterData!$C$3:$C$18,0))), DATEDIF(E11,I11,"d"), DATEDIF(E11,TODAY(),"d")) -> 9 | R11: =IF($Q11>7,1,0) -> 1 | S11: =IF($Q11>15,1,0) -> 0 | T11: =IF($Q11>30,1,0) -> 0 | U11: =IF($Q11>60,1,0) -> 0
A12: 6000129653 | D12: 3003 | E12: 45686 | G12: Ilona Splichalova (DI IT ERP CZ FICO / Z002Z2VA) | H12: Ilona Splichalova | I12: 45782 | J12: SAP SOLUTION MANAGER S1A | K12: 3: Medium | L12: Confirm_Closed | M12: VIM 2756 und 2774 - Error by 3 step approval WF by Construction Invoices | N12: SIE_S4P_RS Siemens S4P - Readsoft | Q12: =IF(OR(ISNUMBER(MATCH(L12,MasterData!$D$3:$D$18,0)),ISNUMBER(MATCH(L12,MasterData!$C$3:$C$18,0))), DATEDIF(E12,I12,"d"), DATEDIF(E12,TODAY(),"d")) -> 96 | R12: =IF($Q12>7,1,0) -> 1 | S12: =IF($Q12>15,1,0) -> 1 | T12: =IF($Q12>30,1,0) -> 1 | U12: =IF($Q12>60,1,0) -> 1
A13: 6000129990 | B13: INC42154604 | D13: SRE | E13: 45688 | G13: Zdenek Cifka (GBS CEE P2P CZ AP 2 3 / Z003JPCS) | H13: Albert Galek | I13: 45699 | J13: RFC_FITS | K13: 3: Medium | L13: Confirm_Closed | M13: Is not possible to start the approval workflow for VIM ID 2515 | N13: SIE_S4P_RS Siemens S4P - Readsoft | Q13: =IF(OR(ISNUMBER(MATCH(L13,MasterData!$D$3:$D$18,0)),ISNUMBER(MATCH(L13,MasterData!$C$3:$C$18,0))), DATEDIF(E13,I13,"d"), DATEDIF(E13,TODAY(),"d")) -> 11 | R13: =IF($Q13>7,1,0) -> 1 | S13: =IF($Q13>15,1,0) -> 0 | T13: =IF($Q13>30,1,0) -> 0 | U13: =IF($Q13>60,1,0) -> 0
A14: 6000130122 | B14: INC42161605 | D14: 3014 | E14: 45691 | G14: Pompilia Bianca Trifa (DI MC GMC MF-EWN PU-BUZ FIN LOG 1-2 / | H14: Ulrich Rauch / 81739 Muenchen | I14: 45708 | J14: RFC_FITS | K14: 3: Medium | L14: Confirm_Closed | M14: S4P VIM - Invoices in Approval steps (direct materials) not visible to the approver | N14: SIE_S4P_RS Siemens S4P - Readsoft | Q14: =IF(OR(ISNUMBER(MATCH(L14,MasterData!$D$3:$D$18,0)),ISNUMBER(MATCH(L14,MasterData!$C$3:$C$18,0))), DATEDIF(E14,I14,"d"), DATEDIF(E14,TODAY(),"d")) -> 17 | R14: =IF($Q14>7,1,0) -> 1 | S14: =IF($Q14>15,1,0) -> 1 | T14: =IF($Q14>30,1,0) -> 0 | U14: =IF($Q14>60,1,0) -> 0
A15: 6000130131 | B15: INC42161726 | D15: 3014 | E15: 45691 | G15: Andreea Laura Boran (DI MC GMC MF-EWN PU-BUZ FIN LOG 1-2 / Z | H15: Ulrich Rauch / 81739 Muenchen | I15: 45708 | J15: RFC_FITS | K15: 3: Medium | L15: Confirm_Closed | M15: S4P - VIM error in invoice approval | N15: SIE_S4P_RS Siemens S4P - Readsoft | Q15: =IF(OR(ISNUMBER(MATCH(L15,MasterData!$D$3:$D$18,0)),ISNUMBER(MATCH(L15,MasterData!$C$3:$C$18,0))), DATEDIF(E15,I15,"d"), DATEDIF(E15,TODAY(),"d")) -> 17 | R15: =IF($Q15>7,1,0) -> 1 | S15: =IF($Q15>15,1,0) -> 1 | T15: =IF($Q15>30,1,0) -> 0 | U15: =IF($Q15>60,1,0) -> 0
A16: 6000130842 | B16: INC42203263 | D16: 3003 | E16: 45698 | G16: Helge Preiss (SRE DP PM EU / Z001WZ3K) | H16: Albert Galek | I16: 45831 | J16: RFC_FITS | K16: 3: Medium | L16: Confirm_Closed | M16: S4P VIM FIORI Approval Invoice Management Fehlermeldung | N16: SIE_S4P_RS Siemens S4P - Readsoft | Q16: =IF(OR(ISNUMBER(MATCH(L16,MasterData!$D$3:$D$18,0)),ISNUMBER(MATCH(L16,MasterData!$C$3:$C$18,0))), DATEDIF(E16,I16,"d"), DATEDIF(E16,TODAY(),"d")) -> 133 | R16: =IF($Q16>7,1,0) -> 1 | S16: =IF($Q16>15,1,0) -> 1 | T16: =IF($Q16>30,1,0) -> 1 | U16: =IF($Q16>60,1,0) -> 1
A17: 6000130889 | B17: INC42205466 | D17: 7092 | E17: 45698 | G17: Laura Hochwind (IT ECP FPS AP1 / Z003NVNW) | H17: Ulrich Rauch / 81739 Muenchen | I17: 45705 | J17: RFC_FITS | K17: 3: Medium | L17: Confirm_Closed | M17: Add Substitute for Webcycle Readsoft | N17: SIE_S4P_RS Siemens S4P - Readsoft | Q17: =IF(OR(ISNUMBER(MATCH(L17,MasterData!$D$3:$D$18,0)),ISNUMBER(MATCH(L17,MasterData!$C$3:$C$18,0))), DATEDIF(E17,I17,"d"), DATEDIF(E17,TODAY(),"d")) -> 7 | R17: =IF($Q17>7,1,0) -> 0 | S17: =IF($Q17>15,1,0) -> 0 | T17: =IF($Q17>30,1,0) -> 0 | U17: =IF($Q17>60,1,0) -> 0
A18: 6000131438 | B18: INC42234456 | D18: 3003 | E18: 45701 | G18: Mario Beck (SRE DP PM EU / Z00109RY) | H18: Ramesh Itamsetti | I18: 45831 | J18: RFC_FITS | K18: 3: Medium | L18: Confirm_Closed | M18: S4P 100 VIM - Fehlermeldung bei WF-Freigabe | N18: SIE_S4P_RS Siemens S4P - Readsoft | Q18: =IF(OR(ISNUMBER(MATCH(L18,MasterData!$D$3:$D$18,0)),ISNUMBER(MATCH(L18,MasterData!$C$3:$C$18,0))), DATEDIF(E18,I18,"d"), DATEDIF(E18,TODAY(),"d")) -> 130 | R18: =IF($Q18>7,1,0) -> 1 | S18: =IF($Q18>15,1,0) -> 1 | T18: =IF($Q18>30,1,0) -> 1 | U18: =IF($Q18>60,1,0) -> 1
A19: 6000131514 | D19: 7092 | E19: 45702 | G19: Ulrich Rauch (IT ECP ERP-CP ARC2 / Z00060NO) | H19: Ulrich Rauch / 81739 Muenchen | I19: 45723 | J19: SAP SOLUTION MANAGER S1A | K19: 3: Medium | L19: Confirm_Closed | M19: VIM: VIM Authorization issue in Exceptions App (mid-term solution) | N19: SIE_S4P_RS Siemens S4P - Readsoft | Q19: =IF(OR(ISNUMBER(MATCH(L19,MasterData!$D$3:$D$18,0)),ISNUMBER(MATCH(L19,MasterData!$C$3:$C$18,0))), DATEDIF(E19,I19,"d"), DATEDIF(E19,TODAY(),"d")) -> 21 | R19: =IF($Q19>7,1,0) -> 1 | S19: =IF($Q19>15,1,0) -> 1 | T19: =IF($Q19>30,1,0) -> 0 | U19: =IF($Q19>60,1,0) -> 0
A20: 6000131715 | B20: INC42252236 | D20: 5975 | E20: 45705 | G20: Pavel Mego (GBS CEE P2P CZ AP 2 4 / Z001SCDJ) | H20: Ulrich Rauch / 81739 Muenchen | I20: 45713 | J20: RFC_FITS | K20: 4: Low | L20: Confirm_Closed | M20: duplicity check | N20: SIE_S4P_RS Siemens S4P - Readsoft | Q20: =IF(OR(ISNUMBER(MATCH(L20,MasterData!$D$3:$D$18,0)),ISNUMBER(MATCH(L20,MasterData!$C$3:$C$18,0))), DATEDIF(E20,I20,"d"), DATEDIF(E20,TODAY(),"d")) -> 8 | R20: =IF($Q20>7,1,0) -> 1 | S20: =IF($Q20>15,1,0) -> 0 | T20: =IF($Q20>30,1,0) -> 0 | U20: =IF($Q20>60,1,0) -> 0
A21: 6000132000 | B21: INC42270698 | D21: SRE | E21: 45707 | G21: Zdenek Cifka (GBS CEE P2P CZ AP 2 3 / Z003JPCS) | H21: Albert Galek | I21: 45735 | J21: RFC_FITS | K21: 3: Medium | L21: Confirm_Closed | M21: In VIM it is not possible to post the recurring documents, which contain multiple Profit Centers - VIM ID 3988 and 4340 | N21: SIE_S4P_RS Siemens S4P - Readsoft | Q21: =IF(OR(ISNUMBER(MATCH(L21,MasterData!$D$3:$D$18,0)),ISNUMBER(MATCH(L21,MasterData!$C$3:$C$18,0))), DATEDIF(E21,I21,"d"), DATEDIF(E21,TODAY(),"d")) -> 28 | R21: =IF($Q21>7,1,0) -> 1 | S21: =IF($Q21>15,1,0) -> 1 | T21: =IF($Q21>30,1,0) -> 0 | U21: =IF($Q21>60,1,0) -> 0
A22: 6000132651 | B22: INC42313692 | D22: 3003 | E22: 45714 | G22: Mario Beck (SRE DP PM EU / Z00109RY) | H22: Albert Galek | I22: 45723 | J22: RFC_FITS | K22: 4: Low | L22: Confirm_Closed | M22: S4P 100 VIM - #2777 can't be approved (new error message) | N22: SIE_S4P_RS Siemens S4P - Readsoft | Q22: =IF(OR(ISNUMBER(MATCH(L22,MasterData!$D$3:$D$18,0)),ISNUMBER(MATCH(L22,MasterData!$C$3:$C$18,0))), DATEDIF(E22,I22,"d"), DATEDIF(E22,TODAY(),"d")) -> 9 | R22: =IF($Q22>7,1,0) -> 1 | S22: =IF($Q22>15,1,0) -> 0 | T22: =IF($Q22>30,1,0) -> 0 | U22: =IF($Q22>60,1,0) -> 0
A23: 6000133013 | B23: INC42339428 | D23: 5975 | E23: 45719 | G23: Jitka Krnavkova (GBS CEE P2P CZ AP 2 4 / Z002HBHS) | H23: Ilona Splichalova | I23: 45734 | J23: RFC_FITS | K23: 4: Low | L23: Confirm_Closed | M23: Add user to ICFR group_READSOFT | N23: SIE_S4P_RS Siemens S4P - Readsoft | Q23: =IF(OR(ISNUMBER(MATCH(L23,MasterData!$D$3:$D$18,0)),ISNUMBER(MATCH(L23,MasterData!$C$3:$C$18,0))), DATEDIF(E23,I23,"d"), DATEDIF(E23,TODAY(),"d")) -> 15 | R23: =IF($Q23>7,1,0) -> 1 | S23: =IF($Q23>15,1,0) -> 0 | T23: =IF($Q23>30,1,0) -> 0 | U23: =IF($Q23>60,1,0) -> 0
A24: 6000133061 | B24: INC42342340 | D24: SRE | E24: 45719 | G24: Zdenek Cifka (GBS CEE P2P CZ AP 2 3 / Z003JPCS) | H24: Ilona Splichalova | I24: 45735 | J24: RFC_FITS | K24: 3: Medium | L24: Confirm_Closed | M24: VIM ID 1785 - approval workflow wasn't started but nevertheless is situated in VIM WP in My pending section | N24: SIE_S4P_RS Siemens S4P - Readsoft | Q24: =IF(OR(ISNUMBER(MATCH(L24,MasterData!$D$3:$D$18,0)),ISNUMBER(MATCH(L24,MasterData!$C$3:$C$18,0))), DATEDIF(E24,I24,"d"), DATEDIF(E24,TODAY(),"d")) -> 16 | R24: =IF($Q24>7,1,0) -> 1 | S24: =IF($Q24>15,1,0) -> 1 | T24: =IF($Q24>30,1,0) -> 0 | U24: =IF($Q24>60,1,0) -> 0
A25: 6000133063 | B25: INC42342645 | D25: 5220 | E25: 45719 | G25: Simona-Elena Kovar (CF R EEA PP PI / Z0046E1M) | H25: Ilona Splichalova | I25: 45778 | J25: RFC_FITS | K25: 4: Low | L25: Confirm_Closed | M25: GR posted, the payment block was removed in the background -> VIM workflow NOT completed | N25: SIE_S4P_RS Siemens S4P - Readsoft | Q25: =IF(OR(ISNUMBER(MATCH(L25,MasterData!$D$3:$D$18,0)),ISNUMBER(MATCH(L25,MasterData!$C$3:$C$18,0))), DATEDIF(E25,I25,"d"), DATEDIF(E25,TODAY(),"d")) -> 59 | R25: =IF($Q25>7,1,0) -> 1 | S25: =IF($Q25>15,1,0) -> 1 | T25: =IF($Q25>30,1,0) -> 1 | U25: =IF($Q25>60,1,0) -> 0
A26: 6000133075 | B26: INC42342669 | D26: 5220 | E26: 45719 | G26: Simona-Elena Kovar (CF R EEA PP PI / Z0046E1M) | H26: Albert Galek | I26: 45758 | J26: RFC_FITS | K26: 4: Low | L26: Confirm_Closed | M26: the document requires a technical approval although there is no price or quantity deviation | N26: SIE_S4P_RS Siemens S4P - Readsoft | Q26: =IF(OR(ISNUMBER(MATCH(L26,MasterData!$D$3:$D$18,0)),ISNUMBER(MATCH(L26,MasterData!$C$3:$C$18,0))), DATEDIF(E26,I26,"d"), DATEDIF(E26,TODAY(),"d")) -> 39 | R26: =IF($Q26>7,1,0) -> 1 | S26: =IF($Q26>15,1,0) -> 1 | T26: =IF($Q26>30,1,0) -> 1 | U26: =IF($Q26>60,1,0) -> 0
A27: 6000133085 | D27: 7092 | E27: 45719 | G27: Ulrich Rauch (IT ECP ERP-CP ARC2 / Z00060NO) | H27: Albert Galek | I27: 45731 | J27: SAP SOLUTION MANAGER S1A | K27: 3: Medium | L27: Confirm_Closed | M27: VIM: direct material PO: not able to choose non preferred approver | N27: SIE_S4P_RS Siemens S4P - Readsoft | Q27: =IF(OR(ISNUMBER(MATCH(L27,MasterData!$D$3:$D$18,0)),ISNUMBER(MATCH(L27,MasterData!$C$3:$C$18,0))), DATEDIF(E27,I27,"d"), DATEDIF(E27,TODAY(),"d")) -> 12 | R27: =IF($Q27>7,1,0) -> 1 | S27: =IF($Q27>15,1,0) -> 0 | T27: =IF($Q27>30,1,0) -> 0 | U27: =IF($Q27>60,1,0) -> 0
A28: 6000133086 | D28: 7092 | E28: 45719 | G28: Ulrich Rauch (IT ECP ERP-CP ARC2 / Z00060NO) | H28: Albert Galek | I28: 45773 | J28: SAP SOLUTION MANAGER S1A | K28: 3: Medium | L28: Confirm_Closed | M28: VIM ID 1785 and 5352 - approval workflow wasn't started but nevertheless is s | N28: SIE_S4P_RS Siemens S4P - Readsoft | Q28: =IF(OR(ISNUMBER(MATCH(L28,MasterData!$D$3:$D$18,0)),ISNUMBER(MATCH(L28,MasterData!$C$3:$C$18,0))), DATEDIF(E28,I28,"d"), DATEDIF(E28,TODAY(),"d")) -> 54 | R28: =IF($Q28>7,1,0) -> 1 | S28: =IF($Q28>15,1,0) -> 1 | T28: =IF($Q28>30,1,0) -> 1 | U28: =IF($Q28>60,1,0) -> 0
A29: 6000133087 | D29: 7092 | E29: 45719 | G29: Ulrich Rauch (IT ECP ERP-CP ARC2 / Z00060NO) | H29: Ilona Splichalova | I29: 45807 | J29: SAP SOLUTION MANAGER S1A | K29: 3: Medium | L29: Confirm_Closed | M29: VIM: different statuses in VIM Workplace and VIM Analytics | N29: SIE_S4P_RS Siemens S4P - Readsoft | Q29: =IF(OR(ISNUMBER(MATCH(L29,MasterData!$D$3:$D$18,0)),ISNUMBER(MATCH(L29,MasterData!$C$3:$C$18,0))), DATEDIF(E29,I29,"d"), DATEDIF(E29,TODAY(),"d")) -> 88 | R29: =IF($Q29>7,1,0) -> 1 | S29: =IF($Q29>15,1,0) -> 1 | T29: =IF($Q29>30,1,0) -> 1 | U29: =IF($Q29>60,1,0) -> 1
A30: 6000133442 | D30: 3003 | E30: 45722 | G30: Ilona Splichalova (DI IT ERP CZ FICO / Z002Z2VA) | H30: Ilona Splichalova | I30: 45786 | J30: SAP SOLUTION MANAGER S1A | K30: 3: Medium | L30: Confirm_Closed | M30: In VIM is not possible to cancel the invoice - DP 4288 | N30: SIE_S4P_RS Siemens S4P - Readsoft | Q30: =IF(OR(ISNUMBER(MATCH(L30,MasterData!$D$3:$D$18,0)),ISNUMBER(MATCH(L30,MasterData!$C$3:$C$18,0))), DATEDIF(E30,I30,"d"), DATEDIF(E30,TODAY(),"d")) -> 64 | R30: =IF($Q30>7,1,0) -> 1 | S30: =IF($Q30>15,1,0) -> 1 | T30: =IF($Q30>30,1,0) -> 1 | U30: =IF($Q30>60,1,0) -> 1
A31: 6000133644 | B31: INC42377517 | D31: 3014 | E31: 45723 | G31: Simon Kostovski (GBS CEE P2P CZ AP PE 2 / Z003DW1N) | H31: Albert Galek | I31: 45789 | J31: Ilona Splichalova | K31: 3: Medium | L31: In Process | M31: S4P Please adjust the VAT date to be identical with the invoice date for Company code 3014 | N31: SIE_S4P_RS Siemens S4P - Readsoft | Q31: =IF(OR(ISNUMBER(MATCH(L31,MasterData!$D$3:$D$18,0)),ISNUMBER(MATCH(L31,MasterData!$C$3:$C$18,0))), DATEDIF(E31,I31,"d"), DATEDIF(E31,TODAY(),"d")) -> 284 | R31: =IF($Q31>7,1,0) -> 1 | S31: =IF($Q31>15,1,0) -> 1 | T31: =IF($Q31>30,1,0) -> 1 | U31: =IF($Q31>60,1,0) -> 1
A32: 6000133647 | B32: INC42377569 | D32: 5975 | E32: 45723 | G32: Jan Binder (GBS CEE P2P CZ AP 2 2 / Z00435WC) | H32: Ilona Splichalova | I32: 45733 | J32: RFC_FITS | K32: 4: Low | L32: Confirm_Closed | M32: Receipt of invoices and posting in a different month/period. | N32: SIE_S4P_RS Siemens S4P - Readsoft | Q32: =IF(OR(ISNUMBER(MATCH(L32,MasterData!$D$3:$D$18,0)),ISNUMBER(MATCH(L32,MasterData!$C$3:$C$18,0))), DATEDIF(E32,I32,"d"), DATEDIF(E32,TODAY(),"d")) -> 10 | R32: =IF($Q32>7,1,0) -> 1 | S32: =IF($Q32>15,1,0) -> 0 | T32: =IF($Q32>30,1,0) -> 0 | U32: =IF($Q32>60,1,0) -> 0
A33: 6000133780 | B33: INC42386307 | D33: 3014 | E33: 45726 | G33: Andrei Vulpescu (DI MC GMC MF-EWN PU-BUZ FIN / Z00172BA) | H33: Albert Galek | I33: 45741 | J33: RFC_FITS | K33: 4: Low | L33: Confirm_Closed | M33: I cannot approve invoice release | N33: SIE_S4P_RS Siemens S4P - Readsoft | Q33: =IF(OR(ISNUMBER(MATCH(L33,MasterData!$D$3:$D$18,0)),ISNUMBER(MATCH(L33,MasterData!$C$3:$C$18,0))), DATEDIF(E33,I33,"d"), DATEDIF(E33,TODAY(),"d")) -> 15 | R33: =IF($Q33>7,1,0) -> 1 | S33: =IF($Q33>15,1,0) -> 0 | T33: =IF($Q33>30,1,0) -> 0 | U33: =IF($Q33>60,1,0) -> 0
A34: 6000133782 | B34: INC42386439 | D34: SRE | E34: 45726 | G34: Zdenek Cifka (GBS CEE P2P CZ AP 2 3 / Z003JPCS) | H34: Albert Galek | I34: 45735 | J34: RFC_FITS | K34: 3: Medium | L34: Confirm_Closed | M34: At VIM ID's 2977 and 1961 it's not possible to recall the approval workflow because they are situated in VIM WP in My co | N34: SIE_S4P_RS Siemens S4P - Readsoft | Q34: =IF(OR(ISNUMBER(MATCH(L34,MasterData!$D$3:$D$18,0)),ISNUMBER(MATCH(L34,MasterData!$C$3:$C$18,0))), DATEDIF(E34,I34,"d"), DATEDIF(E34,TODAY(),"d")) -> 9 | R34: =IF($Q34>7,1,0) -> 1 | S34: =IF($Q34>15,1,0) -> 0 | T34: =IF($Q34>30,1,0) -> 0 | U34: =IF($Q34>60,1,0) -> 0
A35: 6000133815 | B35: INC42387821 | D35: SRE | E35: 45726 | G35: Zdenek Cifka (GBS CEE P2P CZ AP 2 3 / Z003JPCS) | H35: Albert Galek | I35: 45748 | J35: RFC_FITS | K35: 3: Medium | L35: Confirm_Closed | M35: VIM ID 5033 - it's not possible to start the approval workflow manually for the specific person. | N35: SIE_S4P_RS Siemens S4P - Readsoft | Q35: =IF(OR(ISNUMBER(MATCH(L35,MasterData!$D$3:$D$18,0)),ISNUMBER(MATCH(L35,MasterData!$C$3:$C$18,0))), DATEDIF(E35,I35,"d"), DATEDIF(E35,TODAY(),"d")) -> 22 | R35: =IF($Q35>7,1,0) -> 1 | S35: =IF($Q35>15,1,0) -> 1 | T35: =IF($Q35>30,1,0) -> 0 | U35: =IF($Q35>60,1,0) -> 0
A36: 6000133897 | D36: 5975 | E36: 45727 | G36: Ilona Splichalova (DI IT ERP CZ FICO / Z002Z2VA) | H36: Albert Galek | I36: 45751 | J36: SAP SOLUTION MANAGER S1A | K36: 3: Medium | L36: Confirm_Closed | M36: VIM Table U-date Clarifications | N36: SIE_S4P_RS Siemens S4P - Readsoft | Q36: =IF(OR(ISNUMBER(MATCH(L36,MasterData!$D$3:$D$18,0)),ISNUMBER(MATCH(L36,MasterData!$C$3:$C$18,0))), DATEDIF(E36,I36,"d"), DATEDIF(E36,TODAY(),"d")) -> 24 | R36: =IF($Q36>7,1,0) -> 1 | S36: =IF($Q36>15,1,0) -> 1 | T36: =IF($Q36>30,1,0) -> 0 | U36: =IF($Q36>60,1,0) -> 0
A37: 6000134052 | B37: INC42401853 | D37: 3014 | E37: 45728 | G37: Ivana Tomisova (GBS CEE P2P CZ AP 3 2 / Z004PK7A) | H37: Mr. Silambarasan Vasu | I37: 45819 | K37: 4: Low | L37: Forwarded | M37: 3014 - ICC invoice not visible in VIM workplace | N37: MM - Materials Management | Q37: =IF(OR(ISNUMBER(MATCH(L37,MasterData!$D$3:$D$18,0)),ISNUMBER(MATCH(L37,MasterData!$C$3:$C$18,0))), DATEDIF(E37,I37,"d"), DATEDIF(E37,TODAY(),"d")) -> 279 | R37: =IF($Q37>7,1,0) -> 1 | S37: =IF($Q37>15,1,0) -> 1 | T37: =IF($Q37>30,1,0) -> 1 | U37: =IF($Q37>60,1,0) -> 1
A38: 6000134157 | B38: INC42406593 | D38: 5975 | E38: 45729 | G38: Pavel Mego (GBS CEE P2P CZ AP 2 4 / Z001SCDJ) | H38: Ilona Splichalova | I38: 45737 | J38: RFC_FITS | K38: 4: Low | L38: Confirm_Closed | M38: Stucked Webcycle | N38: SIE_S4P_RS Siemens S4P - Readsoft | Q38: =IF(OR(ISNUMBER(MATCH(L38,MasterData!$D$3:$D$18,0)),ISNUMBER(MATCH(L38,MasterData!$C$3:$C$18,0))), DATEDIF(E38,I38,"d"), DATEDIF(E38,TODAY(),"d")) -> 8 | R38: =IF($Q38>7,1,0) -> 1 | S38: =IF($Q38>15,1,0) -> 0 | T38: =IF($Q38>30,1,0) -> 0 | U38: =IF($Q38>60,1,0) -> 0
A39: 6000134167 | D39: 7092 | E39: 45729 | G39: Muskan Khanum Nagad (IT ECP ERP-CP / Z0053CPH) | H39: Albert Galek | I39: 45792 | J39: SAP SOLUTION MANAGER S1A | K39: 3: Medium | L39: Confirm_Closed | M39: Abap programming error in S4P | N39: SIE_S4P_RS Siemens S4P - Readsoft | Q39: =IF(OR(ISNUMBER(MATCH(L39,MasterData!$D$3:$D$18,0)),ISNUMBER(MATCH(L39,MasterData!$C$3:$C$18,0))), DATEDIF(E39,I39,"d"), DATEDIF(E39,TODAY(),"d")) -> 63 | R39: =IF($Q39>7,1,0) -> 1 | S39: =IF($Q39>15,1,0) -> 1 | T39: =IF($Q39>30,1,0) -> 1 | U39: =IF($Q39>60,1,0) -> 1
A40: 6000134304 | B40: INC42414880 | D40: 7011 | E40: 45729 | G40: Cosmin-Ovidiu Sarbu (DI MC GMC MF-EWN PU-BUZ FIN BC / Z0026A | H40: Ilona Splichalova | I40: 45782 | J40: RFC_FITS | K40: 4: Low | L40: Confirm_Closed | M40: Approval of invoices in VIM according to SAT | N40: SIE_S4P_RS Siemens S4P - Readsoft | Q40: =IF(OR(ISNUMBER(MATCH(L40,MasterData!$D$3:$D$18,0)),ISNUMBER(MATCH(L40,MasterData!$C$3:$C$18,0))), DATEDIF(E40,I40,"d"), DATEDIF(E40,TODAY(),"d")) -> 53 | R40: =IF($Q40>7,1,0) -> 1 | S40: =IF($Q40>15,1,0) -> 1 | T40: =IF($Q40>30,1,0) -> 1 | U40: =IF($Q40>60,1,0) -> 0
A41: 6000134423 | B41: INC42420961 | D41: 5975 | E41: 45730 | G41: Pavel Mego (GBS CEE P2P CZ AP 2 4 / Z001SCDJ) | H41: Ilona Splichalova | I41: 45748 | J41: RFC_FITS | K41: 4: Low | L41: Confirm_Closed | M41: readsoft messages | N41: SIE_S4P_RS Siemens S4P - Readsoft | Q41: =IF(OR(ISNUMBER(MATCH(L41,MasterData!$D$3:$D$18,0)),ISNUMBER(MATCH(L41,MasterData!$C$3:$C$18,0))), DATEDIF(E41,I41,"d"), DATEDIF(E41,TODAY(),"d")) -> 18 | R41: =IF($Q41>7,1,0) -> 1 | S41: =IF($Q41>15,1,0) -> 1 | T41: =IF($Q41>30,1,0) -> 0 | U41: =IF($Q41>60,1,0) -> 0
A42: 6000134460 | B42: INC42422286 | D42: 5975 | E42: 45730 | G42: Ivana Tomisova (GBS CEE P2P CZ AP 3 2 / Z004PK7A) | H42: Albert Galek | I42: 45748 | J42: RFC_FITS | K42: 4: Low | L42: Confirm_Closed | M42: 3014 - posting of inovices on mutiple POs | N42: SIE_S4P_RS Siemens S4P - Readsoft | Q42: =IF(OR(ISNUMBER(MATCH(L42,MasterData!$D$3:$D$18,0)),ISNUMBER(MATCH(L42,MasterData!$C$3:$C$18,0))), DATEDIF(E42,I42,"d"), DATEDIF(E42,TODAY(),"d")) -> 18 | R42: =IF($Q42>7,1,0) -> 1 | S42: =IF($Q42>15,1,0) -> 1 | T42: =IF($Q42>30,1,0) -> 0 | U42: =IF($Q42>60,1,0) -> 0
A43: 6000134543 | B43: INC42429350 | D43: 3014 | E43: 45733 | G43: Cristina Mariana Vega (DI MC GMC MF-EWN PU-BUZ FIN LOG / Z00 | H43: Albert Galek | I43: 45754 | J43: RFC_FITS | K43: 2: High | L43: Confirm_Closed | M43: Approval invoice not possible in Approval invoice Management app | N43: SIE_S4P_RS Siemens S4P - Readsoft | Q43: =IF(OR(ISNUMBER(MATCH(L43,MasterData!$D$3:$D$18,0)),ISNUMBER(MATCH(L43,MasterData!$C$3:$C$18,0))), DATEDIF(E43,I43,"d"), DATEDIF(E43,TODAY(),"d")) -> 21 | R43: =IF($Q43>7,1,0) -> 1 | S43: =IF($Q43>15,1,0) -> 1 | T43: =IF($Q43>30,1,0) -> 0 | U43: =IF($Q43>60,1,0) -> 0
A44: 6000134731 | B44: INC42441623 | D44: 5975 | E44: 45734 | G44: Pavel Mego (GBS CEE P2P CZ AP 2 4 / Z001SCDJ) | H44: Ilona Splichalova | I44: 45743 | J44: RFC_FITS | K44: 4: Low | L44: Confirm_Closed | M44: Webcycles with error | N44: SIE_S4P_RS Siemens S4P - Readsoft | Q44: =IF(OR(ISNUMBER(MATCH(L44,MasterData!$D$3:$D$18,0)),ISNUMBER(MATCH(L44,MasterData!$C$3:$C$18,0))), DATEDIF(E44,I44,"d"), DATEDIF(E44,TODAY(),"d")) -> 9 | R44: =IF($Q44>7,1,0) -> 1 | S44: =IF($Q44>15,1,0) -> 0 | T44: =IF($Q44>30,1,0) -> 0 | U44: =IF($Q44>60,1,0) -> 0
A45: 6000134816 | B45: INC42448216 | D45: 5220 | E45: 45735 | G45: Simona-Elena Kovar (CF R EEA PP PI / Z0046E1M) | H45: Ilona Splichalova | I45: 45762 | J45: RFC_FITS | K45: 4: Low | L45: Confirm_Closed | M45: Invoice in approval step but not visible in Approval Invoice Management application | N45: SIE_S4P_RS Siemens S4P - Readsoft | Q45: =IF(OR(ISNUMBER(MATCH(L45,MasterData!$D$3:$D$18,0)),ISNUMBER(MATCH(L45,MasterData!$C$3:$C$18,0))), DATEDIF(E45,I45,"d"), DATEDIF(E45,TODAY(),"d")) -> 27 | R45: =IF($Q45>7,1,0) -> 1 | S45: =IF($Q45>15,1,0) -> 1 | T45: =IF($Q45>30,1,0) -> 0 | U45: =IF($Q45>60,1,0) -> 0
A46: 6000134850 | B46: INC42449485 | D46: 3014 | E46: 45735 | G46: Juliana Batya Dora Ciupe (DI MC GMC MF-EWN PU-BUZ FIN BC / Z | H46: Albert Galek | I46: 45761 | J46: RFC_FITS | K46: 3: Medium | L46: Confirm_Closed | M46: Invoice with IDoc quantity incorect - issue in approval process | N46: SIE_S4P_RS Siemens S4P - Readsoft | Q46: =IF(OR(ISNUMBER(MATCH(L46,MasterData!$D$3:$D$18,0)),ISNUMBER(MATCH(L46,MasterData!$C$3:$C$18,0))), DATEDIF(E46,I46,"d"), DATEDIF(E46,TODAY(),"d")) -> 26 | R46: =IF($Q46>7,1,0) -> 1 | S46: =IF($Q46>15,1,0) -> 1 | T46: =IF($Q46>30,1,0) -> 0 | U46: =IF($Q46>60,1,0) -> 0
A47: 6000134958 | B47: INC42458439 | D47: 3003 | E47: 45736 | G47: Pavla Tothova (GBS CEE P2P CZ AP 2 3 / Z002NYHT) | H47: Ilona Splichalova | I47: 45750 | J47: RFC_FITS | K47: 3: Medium | L47: Confirm_Closed | M47: S4P/AUN 3003 VIM ID 5424 - the credit note was incorrectly booked as an invoice, nevertheless is situated in VIM WP in | N47: SIE_S4P_RS Siemens S4P - Readsoft | Q47: =IF(OR(ISNUMBER(MATCH(L47,MasterData!$D$3:$D$18,0)),ISNUMBER(MATCH(L47,MasterData!$C$3:$C$18,0))), DATEDIF(E47,I47,"d"), DATEDIF(E47,TODAY(),"d")) -> 14 | R47: =IF($Q47>7,1,0) -> 1 | S47: =IF($Q47>15,1,0) -> 0 | T47: =IF($Q47>30,1,0) -> 0 | U47: =IF($Q47>60,1,0) -> 0
A48: 6000135155 | B48: INC42469024 | D48: 7092 | E48: 45737 | G48: Dirk Eska (IT DF COL UC / Z0000X0D) | H48: Ilona Splichalova | I48: 45757 | J48: RFC_FITS | K48: 4: Low | L48: Confirm_Closed | M48: S4-line Service - Kein Zugang zum Webcycle Tool mehr | N48: SIE_S4P_RS Siemens S4P - Readsoft | Q48: =IF(OR(ISNUMBER(MATCH(L48,MasterData!$D$3:$D$18,0)),ISNUMBER(MATCH(L48,MasterData!$C$3:$C$18,0))), DATEDIF(E48,I48,"d"), DATEDIF(E48,TODAY(),"d")) -> 20 | R48: =IF($Q48>7,1,0) -> 1 | S48: =IF($Q48>15,1,0) -> 1 | T48: =IF($Q48>30,1,0) -> 0 | U48: =IF($Q48>60,1,0) -> 0
A49: 6000135247 | D49: SRE | E49: 45740 | G49: Ilona Splichalova (DI IT ERP CZ FICO / Z002Z2VA) | H49: Ilona Splichalova | I49: 45779 | J49: SAP SOLUTION MANAGER S1A | K49: 3: Medium | L49: Confirm_Closed | M49: VIM: Issue with items incorrectly placed in My Completed tab | N49: SIE_S4P_RS Siemens S4P - Readsoft | Q49: =IF(OR(ISNUMBER(MATCH(L49,MasterData!$D$3:$D$18,0)),ISNUMBER(MATCH(L49,MasterData!$C$3:$C$18,0))), DATEDIF(E49,I49,"d"), DATEDIF(E49,TODAY(),"d")) -> 39 | R49: =IF($Q49>7,1,0) -> 1 | S49: =IF($Q49>15,1,0) -> 1 | T49: =IF($Q49>30,1,0) -> 1 | U49: =IF($Q49>60,1,0) -> 0
A50: 6000135249 | B50: INC42467829 | D50: 3014 | E50: 45740 | G50: Andrei Vulpescu (DI MC GMC MF-EWN PU-BUZ FIN / Z00172BA) | H50: Ilona Splichalova | I50: 45782 | J50: RFC_FITS | K50: 3: Medium | L50: Confirm_Closed | M50: SAT / S4 approval step | N50: SIE_S4P_RS Siemens S4P - Readsoft | Q50: =IF(OR(ISNUMBER(MATCH(L50,MasterData!$D$3:$D$18,0)),ISNUMBER(MATCH(L50,MasterData!$C$3:$C$18,0))), DATEDIF(E50,I50,"d"), DATEDIF(E50,TODAY(),"d")) -> 42 | R50: =IF($Q50>7,1,0) -> 1 | S50: =IF($Q50>15,1,0) -> 1 | T50: =IF($Q50>30,1,0) -> 1 | U50: =IF($Q50>60,1,0) -> 0
A51: 6000135321 | B51: INC42480479 | D51: SRE | E51: 45740 | G51: Zdenek Cifka (GBS CEE P2P CZ AP 2 3 / Z003JPCS) | H51: Ilona Splichalova | I51: 45784 | J51: RFC_FITS | K51: 3: Medium | L51: Confirm_Closed | M51: it's not possible to post VIM ID 5242 on the account 65811000, because there an error is displayed | N51: SIE_S4P_RS Siemens S4P - Readsoft | Q51: =IF(OR(ISNUMBER(MATCH(L51,MasterData!$D$3:$D$18,0)),ISNUMBER(MATCH(L51,MasterData!$C$3:$C$18,0))), DATEDIF(E51,I51,"d"), DATEDIF(E51,TODAY(),"d")) -> 44 | R51: =IF($Q51>7,1,0) -> 1 | S51: =IF($Q51>15,1,0) -> 1 | T51: =IF($Q51>30,1,0) -> 1 | U51: =IF($Q51>60,1,0) -> 0
A52: 6000135513 | B52: INC42494408 | D52: 3003 | E52: 45742 | G52: Tobias Moest (SRE FIN AR 2 / Z000F12V) | I52: 45749 | J52: RFC_FITS | K52: 4: Low | L52: Confirm_Closed | M52: S4P VIM - Zahlungsbedingung falsch ermittelt? | N52: SIE_S4P_RS Siemens S4P - Readsoft | Q52: =IF(OR(ISNUMBER(MATCH(L52,MasterData!$D$3:$D$18,0)),ISNUMBER(MATCH(L52,MasterData!$C$3:$C$18,0))), DATEDIF(E52,I52,"d"), DATEDIF(E52,TODAY(),"d")) -> 7 | R52: =IF($Q52>7,1,0) -> 0 | S52: =IF($Q52>15,1,0) -> 0 | T52: =IF($Q52>30,1,0) -> 0 | U52: =IF($Q52>60,1,0) -> 0
A53: 6000135668 | B53: INC42504595 | D53: 5975 | E53: 45743 | G53: Simon Kostovski (GBS CEE P2P CZ AP PE 2 / Z003DW1N) | H53: Ulrich Rauch / 81739 Muenchen | I53: 45782 | J53: RFC_FITS | K53: 3: Medium | L53: Confirm_Closed | M53: S4P/3014- Invoices which have posted GR or adjusted prices and posted Invoices are stuck in approver’s workflow | N53: SIE_S4P_RS Siemens S4P - Readsoft | Q53: =IF(OR(ISNUMBER(MATCH(L53,MasterData!$D$3:$D$18,0)),ISNUMBER(MATCH(L53,MasterData!$C$3:$C$18,0))), DATEDIF(E53,I53,"d"), DATEDIF(E53,TODAY(),"d")) -> 39 | R53: =IF($Q53>7,1,0) -> 1 | S53: =IF($Q53>15,1,0) -> 1 | T53: =IF($Q53>30,1,0) -> 1 | U53: =IF($Q53>60,1,0) -> 0
A54: 6000135843 | D54: 7092 | E54: 45744 | G54: Ulrich Rauch (IT ECP ERP-CP ARC2 / Z00060NO) | H54: Ulrich Rauch / 81739 Muenchen | I54: 45759 | J54: SAP SOLUTION MANAGER S1A | K54: 3: Medium | L54: Confirm_Closed | M54: Fix missing purpose code JP in Readsoft GEN table | N54: SIE_S4P_RS Siemens S4P - Readsoft | Q54: =IF(OR(ISNUMBER(MATCH(L54,MasterData!$D$3:$D$18,0)),ISNUMBER(MATCH(L54,MasterData!$C$3:$C$18,0))), DATEDIF(E54,I54,"d"), DATEDIF(E54,TODAY(),"d")) -> 15 | R54: =IF($Q54>7,1,0) -> 1 | S54: =IF($Q54>15,1,0) -> 0 | T54: =IF($Q54>30,1,0) -> 0 | U54: =IF($Q54>60,1,0) -> 0
A55: 6000135916 | B55: INC42521355 | D55: 7092 | E55: 45747 | G55: Jonas Weber (IT DA DO PL / Z003DMKU) | H55: Ulrich Rauch / 81739 Muenchen | I55: 45754 | J55: RFC_FITS | K55: 4: Low | L55: Confirm_Closed | M55: Readsoft - Mailversand nach Query fehlt | N55: SIE_S4P_RS Siemens S4P - Readsoft | Q55: =IF(OR(ISNUMBER(MATCH(L55,MasterData!$D$3:$D$18,0)),ISNUMBER(MATCH(L55,MasterData!$C$3:$C$18,0))), DATEDIF(E55,I55,"d"), DATEDIF(E55,TODAY(),"d")) -> 7 | R55: =IF($Q55>7,1,0) -> 0 | S55: =IF($Q55>15,1,0) -> 0 | T55: =IF($Q55>30,1,0) -> 0 | U55: =IF($Q55>60,1,0) -> 0
A56: 6000135930 | B56: INC42521949 | D56: SRE | E56: 45747 | G56: Tobias Moest (SRE FIN AR 2 / Z000F12V) | H56: Ulrich Rauch / 81739 Muenchen | I56: 45758 | J56: RFC_FITS | K56: 4: Low | L56: Confirm_Closed | M56: S4P 100 - VIM: User erhält keine E-Mail zur Workflow Freigabe | N56: SIE_S4P_RS Siemens S4P - Readsoft | Q56: =IF(OR(ISNUMBER(MATCH(L56,MasterData!$D$3:$D$18,0)),ISNUMBER(MATCH(L56,MasterData!$C$3:$C$18,0))), DATEDIF(E56,I56,"d"), DATEDIF(E56,TODAY(),"d")) -> 11 | R56: =IF($Q56>7,1,0) -> 1 | S56: =IF($Q56>15,1,0) -> 0 | T56: =IF($Q56>30,1,0) -> 0 | U56: =IF($Q56>60,1,0) -> 0
A57: 6000136043 | D57: 7092 | E57: 45748 | G57: Ulrich Rauch (IT ECP ERP-CP ARC2 / Z00060NO) | H57: Kerstin Mueller / 81739 Muenchen | I57: 45786 | J57: SAP SOLUTION MANAGER S1A | K57: 3: Medium | L57: Confirm_Closed | M57: Readsoft: adaption tax code determination | N57: SIE_S4P_RS Siemens S4P - Readsoft | Q57: =IF(OR(ISNUMBER(MATCH(L57,MasterData!$D$3:$D$18,0)),ISNUMBER(MATCH(L57,MasterData!$C$3:$C$18,0))), DATEDIF(E57,I57,"d"), DATEDIF(E57,TODAY(),"d")) -> 38 | R57: =IF($Q57>7,1,0) -> 1 | S57: =IF($Q57>15,1,0) -> 1 | T57: =IF($Q57>30,1,0) -> 1 | U57: =IF($Q57>60,1,0) -> 0
A58: 6000136104 | B58: INC42532842 | D58: 3014 | E58: 45748 | G58: Alina Corina Maresi (DI MC GMC MF-EWN PU-BUZ FIN LOG 1-2 / Z | H58: Ulrich Rauch / 81739 Muenchen | I58: 45755 | J58: RFC_FITS | K58: 3: Medium | L58: Confirm_Closed | M58: No possible to approve the invoices because there is an error in determining the next approver | N58: SIE_S4P_RS Siemens S4P - Readsoft | Q58: =IF(OR(ISNUMBER(MATCH(L58,MasterData!$D$3:$D$18,0)),ISNUMBER(MATCH(L58,MasterData!$C$3:$C$18,0))), DATEDIF(E58,I58,"d"), DATEDIF(E58,TODAY(),"d")) -> 7 | R58: =IF($Q58>7,1,0) -> 0 | S58: =IF($Q58>15,1,0) -> 0 | T58: =IF($Q58>30,1,0) -> 0 | U58: =IF($Q58>60,1,0) -> 0
A59: 6000136206 | B59: INC42539676 | D59: 7411 | E59: 45749 | G59: Mona Sangl (DI MC GMC MF-EWN FIN LOG 1 2 / Z002Z0BD) | H59: Ilona Splichalova | I59: 45798 | J59: RFC_FITS | K59: 3: Medium | L59: Confirm_Closed | M59: Block reason "Over Limit" is not given | N59: SIE_S4P_RS Siemens S4P - Readsoft | Q59: =IF(OR(ISNUMBER(MATCH(L59,MasterData!$D$3:$D$18,0)),ISNUMBER(MATCH(L59,MasterData!$C$3:$C$18,0))), DATEDIF(E59,I59,"d"), DATEDIF(E59,TODAY(),"d")) -> 49 | R59: =IF($Q59>7,1,0) -> 1 | S59: =IF($Q59>15,1,0) -> 1 | T59: =IF($Q59>30,1,0) -> 1 | U59: =IF($Q59>60,1,0) -> 0
A60: 6000136305 | B60: INC42544021 | D60: 3011 | E60: 45749 | G60: Asma Meftah (DI SW EDA MNA / Z003U86H) | H60: Ulrich Rauch / 81739 Muenchen | I60: 45756 | J60: RFC_FITS | K60: 3: Medium | L60: Confirm_Closed | M60: KOFAX shows the following error: User Asma Meftah (Z003U86H) locked | N60: SIE_S4P_RS Siemens S4P - Readsoft | Q60: =IF(OR(ISNUMBER(MATCH(L60,MasterData!$D$3:$D$18,0)),ISNUMBER(MATCH(L60,MasterData!$C$3:$C$18,0))), DATEDIF(E60,I60,"d"), DATEDIF(E60,TODAY(),"d")) -> 7 | R60: =IF($Q60>7,1,0) -> 0 | S60: =IF($Q60>15,1,0) -> 0 | T60: =IF($Q60>30,1,0) -> 0 | U60: =IF($Q60>60,1,0) -> 0
A61: 6000136404 | B61: INC42552933 | D61: 3003 | E61: 45750 | G61: Pavla Tothova (GBS CEE P2P CZ AP 2 3 / Z002NYHT) | H61: Ilona Splichalova | I61: 45764 | J61: RFC_FITS | K61: 3: Medium | L61: Confirm_Closed | M61: S4P/AUN 3003 VIM ID 3471- the document cannot be cancelled | N61: SIE_S4P_RS Siemens S4P - Readsoft | Q61: =IF(OR(ISNUMBER(MATCH(L61,MasterData!$D$3:$D$18,0)),ISNUMBER(MATCH(L61,MasterData!$C$3:$C$18,0))), DATEDIF(E61,I61,"d"), DATEDIF(E61,TODAY(),"d")) -> 14 | R61: =IF($Q61>7,1,0) -> 1 | S61: =IF($Q61>15,1,0) -> 0 | T61: =IF($Q61>30,1,0) -> 0 | U61: =IF($Q61>60,1,0) -> 0
A62: 6000136413 | B62: INC42553406 | D62: SRE | E62: 45750 | G62: Pavla Tothova (GBS CEE P2P CZ AP 2 3 / Z002NYHT) | H62: Ilona Splichalova | I62: 45758 | J62: RFC_FITS | K62: 3: Medium | L62: Confirm_Closed | M62: S4P/7998 - DPs 2977 and 1961 - it's not possible to recall the approval workflows | N62: SIE_S4P_RS Siemens S4P - Readsoft | Q62: =IF(OR(ISNUMBER(MATCH(L62,MasterData!$D$3:$D$18,0)),ISNUMBER(MATCH(L62,MasterData!$C$3:$C$18,0))), DATEDIF(E62,I62,"d"), DATEDIF(E62,TODAY(),"d")) -> 8 | R62: =IF($Q62>7,1,0) -> 1 | S62: =IF($Q62>15,1,0) -> 0 | T62: =IF($Q62>30,1,0) -> 0 | U62: =IF($Q62>60,1,0) -> 0
A63: 6000136417 | B63: INC42553572 | D63: SRE | E63: 45750 | G63: Pavla Tothova (GBS CEE P2P CZ AP 2 3 / Z002NYHT) | H63: Albert Galek | I63: 45758 | J63: RFC_FITS | K63: 3: Medium | L63: Confirm_Closed | M63: S4P/7998 - VIM ID 5352 - approval workflow wasn't started. | N63: SIE_S4P_RS Siemens S4P - Readsoft | Q63: =IF(OR(ISNUMBER(MATCH(L63,MasterData!$D$3:$D$18,0)),ISNUMBER(MATCH(L63,MasterData!$C$3:$C$18,0))), DATEDIF(E63,I63,"d"), DATEDIF(E63,TODAY(),"d")) -> 8 | R63: =IF($Q63>7,1,0) -> 1 | S63: =IF($Q63>15,1,0) -> 0 | T63: =IF($Q63>30,1,0) -> 0 | U63: =IF($Q63>60,1,0) -> 0
A64: 6000136696 | B64: INC42571709 | D64: SRE | E64: 45755 | G64: Pavla Tothova (GBS CEE P2P CZ AP 2 3 / Z002NYHT) | H64: Ilona Splichalova | I64: 45763 | J64: RFC_FITS | K64: 3: Medium | L64: Confirm_Closed | M64: S4P/7998 - DP 2512 - it's not possible to recall the approval workflow | N64: SIE_S4P_RS Siemens S4P - Readsoft | Q64: =IF(OR(ISNUMBER(MATCH(L64,MasterData!$D$3:$D$18,0)),ISNUMBER(MATCH(L64,MasterData!$C$3:$C$18,0))), DATEDIF(E64,I64,"d"), DATEDIF(E64,TODAY(),"d")) -> 8 | R64: =IF($Q64>7,1,0) -> 1 | S64: =IF($Q64>15,1,0) -> 0 | T64: =IF($Q64>30,1,0) -> 0 | U64: =IF($Q64>60,1,0) -> 0
A65: 6000136707 | B65: INC42571588 | D65: SRE | E65: 45755 | G65: Pavla Tothova (GBS CEE P2P CZ AP 2 3 / Z002NYHT) | H65: Ilona Splichalova | I65: 45763 | J65: RFC_FITS | K65: 3: Medium | L65: Confirm_Closed | M65: S4P/7998 - DP 1032 - it's not possible to recall the approval workflow | N65: SIE_S4P_RS Siemens S4P - Readsoft | Q65: =IF(OR(ISNUMBER(MATCH(L65,MasterData!$D$3:$D$18,0)),ISNUMBER(MATCH(L65,MasterData!$C$3:$C$18,0))), DATEDIF(E65,I65,"d"), DATEDIF(E65,TODAY(),"d")) -> 8 | R65: =IF($Q65>7,1,0) -> 1 | S65: =IF($Q65>15,1,0) -> 0 | T65: =IF($Q65>30,1,0) -> 0 | U65: =IF($Q65>60,1,0) -> 0
A66: 6000136806 | D66: 7092 | E66: 45755 | G66: Ulrich Rauch (IT ECP FPS LV / Z00060NO) | H66: Ramesh Itamsetti | I66: 45789 | J66: SAP SOLUTION MANAGER S1A | K66: 3: Medium | L66: Confirm_Closed | M66: VIM: bugfix in GR Wait functionality | N66: SIE_S4P_RS Siemens S4P - Readsoft | Q66: =IF(OR(ISNUMBER(MATCH(L66,MasterData!$D$3:$D$18,0)),ISNUMBER(MATCH(L66,MasterData!$C$3:$C$18,0))), DATEDIF(E66,I66,"d"), DATEDIF(E66,TODAY(),"d")) -> 34 | R66: =IF($Q66>7,1,0) -> 1 | S66: =IF($Q66>15,1,0) -> 1 | T66: =IF($Q66>30,1,0) -> 1 | U66: =IF($Q66>60,1,0) -> 0
A67: 6000136916 | B67: INC42586578 | D67: SRE | E67: 45756 | G67: Pavla Tothova (GBS CEE P2P CZ AP 2 3 / Z002NYHT) | H67: Ilona Splichalova | I67: 45764 | J67: RFC_FITS | K67: 3: Medium | L67: Confirm_Closed | M67: S4P/7998 - problem with approval workflow - VIM ID 4984 und 4985 | N67: SIE_S4P_RS Siemens S4P - Readsoft | Q67: =IF(OR(ISNUMBER(MATCH(L67,MasterData!$D$3:$D$18,0)),ISNUMBER(MATCH(L67,MasterData!$C$3:$C$18,0))), DATEDIF(E67,I67,"d"), DATEDIF(E67,TODAY(),"d")) -> 8 | R67: =IF($Q67>7,1,0) -> 1 | S67: =IF($Q67>15,1,0) -> 0 | T67: =IF($Q67>30,1,0) -> 0 | U67: =IF($Q67>60,1,0) -> 0
A68: 6000137097 | B68: INC42596308 | D68: 7092 | E68: 45757 | G68: Nadine Huettl (LC IP LTA / Z0005Q3T) | H68: Ulrich Rauch / 81739 Muenchen | I68: 45765 | J68: RFC_FITS | K68: 4: Low | L68: Confirm_Closed | M68: Freigabe von Rechnungen nicht möglich (ARE 5811) | N68: SIE_S4P_RS Siemens S4P - Readsoft | Q68: =IF(OR(ISNUMBER(MATCH(L68,MasterData!$D$3:$D$18,0)),ISNUMBER(MATCH(L68,MasterData!$C$3:$C$18,0))), DATEDIF(E68,I68,"d"), DATEDIF(E68,TODAY(),"d")) -> 8 | R68: =IF($Q68>7,1,0) -> 1 | S68: =IF($Q68>15,1,0) -> 0 | T68: =IF($Q68>30,1,0) -> 0 | U68: =IF($Q68>60,1,0) -> 0
A69: 6000137324 | B69: INC42614440 | D69: 3014 | E69: 45761 | G69: Alina Corina Maresi (DI MC GMC MF-EWN PU-BUZ FIN LOG 1-2 / Z | H69: Ulrich Rauch / 81739 Muenchen | I69: 45771 | J69: RFC_FITS | K69: 2: High | L69: Confirm_Closed | M69: Error on approval invoices in "My inbox" VIM AUN 3014 | N69: SIE_S4P_RS Siemens S4P - Readsoft | Q69: =IF(OR(ISNUMBER(MATCH(L69,MasterData!$D$3:$D$18,0)),ISNUMBER(MATCH(L69,MasterData!$C$3:$C$18,0))), DATEDIF(E69,I69,"d"), DATEDIF(E69,TODAY(),"d")) -> 10 | R69: =IF($Q69>7,1,0) -> 1 | S69: =IF($Q69>15,1,0) -> 0 | T69: =IF($Q69>30,1,0) -> 0 | U69: =IF($Q69>60,1,0) -> 0
A70: 6000137341 | B70: INC42614781 | D70: 7092 | E70: 45761 | G70: Fabian Schmitzer (IT DA DO E / Z001WYFH) | H70: Ilona Splichalova | I70: 45768 | J70: RFC_FITS | K70: 4: Low | L70: Confirm_Closed | M70: No access to my S4P 100 / Webcycle list of documents | N70: SIE_S4P_RS Siemens S4P - Readsoft | Q70: =IF(OR(ISNUMBER(MATCH(L70,MasterData!$D$3:$D$18,0)),ISNUMBER(MATCH(L70,MasterData!$C$3:$C$18,0))), DATEDIF(E70,I70,"d"), DATEDIF(E70,TODAY(),"d")) -> 7 | R70: =IF($Q70>7,1,0) -> 0 | S70: =IF($Q70>15,1,0) -> 0 | T70: =IF($Q70>30,1,0) -> 0 | U70: =IF($Q70>60,1,0) -> 0
A71: 6000137533 | D71: 3008 | E71: 45762 | G71: Ulrich Rauch (IT ECP FPS LV / Z00060NO) | H71: Ilona Splichalova | I71: 45782 | J71: SAP SOLUTION MANAGER S1A | K71: 3: Medium | L71: Confirm_Closed | M71: VIM: DP 3924 block removed with single appr.step | N71: SIE_S4P_RS Siemens S4P - Readsoft | Q71: =IF(OR(ISNUMBER(MATCH(L71,MasterData!$D$3:$D$18,0)),ISNUMBER(MATCH(L71,MasterData!$C$3:$C$18,0))), DATEDIF(E71,I71,"d"), DATEDIF(E71,TODAY(),"d")) -> 20 | R71: =IF($Q71>7,1,0) -> 1 | S71: =IF($Q71>15,1,0) -> 1 | T71: =IF($Q71>30,1,0) -> 0 | U71: =IF($Q71>60,1,0) -> 0
A72: 6000137544 | B72: INC42625312 | D72: 3003 | E72: 45762 | G72: Tobias Moest (SRE FIN AR 2 / Z000F12V) | H72: Ulrich Rauch / 81739 Muenchen | I72: 45821 | J72: RFC_FITS | K72: 4: Low | L72: Confirm_Closed | M72: S4P 100 VIM - Selektion in VIM Analytics fehlerhaft | N72: SIE_S4P_RS Siemens S4P - Readsoft | Q72: =IF(OR(ISNUMBER(MATCH(L72,MasterData!$D$3:$D$18,0)),ISNUMBER(MATCH(L72,MasterData!$C$3:$C$18,0))), DATEDIF(E72,I72,"d"), DATEDIF(E72,TODAY(),"d")) -> 59 | R72: =IF($Q72>7,1,0) -> 1 | S72: =IF($Q72>15,1,0) -> 1 | T72: =IF($Q72>30,1,0) -> 1 | U72: =IF($Q72>60,1,0) -> 0
A73: 6000137636 | B73: INC42632582 | D73: 3014 | E73: 45763 | G73: Andrei Vulpescu (DI MC GMC MF-EWN PU-BUZ FIN / Z00172BA) | H73: Albert Galek | I73: 45782 | J73: RFC_FITS | K73: 2: High | L73: Confirm_Closed | M73: I cannot approve invoice due to error | N73: SIE_S4P_RS Siemens S4P - Readsoft | Q73: =IF(OR(ISNUMBER(MATCH(L73,MasterData!$D$3:$D$18,0)),ISNUMBER(MATCH(L73,MasterData!$C$3:$C$18,0))), DATEDIF(E73,I73,"d"), DATEDIF(E73,TODAY(),"d")) -> 19 | R73: =IF($Q73>7,1,0) -> 1 | S73: =IF($Q73>15,1,0) -> 1 | T73: =IF($Q73>30,1,0) -> 0 | U73: =IF($Q73>60,1,0) -> 0
A74: 6000137924 | B74: INC42657410 | D74: 5975 | E74: 45769 | G74: Libor Pas (GBS CEE P2P CZ SC 2 8 / Z004VCDA) | H74: Albert Galek | I74: 45782 | J74: RFC_FITS | K74: 4: Low | L74: Confirm_Closed | M74: proces blocked | N74: SIE_S4P_RS Siemens S4P - Readsoft | Q74: =IF(OR(ISNUMBER(MATCH(L74,MasterData!$D$3:$D$18,0)),ISNUMBER(MATCH(L74,MasterData!$C$3:$C$18,0))), DATEDIF(E74,I74,"d"), DATEDIF(E74,TODAY(),"d")) -> 13 | R74: =IF($Q74>7,1,0) -> 1 | S74: =IF($Q74>15,1,0) -> 0 | T74: =IF($Q74>30,1,0) -> 0 | U74: =IF($Q74>60,1,0) -> 0
A75: 6000138263 | D75: 3014 | E75: 45771 | G75: Albert Galek (IT ECP FPS LV / Z004W53N) | H75: Ilona Splichalova | I75: 45832 | J75: Ilona Splichalova | K75: 3: Medium | L75: In Process | M75: Please check below DPs ald close approval WF if needed | N75: SIE_S4P_RS Siemens S4P - Readsoft | Q75: =IF(OR(ISNUMBER(MATCH(L75,MasterData!$D$3:$D$18,0)),ISNUMBER(MATCH(L75,MasterData!$C$3:$C$18,0))), DATEDIF(E75,I75,"d"), DATEDIF(E75,TODAY(),"d")) -> 236 | R75: =IF($Q75>7,1,0) -> 1 | S75: =IF($Q75>15,1,0) -> 1 | T75: =IF($Q75>30,1,0) -> 1 | U75: =IF($Q75>60,1,0) -> 1
A76: 6000138316 | B76: INC42678209 | D76: SRE | E76: 45772 | G76: Pavla Tothova (GBS CEE P2P CZ AP 2 3 / Z002NYHT) | H76: Ilona Splichalova | I76: 45779 | J76: RFC_FITS | K76: 3: Medium | L76: Confirm_Closed | M76: S4P/7998 - VIM 6944 - it's not possible to recall the approval workflow and send it to a specific person | N76: SIE_S4P_RS Siemens S4P - Readsoft | Q76: =IF(OR(ISNUMBER(MATCH(L76,MasterData!$D$3:$D$18,0)),ISNUMBER(MATCH(L76,MasterData!$C$3:$C$18,0))), DATEDIF(E76,I76,"d"), DATEDIF(E76,TODAY(),"d")) -> 7 | R76: =IF($Q76>7,1,0) -> 0 | S76: =IF($Q76>15,1,0) -> 0 | T76: =IF($Q76>30,1,0) -> 0 | U76: =IF($Q76>60,1,0) -> 0
A77: 6000138428 | B77: INC42684362 | D77: SRE | E77: 45772 | G77: Pavla Tothova (GBS CEE P2P CZ AP 2 3 / Z002NYHT) | H77: Ulrich Rauch / 81739 Muenchen | I77: 45832 | J77: Ilona Splichalova | K77: 4: Low | L77: In Process | M77: S4P/7998 - VIM ID 6783 - approval workflow wasn't started | N77: SIE_S4P_RS Siemens S4P - Readsoft | Q77: =IF(OR(ISNUMBER(MATCH(L77,MasterData!$D$3:$D$18,0)),ISNUMBER(MATCH(L77,MasterData!$C$3:$C$18,0))), DATEDIF(E77,I77,"d"), DATEDIF(E77,TODAY(),"d")) -> 235 | R77: =IF($Q77>7,1,0) -> 1 | S77: =IF($Q77>15,1,0) -> 1 | T77: =IF($Q77>30,1,0) -> 1 | U77: =IF($Q77>60,1,0) -> 1
A78: 6000138437 | B78: INC42684231 | D78: SRE | E78: 45772 | G78: Pavla Tothova (GBS CEE P2P CZ AP 2 3 / Z002NYHT) | H78: Ilona Splichalova | I78: 45833 | J78: Ilona Splichalova | K78: 3: Medium | L78: In Process | M78: S4P/7998 - VIM ID 6829 - approval workflow wasn't started | N78: SIE_S4P_RS Siemens S4P - Readsoft | Q78: =IF(OR(ISNUMBER(MATCH(L78,MasterData!$D$3:$D$18,0)),ISNUMBER(MATCH(L78,MasterData!$C$3:$C$18,0))), DATEDIF(E78,I78,"d"), DATEDIF(E78,TODAY(),"d")) -> 235 | R78: =IF($Q78>7,1,0) -> 1 | S78: =IF($Q78>15,1,0) -> 1 | T78: =IF($Q78>30,1,0) -> 1 | U78: =IF($Q78>60,1,0) -> 1
A79: 6000138440 | B79: INC42684494 | D79: SRE | E79: 45772 | G79: Pavla Tothova (GBS CEE P2P CZ AP 2 3 / Z002NYHT) | H79: Ilona Splichalova | I79: 45786 | J79: RFC_FITS | K79: 4: Low | L79: Confirm_Closed | M79: S4P/7998 - VIM ID 6579 - twice in the system, cleared, but situated in My inbox | N79: SIE_S4P_RS Siemens S4P - Readsoft | Q79: =IF(OR(ISNUMBER(MATCH(L79,MasterData!$D$3:$D$18,0)),ISNUMBER(MATCH(L79,MasterData!$C$3:$C$18,0))), DATEDIF(E79,I79,"d"), DATEDIF(E79,TODAY(),"d")) -> 14 | R79: =IF($Q79>7,1,0) -> 1 | S79: =IF($Q79>15,1,0) -> 0 | T79: =IF($Q79>30,1,0) -> 0 | U79: =IF($Q79>60,1,0) -> 0
A80: 6000138481 | B80: INC42689919 | D80: 5975 | E80: 45775 | G80: Jitka Krnavkova (GBS CEE P2P CZ AP 2 4 / Z002HBHS) | H80: Ilona Splichalova | I80: 45786 | J80: RFC_FITS | K80: 3: Medium | L80: Confirm_Closed | M80: Permissions to removing od payment block X from RS | N80: SIE_S4P_RS Siemens S4P - Readsoft | Q80: =IF(OR(ISNUMBER(MATCH(L80,MasterData!$D$3:$D$18,0)),ISNUMBER(MATCH(L80,MasterData!$C$3:$C$18,0))), DATEDIF(E80,I80,"d"), DATEDIF(E80,TODAY(),"d")) -> 11 | R80: =IF($Q80>7,1,0) -> 1 | S80: =IF($Q80>15,1,0) -> 0 | T80: =IF($Q80>30,1,0) -> 0 | U80: =IF($Q80>60,1,0) -> 0
A81: 6000138500 | B81: INC42690787 | D81: SRE | E81: 45775 | G81: Zdenek Cifka (GBS CEE P2P CZ AP 2 3 / Z003JPCS) | H81: Ulrich Rauch / 81739 Muenchen | I81: 45832 | J81: RFC_FITS | K81: 3: Medium | L81: Confirm_Closed | M81: S4P / It's not possible to start approval workflow for VIM ID 6022 and 6129 (company code 3003) | N81: SIE_S4P_RS Siemens S4P - Readsoft | Q81: =IF(OR(ISNUMBER(MATCH(L81,MasterData!$D$3:$D$18,0)),ISNUMBER(MATCH(L81,MasterData!$C$3:$C$18,0))), DATEDIF(E81,I81,"d"), DATEDIF(E81,TODAY(),"d")) -> 57 | R81: =IF($Q81>7,1,0) -> 1 | S81: =IF($Q81>15,1,0) -> 1 | T81: =IF($Q81>30,1,0) -> 1 | U81: =IF($Q81>60,1,0) -> 0
A82: 6000138582 | B82: INC42694021 | D82: 5975 | E82: 45775 | G82: Pavel Mego (GBS CEE P2P CZ AP 2 4 / Z001SCDJ) | H82: Ilona Splichalova | I82: 45824 | J82: RFC_FITS | K82: 4: Low | L82: Confirm_Closed | M82: not possible to post credit note | N82: SIE_S4P_RS Siemens S4P - Readsoft | Q82: =IF(OR(ISNUMBER(MATCH(L82,MasterData!$D$3:$D$18,0)),ISNUMBER(MATCH(L82,MasterData!$C$3:$C$18,0))), DATEDIF(E82,I82,"d"), DATEDIF(E82,TODAY(),"d")) -> 49 | R82: =IF($Q82>7,1,0) -> 1 | S82: =IF($Q82>15,1,0) -> 1 | T82: =IF($Q82>30,1,0) -> 1 | U82: =IF($Q82>60,1,0) -> 0
A83: 6000138600 | B83: INC42694920 | D83: 3014 | E83: 45775 | G83: Marcus Pfau (DI MC GMC MF-EWN PU-BUZ QM&EHS / Z004UA4Y) | H83: Ilona Splichalova | I83: 45812 | J83: RFC_FITS | K83: 3: Medium | L83: Confirm_Closed | M83: Invoice already approved by the user | N83: SIE_S4P_RS Siemens S4P - Readsoft | Q83: =IF(OR(ISNUMBER(MATCH(L83,MasterData!$D$3:$D$18,0)),ISNUMBER(MATCH(L83,MasterData!$C$3:$C$18,0))), DATEDIF(E83,I83,"d"), DATEDIF(E83,TODAY(),"d")) -> 37 | R83: =IF($Q83>7,1,0) -> 1 | S83: =IF($Q83>15,1,0) -> 1 | T83: =IF($Q83>30,1,0) -> 1 | U83: =IF($Q83>60,1,0) -> 0
A84: 6000138844 | B84: INC42711347 | D84: 5975 | E84: 45777 | G84: Jitka Krnavkova (GBS CEE P2P CZ AP 2 4 / Z002HBHS) | H84: Ilona Splichalova | I84: 45807 | J84: SAP SOLUTION MANAGER S1A | K84: 3: Medium | L84: Confirm_Closed | M84: Permission for removing payment block X | N84: SIE_S4P_RS Siemens S4P - Readsoft | Q84: =IF(OR(ISNUMBER(MATCH(L84,MasterData!$D$3:$D$18,0)),ISNUMBER(MATCH(L84,MasterData!$C$3:$C$18,0))), DATEDIF(E84,I84,"d"), DATEDIF(E84,TODAY(),"d")) -> 30 | R84: =IF($Q84>7,1,0) -> 1 | S84: =IF($Q84>15,1,0) -> 1 | T84: =IF($Q84>30,1,0) -> 0 | U84: =IF($Q84>60,1,0) -> 0
A85: 6000138916 | D85: 5975 | E85: 45779 | G85: Ilona Splichalova (DI IT ERP CZ FICO / Z002Z2VA) | H85: Ilona Splichalova | I85: 45817 | J85: SAP SOLUTION MANAGER S1A | K85: 3: Medium | L85: Confirm_Closed | M85: Reminders not generated for Approvers | N85: SIE_S4P_RS Siemens S4P - Readsoft | Q85: =IF(OR(ISNUMBER(MATCH(L85,MasterData!$D$3:$D$18,0)),ISNUMBER(MATCH(L85,MasterData!$C$3:$C$18,0))), DATEDIF(E85,I85,"d"), DATEDIF(E85,TODAY(),"d")) -> 38 | R85: =IF($Q85>7,1,0) -> 1 | S85: =IF($Q85>15,1,0) -> 1 | T85: =IF($Q85>30,1,0) -> 1 | U85: =IF($Q85>60,1,0) -> 0
A86: 6000139044 | B86: INC42725740 | D86: SRE | E86: 45782 | G86: Pavla Tothova (GBS CEE P2P CZ AP 2 3 / Z002NYHT) | H86: Ulrich Rauch / 81739 Muenchen | I86: 45805 | J86: RFC_FITS | K86: 3: Medium | L86: Confirm_Closed | M86: S4P/7998 - problem with approval workflow - VIM ID 4985 | N86: SIE_S4P_RS Siemens S4P - Readsoft | Q86: =IF(OR(ISNUMBER(MATCH(L86,MasterData!$D$3:$D$18,0)),ISNUMBER(MATCH(L86,MasterData!$C$3:$C$18,0))), DATEDIF(E86,I86,"d"), DATEDIF(E86,TODAY(),"d")) -> 23 | R86: =IF($Q86>7,1,0) -> 1 | S86: =IF($Q86>15,1,0) -> 1 | T86: =IF($Q86>30,1,0) -> 0 | U86: =IF($Q86>60,1,0) -> 0
A87: 6000139205 | B87: INC42735561 | D87: 5975 | E87: 45783 | G87: Ivana Tomisova (GBS CEE P2P CZ AP 3 2 / Z004PK7A) | H87: Ulrich Rauch / 81739 Muenchen | I87: 45812 | J87: RFC_FITS | K87: 4: Low | L87: Confirm_Closed | M87: 3014 – Freight order - Doc ID 6183 stucked and not possible to post it | N87: SIE_S4P_RS Siemens S4P - Readsoft | Q87: =IF(OR(ISNUMBER(MATCH(L87,MasterData!$D$3:$D$18,0)),ISNUMBER(MATCH(L87,MasterData!$C$3:$C$18,0))), DATEDIF(E87,I87,"d"), DATEDIF(E87,TODAY(),"d")) -> 29 | R87: =IF($Q87>7,1,0) -> 1 | S87: =IF($Q87>15,1,0) -> 1 | T87: =IF($Q87>30,1,0) -> 0 | U87: =IF($Q87>60,1,0) -> 0
A88: 6000139326 | B88: INC42743833 | D88: 7040 | E88: 45784 | G88: Nicole Oulik (SI S MK / Z0005O5V) | H88: Ilona Splichalova | I88: 45791 | J88: RFC_FITS | K88: 3: Medium | L88: Confirm_Closed | M88: Work cycle login not possible, | N88: SIE_S4P_RS Siemens S4P - Readsoft | Q88: =IF(OR(ISNUMBER(MATCH(L88,MasterData!$D$3:$D$18,0)),ISNUMBER(MATCH(L88,MasterData!$C$3:$C$18,0))), DATEDIF(E88,I88,"d"), DATEDIF(E88,TODAY(),"d")) -> 7 | R88: =IF($Q88>7,1,0) -> 0 | S88: =IF($Q88>15,1,0) -> 0 | T88: =IF($Q88>30,1,0) -> 0 | U88: =IF($Q88>60,1,0) -> 0
A89: 6000139329 | B89: INC42744162 | D89: 5975 | E89: 45784 | G89: Martina Cajtchamlova (GBS CEE P2P CZ AP PE 2 / Z002M3FD) | H89: Albert Galek | I89: 45812 | J89: RFC_FITS | K89: 4: Low | L89: Confirm_Closed | M89: Bug fix for OpenText development - activate SHKZG field for VX_PO documents for tab Line Items - G/L Account | N89: SIE_S4P_RS Siemens S4P - Readsoft | Q89: =IF(OR(ISNUMBER(MATCH(L89,MasterData!$D$3:$D$18,0)),ISNUMBER(MATCH(L89,MasterData!$C$3:$C$18,0))), DATEDIF(E89,I89,"d"), DATEDIF(E89,TODAY(),"d")) -> 28 | R89: =IF($Q89>7,1,0) -> 1 | S89: =IF($Q89>15,1,0) -> 1 | T89: =IF($Q89>30,1,0) -> 0 | U89: =IF($Q89>60,1,0) -> 0
A90: 6000139369 | B90: INC42747521 | D90: SRE | E90: 45785 | G90: Pavla Tothova (GBS CEE P2P CZ AP 2 3 / Z002NYHT) | H90: Mr. Mukthar Baig | I90: 45818 | J90: Mukthar Baig | K90: 3: Medium | L90: In Process | M90: S4P/7998 - VIM ID 3854 and VIM ID 7194 | N90: SIE_S4P_RS Siemens S4P - Readsoft | Q90: =IF(OR(ISNUMBER(MATCH(L90,MasterData!$D$3:$D$18,0)),ISNUMBER(MATCH(L90,MasterData!$C$3:$C$18,0))), DATEDIF(E90,I90,"d"), DATEDIF(E90,TODAY(),"d")) -> 222 | R90: =IF($Q90>7,1,0) -> 1 | S90: =IF($Q90>15,1,0) -> 1 | T90: =IF($Q90>30,1,0) -> 1 | U90: =IF($Q90>60,1,0) -> 1
A91: 6000139374 | D91: SRE | E91: 45784 | G91: Ulrich Rauch (IT ECP FPS LV / Z00060NO) | H91: Albert Galek | I91: 45807 | J91: Albert Galek | K91: 3: Medium | L91: In Process | M91: VIM: DP No. missing in My Approved Invoices App | N91: SIE_S4P_RS Siemens S4P - Readsoft | Q91: =IF(OR(ISNUMBER(MATCH(L91,MasterData!$D$3:$D$18,0)),ISNUMBER(MATCH(L91,MasterData!$C$3:$C$18,0))), DATEDIF(E91,I91,"d"), DATEDIF(E91,TODAY(),"d")) -> 223 | R91: =IF($Q91>7,1,0) -> 1 | S91: =IF($Q91>15,1,0) -> 1 | T91: =IF($Q91>30,1,0) -> 1 | U91: =IF($Q91>60,1,0) -> 1
A92: 6000139577 | B92: INC42760716 | D92: 7092 | E92: 45786 | G92: Judith Kraus (CF R 7 4 5 / Z004MKEC) | H92: Ulrich Rauch / 81739 Muenchen | I92: 45793 | J92: RFC_FITS | K92: 2: High | L92: Confirm_Closed | M92: ARE 7040 S4P Buchungsperiode 007 2025 noch nicht geöffnet | N92: SIE_S4P_RS Siemens S4P - Readsoft | Q92: =IF(OR(ISNUMBER(MATCH(L92,MasterData!$D$3:$D$18,0)),ISNUMBER(MATCH(L92,MasterData!$C$3:$C$18,0))), DATEDIF(E92,I92,"d"), DATEDIF(E92,TODAY(),"d")) -> 7 | R92: =IF($Q92>7,1,0) -> 0 | S92: =IF($Q92>15,1,0) -> 0 | T92: =IF($Q92>30,1,0) -> 0 | U92: =IF($Q92>60,1,0) -> 0
A93: 6000139584 | B93: INC42760154 | D93: SRE | E93: 45786 | G93: Pavla Tothova (GBS CEE P2P CZ AP 2 3 / Z002NYHT) | H93: Ulrich Rauch / 81739 Muenchen | I93: 45797 | J93: RFC_FITS | K93: 3: Medium | L93: Confirm_Closed | M93: S4P/7998 - VIM ID 2977 and VIM ID 1961 - the invoices in "VIM completed" without approval | N93: SIE_S4P_RS Siemens S4P - Readsoft | Q93: =IF(OR(ISNUMBER(MATCH(L93,MasterData!$D$3:$D$18,0)),ISNUMBER(MATCH(L93,MasterData!$C$3:$C$18,0))), DATEDIF(E93,I93,"d"), DATEDIF(E93,TODAY(),"d")) -> 11 | R93: =IF($Q93>7,1,0) -> 1 | S93: =IF($Q93>15,1,0) -> 0 | T93: =IF($Q93>30,1,0) -> 0 | U93: =IF($Q93>60,1,0) -> 0
A94: 6000139600 | B94: INC42760922 | D94: SRE | E94: 45786 | G94: Pavla Tothova (GBS CEE P2P CZ AP 2 3 / Z002NYHT) | H94: Albert Galek | I94: 45811 | J94: RFC_FITS | K94: 2: High | L94: Confirm_Closed | M94: S4P/7998 - approval workflows not started | N94: SIE_S4P_RS Siemens S4P - Readsoft | Q94: =IF(OR(ISNUMBER(MATCH(L94,MasterData!$D$3:$D$18,0)),ISNUMBER(MATCH(L94,MasterData!$C$3:$C$18,0))), DATEDIF(E94,I94,"d"), DATEDIF(E94,TODAY(),"d")) -> 25 | R94: =IF($Q94>7,1,0) -> 1 | S94: =IF($Q94>15,1,0) -> 1 | T94: =IF($Q94>30,1,0) -> 0 | U94: =IF($Q94>60,1,0) -> 0
A95: 6000139702 | D95: 7092 | E95: 45789 | G95: Ulrich Rauch (IT ECP FPS LV / Z00060NO) | H95: Albert Galek | I95: 45810 | J95: SAP SOLUTION MANAGER S1A | K95: 2: High | L95: Confirm_Closed | M95: VIM: receiver_function_module with outdated status in S4P | N95: SIE_S4P_RS Siemens S4P - Readsoft | Q95: =IF(OR(ISNUMBER(MATCH(L95,MasterData!$D$3:$D$18,0)),ISNUMBER(MATCH(L95,MasterData!$C$3:$C$18,0))), DATEDIF(E95,I95,"d"), DATEDIF(E95,TODAY(),"d")) -> 21 | R95: =IF($Q95>7,1,0) -> 1 | S95: =IF($Q95>15,1,0) -> 1 | T95: =IF($Q95>30,1,0) -> 0 | U95: =IF($Q95>60,1,0) -> 0
A96: 6000139704 | B96: INC42769267 | D96: 7092 | E96: 45789 | G96: Wolfgang Geitner (DI IT FA UIT / Z00213NZ) | H96: Ilona Splichalova | I96: 45797 | J96: RFC_FITS | K96: 4: Low | L96: Confirm_Closed | M96: Ich benötige Zugang zum S4-Line-Service. | N96: SIE_S4P_RS Siemens S4P - Readsoft | Q96: =IF(OR(ISNUMBER(MATCH(L96,MasterData!$D$3:$D$18,0)),ISNUMBER(MATCH(L96,MasterData!$C$3:$C$18,0))), DATEDIF(E96,I96,"d"), DATEDIF(E96,TODAY(),"d")) -> 8 | R96: =IF($Q96>7,1,0) -> 1 | S96: =IF($Q96>15,1,0) -> 0 | T96: =IF($Q96>30,1,0) -> 0 | U96: =IF($Q96>60,1,0) -> 0
A97: 6000139963 | B97: INC42783591 | D97: 3003 | E97: 45791 | G97: Tobias Moest (SRE FIN AR 2 / Z000F12V) | H97: Kerstin Mueller / 81739 Muenchen | I97: 45805 | J97: RFC_FITS | K97: 2: High | L97: Confirm_Closed | M97: S4P VIM - Fehlermeldung bei Aufruf der Approval App | N97: SIE_S4P_RS Siemens S4P - Readsoft | Q97: =IF(OR(ISNUMBER(MATCH(L97,MasterData!$D$3:$D$18,0)),ISNUMBER(MATCH(L97,MasterData!$C$3:$C$18,0))), DATEDIF(E97,I97,"d"), DATEDIF(E97,TODAY(),"d")) -> 14 | R97: =IF($Q97>7,1,0) -> 1 | S97: =IF($Q97>15,1,0) -> 0 | T97: =IF($Q97>30,1,0) -> 0 | U97: =IF($Q97>60,1,0) -> 0
A98: 6000139986 | B98: INC42784591 | D98: SRE | E98: 45791 | G98: Zdenek Cifka (GBS CEE P2P CZ AP 2 3 / Z003JPCS) | H98: Albert Galek | I98: 45805 | J98: RFC_FITS | K98: 2: High | L98: Confirm_Closed | M98: S4P / It's not possible to use VIM Workplace, because there an ABAP error occurs | N98: SIE_S4P_RS Siemens S4P - Readsoft | Q98: =IF(OR(ISNUMBER(MATCH(L98,MasterData!$D$3:$D$18,0)),ISNUMBER(MATCH(L98,MasterData!$C$3:$C$18,0))), DATEDIF(E98,I98,"d"), DATEDIF(E98,TODAY(),"d")) -> 14 | R98: =IF($Q98>7,1,0) -> 1 | S98: =IF($Q98>15,1,0) -> 0 | T98: =IF($Q98>30,1,0) -> 0 | U98: =IF($Q98>60,1,0) -> 0
A99: 6000140063 | B99: INC42788004 | D99: 5975 | E99: 45792 | G99: Jitka Krnavkova (GBS CEE P2P CZ AP 2 4 / Z002HBHS) | H99: Ilona Splichalova | I99: 45806 | J99: RFC_FITS | K99: 3: Medium | L99: In Process | M99: T-CODE /COCKPIT/WC | N99: SIE_S4P_RS Siemens S4P - Readsoft | Q99: =IF(OR(ISNUMBER(MATCH(L99,MasterData!$D$3:$D$18,0)),ISNUMBER(MATCH(L99,MasterData!$C$3:$C$18,0))), DATEDIF(E99,I99,"d"), DATEDIF(E99,TODAY(),"d")) -> 215 | R99: =IF($Q99>7,1,0) -> 1 | S99: =IF($Q99>15,1,0) -> 1 | T99: =IF($Q99>30,1,0) -> 1 | U99: =IF($Q99>60,1,0) -> 1
A100: 6000140103 | B100: INC42791427 | D100: 3014 | E100: 45792 | G100: Juliana Batya Dora Ciupe (DI MC GMC MF-EWN PU-BUZ FIN BC / Z | H100: Albert Galek | I100: 45800 | J100: RFC_FITS | K100: 2: High | L100: Confirm_Closed | M100: VIM and Invoice approval app errors | N100: SIE_S4P_RS Siemens S4P - Readsoft | Q100: =IF(OR(ISNUMBER(MATCH(L100,MasterData!$D$3:$D$18,0)),ISNUMBER(MATCH(L100,MasterData!$C$3:$C$18,0))), DATEDIF(E100,I100,"d"), DATEDIF(E100,TODAY(),"d")) -> 8 | R100: =IF($Q100>7,1,0) -> 1 | S100: =IF($Q100>15,1,0) -> 0 | T100: =IF($Q100>30,1,0) -> 0 | U100: =IF($Q100>60,1,0) -> 0
...

Sheet VIM-Incidents_20250630_1325CET
A1: ID | B1: FutureNow Ticket | C1: External ID | D1: ARE | E1: Created On | F1: Due by | G1: Reported By | H1: Message Processor | I1: Last Changed on | J1: Last Changed By | K1: Priority | L1: Status | M1: Description | N1: Support Team | O1: System ID | Q1: Open Days | R1: Open 7D+ | S1: Open 15D+ | T1: Open 30D+ | U1: Open 60D+
A2: 6000127070 | B2: INC41987224 | D2: 5975 | E2: 45663 | G2: Lenka Michalusova (GBS CEE P2P CZ AP 2 4 / Z002HBHR) | H2: Ulrich Rauch / 81739 Muenchen | I2: 45727 | J2: RFC_FITS | K2: 4: Low | L2: Confirm_Closed | M2: VIM- missing tax code | N2: SIE_S4P_RS Siemens S4P - Readsoft | Q2: =IF(OR(ISNUMBER(MATCH(L2,MasterData!$D$3:$D$18,0)),ISNUMBER(MATCH(L2,MasterData!$C$3:$C$18,0))), DATEDIF(E2,I2,"d"), DATEDIF(E2,TODAY(),"d")) -> 64 | R2: =IF($Q2>7,1,0) -> 1 | S2: =IF($Q2>15,1,0) -> 1 | T2: =IF($Q2>30,1,0) -> 1 | U2: =IF($Q2>60,1,0) -> 1
A3: 6000127209 | B3: INC41997245 | D3: 5975 | E3: 45664 | G3: Simon Kostovski (GBS CEE P2P CZ AP 3 2 / Z003DW1N) | H3: Albert Galek | I3: 45673 | J3: RFC_FITS | K3: 3: Medium | L3: Confirm_Closed | M3: INC41861079 not solved but it was closed | N3: SIE_S4P_RS Siemens S4P - Readsoft | Q3: =IF(OR(ISNUMBER(MATCH(L3,MasterData!$D$3:$D$18,0)),ISNUMBER(MATCH(L3,MasterData!$C$3:$C$18,0))), DATEDIF(E3,I3,"d"), DATEDIF(E3,TODAY(),"d")) -> 9 | R3: =IF($Q3>7,1,0) -> 1 | S3: =IF($Q3>15,1,0) -> 0 | T3: =IF($Q3>30,1,0) -> 0 | U3: =IF($Q3>60,1,0) -> 0
A4: 6000127632 | B4: INC42022656 | D4: 5975 | E4: 45667 | G4: Barbora Struskova (GBS CEE P2P CZ AP 2 4 / Z002HZ1U) | H4: Ilona Splichalova | I4: 45679 | J4: RFC_FITS | K4: 4: Low | L4: Confirm_Closed | M4: automatic text | N4: SIE_S4P_RS Siemens S4P - Readsoft | Q4: =IF(OR(ISNUMBER(MATCH(L4,MasterData!$D$3:$D$18,0)),ISNUMBER(MATCH(L4,MasterData!$C$3:$C$18,0))), DATEDIF(E4,I4,"d"), DATEDIF(E4,TODAY(),"d")) -> 12 | R4: =IF($Q4>7,1,0) -> 1 | S4: =IF($Q4>15,1,0) -> 0 | T4: =IF($Q4>30,1,0) -> 0 | U4: =IF($Q4>60,1,0) -> 0
A5: 6000128352 | D5: 3003 | E5: 45674 | G5: Ilona Splichalova (DI IT ERP CZ FICO / Z002Z2VA) | H5: Albert Galek | I5: 45688 | J5: SAP SOLUTION MANAGER S1A | K5: 3: Medium | L5: Confirm_Closed | M5: DP 2807 in S4P: please check the status | N5: SIE_S4P_RS Siemens S4P - Readsoft | Q5: =IF(OR(ISNUMBER(MATCH(L5,MasterData!$D$3:$D$18,0)),ISNUMBER(MATCH(L5,MasterData!$C$3:$C$18,0))), DATEDIF(E5,I5,"d"), DATEDIF(E5,TODAY(),"d")) -> 14 | R5: =IF($Q5>7,1,0) -> 1 | S5: =IF($Q5>15,1,0) -> 0 | T5: =IF($Q5>30,1,0) -> 0 | U5: =IF($Q5>60,1,0) -> 0
A6: 6000128500 | B6: INC42075263 | D6: 7092 | E6: 45677 | G6: Lena Osterhus (CE SEC TPC / Z001MA1B) | H6: Ilona Splichalova | I6: 45684 | J6: RFC_FITS | K6: 4: Low | L6: Confirm_Closed | M6: Falsche Emailadresse bei Readsoft/ WebCycle | N6: SIE_S4P_RS Siemens S4P - Readsoft | Q6: =IF(OR(ISNUMBER(MATCH(L6,MasterData!$D$3:$D$18,0)),ISNUMBER(MATCH(L6,MasterData!$C$3:$C$18,0))), DATEDIF(E6,I6,"d"), DATEDIF(E6,TODAY(),"d")) -> 7 | R6: =IF($Q6>7,1,0) -> 0 | S6: =IF($Q6>15,1,0) -> 0 | T6: =IF($Q6>30,1,0) -> 0 | U6: =IF($Q6>60,1,0) -> 0
A7: 6000128546 | B7: INC42077895 | D7: SRE | E7: 45677 | F7: 45947 | G7: Zdenek Cifka (GBS CEE P2P CZ AP 2 3 / Z003JPCS) | H7: Ilona Splichalova | I7: 45835 | J7: Andrea Lamberty | K7: 3: Medium | L7: Postponed | M7: VIM ID's 2391 and 2623 - after posting the payment block was'nt entered and approval workflow was'nt started | N7: SIE_S4P_RS Siemens S4P - Readsoft | Q7: =IF(OR(ISNUMBER(MATCH(L7,MasterData!$D$3:$D$18,0)),ISNUMBER(MATCH(L7,MasterData!$C$3:$C$18,0))), DATEDIF(E7,I7,"d"), DATEDIF(E7,TODAY(),"d")) -> 330 | R7: =IF($Q7>7,1,0) -> 1 | S7: =IF($Q7>15,1,0) -> 1 | T7: =IF($Q7>30,1,0) -> 1 | U7: =IF($Q7>60,1,0) -> 1
A8: 6000128759 | B8: INC42093959 | D8: 7092 | E8: 45679 | G8: Andreas Mengele (MAP DF&PCM PCM / Z001THRJ) | H8: Ilona Splichalova | I8: 45686 | J8: RFC_FITS | K8: 4: Low | L8: Confirm_Closed | M8: Umstellung der Rechte von Susanne Spiegl auf Philipp Rath | N8: SIE_S4P_RS Siemens S4P - Readsoft | Q8: =IF(OR(ISNUMBER(MATCH(L8,MasterData!$D$3:$D$18,0)),ISNUMBER(MATCH(L8,MasterData!$C$3:$C$18,0))), DATEDIF(E8,I8,"d"), DATEDIF(E8,TODAY(),"d")) -> 7 | R8: =IF($Q8>7,1,0) -> 0 | S8: =IF($Q8>15,1,0) -> 0 | T8: =IF($Q8>30,1,0) -> 0 | U8: =IF($Q8>60,1,0) -> 0
A9: 6000129022 | B9: INC42106952 | D9: 5975 | E9: 45680 | G9: Renata Staricna (GBS CEE P2P CZ AP 2 4 / Z0046K6B) | H9: Ilona Splichalova | I9: 45705 | J9: RFC_FITS | K9: 4: Low | L9: Confirm_Closed | M9: Reminder - automatic answers | N9: SIE_S4P_RS Siemens S4P - Readsoft | Q9: =IF(OR(ISNUMBER(MATCH(L9,MasterData!$D$3:$D$18,0)),ISNUMBER(MATCH(L9,MasterData!$C$3:$C$18,0))), DATEDIF(E9,I9,"d"), DATEDIF(E9,TODAY(),"d")) -> 25 | R9: =IF($Q9>7,1,0) -> 1 | S9: =IF($Q9>15,1,0) -> 1 | T9: =IF($Q9>30,1,0) -> 0 | U9: =IF($Q9>60,1,0) -> 0
A10: 6000129245 | B10: INC42120663 | D10: 7092 | E10: 45684 | G10: Veronika Andres (IT ECP FPS T&CS / Z0029JJZ) | H10: Ilona Splichalova | I10: 45691 | J10: RFC_FITS | K10: 4: Low | L10: Confirm_Closed | M10: WebCycle User locked | N10: SIE_S4P_RS Siemens S4P - Readsoft | Q10: =IF(OR(ISNUMBER(MATCH(L10,MasterData!$D$3:$D$18,0)),ISNUMBER(MATCH(L10,MasterData!$C$3:$C$18,0))), DATEDIF(E10,I10,"d"), DATEDIF(E10,TODAY(),"d")) -> 7 | R10: =IF($Q10>7,1,0) -> 0 | S10: =IF($Q10>15,1,0) -> 0 | T10: =IF($Q10>30,1,0) -> 0 | U10: =IF($Q10>60,1,0) -> 0
A11: 6000129304 | B11: INC42122188 | D11: SRE | E11: 45684 | G11: Tobias Moest (SRE FIN AR 2 / Z000F12V) | H11: Albert Galek | I11: 45693 | J11: RFC_FITS | K11: 4: Low | L11: Confirm_Closed | M11: S4P 100 - VIM: Vorgang aus Klärungs-WF nicht vorhanden | N11: SIE_S4P_RS Siemens S4P - Readsoft | Q11: =IF(OR(ISNUMBER(MATCH(L11,MasterData!$D$3:$D$18,0)),ISNUMBER(MATCH(L11,MasterData!$C$3:$C$18,0))), DATEDIF(E11,I11,"d"), DATEDIF(E11,TODAY(),"d")) -> 9 | R11: =IF($Q11>7,1,0) -> 1 | S11: =IF($Q11>15,1,0) -> 0 | T11: =IF($Q11>30,1,0) -> 0 | U11: =IF($Q11>60,1,0) -> 0
A12: 6000129653 | D12: 3003 | E12: 45686 | G12: Ilona Splichalova (DI IT ERP CZ FICO / Z002Z2VA) | H12: Ilona Splichalova | I12: 45782 | J12: SAP SOLUTION MANAGER S1A | K12: 3: Medium | L12: Confirm_Closed | M12: VIM 2756 und 2774 - Error by 3 step approval WF by Construction Invoices | N12: SIE_S4P_RS Siemens S4P - Readsoft | Q12: =IF(OR(ISNUMBER(MATCH(L12,MasterData!$D$3:$D$18,0)),ISNUMBER(MATCH(L12,MasterData!$C$3:$C$18,0))), DATEDIF(E12,I12,"d"), DATEDIF(E12,TODAY(),"d")) -> 96 | R12: =IF($Q12>7,1,0) -> 1 | S12: =IF($Q12>15,1,0) -> 1 | T12: =IF($Q12>30,1,0) -> 1 | U12: =IF($Q12>60,1,0) -> 1
A13: 6000129990 | B13: INC42154604 | D13: SRE | E13: 45688 | G13: Zdenek Cifka (GBS CEE P2P CZ AP 2 3 / Z003JPCS) | H13: Albert Galek | I13: 45699 | J13: RFC_FITS | K13: 3: Medium | L13: Confirm_Closed | M13: Is not possible to start the approval workflow for VIM ID 2515 | N13: SIE_S4P_RS Siemens S4P - Readsoft | Q13: =IF(OR(ISNUMBER(MATCH(L13,MasterData!$D$3:$D$18,0)),ISNUMBER(MATCH(L13,MasterData!$C$3:$C$18,0))), DATEDIF(E13,I13,"d"), DATEDIF(E13,TODAY(),"d")) -> 11 | R13: =IF($Q13>7,1,0) -> 1 | S13: =IF($Q13>15,1,0) -> 0 | T13: =IF($Q13>30,1,0) -> 0 | U13: =IF($Q13>60,1,0) -> 0
A14: 6000130122 | B14: INC42161605 | D14: 3014 | E14: 45691 | G14: Pompilia Bianca Trifa (DI MC GMC MF-EWN PU-BUZ FIN LOG 1-2 / | H14: Ulrich Rauch / 81739 Muenchen | I14: 45708 | J14: RFC_FITS | K14: 3: Medium | L14: Confirm_Closed | M14: S4P VIM - Invoices in Approval steps (direct materials) not visible to the approver | N14: SIE_S4P_RS Siemens S4P - Readsoft | Q14: =IF(OR(ISNUMBER(MATCH(L14,MasterData!$D$3:$D$18,0)),ISNUMBER(MATCH(L14,MasterData!$C$3:$C$18,0))), DATEDIF(E14,I14,"d"), DATEDIF(E14,TODAY(),"d")) -> 17 | R14: =IF($Q14>7,1,0) -> 1 | S14: =IF($Q14>15,1,0) -> 1 | T14: =IF($Q14>30,1,0) -> 0 | U14: =IF($Q14>60,1,0) -> 0
A15: 6000130131 | B15: INC42161726 | D15: 3014 | E15: 45691 | G15: Andreea Laura Boran (DI MC GMC MF-EWN PU-BUZ FIN LOG 1-2 / Z | H15: Ulrich Rauch / 81739 Muenchen | I15: 45708 | J15: RFC_FITS | K15: 3: Medium | L15: Confirm_Closed | M15: S4P - VIM error in invoice approval | N15: SIE_S4P_RS Siemens S4P - Readsoft | Q15: =IF(OR(ISNUMBER(MATCH(L15,MasterData!$D$3:$D$18,0)),ISNUMBER(MATCH(L15,MasterData!$C$3:$C$18,0))), DATEDIF(E15,I15,"d"), DATEDIF(E15,TODAY(),"d")) -> 17 | R15: =IF($Q15>7,1,0) -> 1 | S15: =IF($Q15>15,1,0) -> 1 | T15: =IF($Q15>30,1,0) -> 0 | U15: =IF($Q15>60,1,0) -> 0
A16: 6000130842 | B16: INC42203263 | D16: 3003 | E16: 45698 | G16: Helge Preiss (SRE DP PM EU / Z001WZ3K) | H16: Albert Galek | I16: 45831 | J16: RFC_FITS | K16: 3: Medium | L16: Confirm_Closed | M16: S4P VIM FIORI Approval Invoice Management Fehlermeldung | N16: SIE_S4P_RS Siemens S4P - Readsoft | Q16: =IF(OR(ISNUMBER(MATCH(L16,MasterData!$D$3:$D$18,0)),ISNUMBER(MATCH(L16,MasterData!$C$3:$C$18,0))), DATEDIF(E16,I16,"d"), DATEDIF(E16,TODAY(),"d")) -> 133 | R16: =IF($Q16>7,1,0) -> 1 | S16: =IF($Q16>15,1,0) -> 1 | T16: =IF($Q16>30,1,0) -> 1 | U16: =IF($Q16>60,1,0) -> 1
A17: 6000130889 | B17: INC42205466 | D17: 7092 | E17: 45698 | G17: Laura Hochwind (IT ECP FPS AP1 / Z003NVNW) | H17: Ulrich Rauch / 81739 Muenchen | I17: 45705 | J17: RFC_FITS | K17: 3: Medium | L17: Confirm_Closed | M17: Add Substitute for Webcycle Readsoft | N17: SIE_S4P_RS Siemens S4P - Readsoft | Q17: =IF(OR(ISNUMBER(MATCH(L17,MasterData!$D$3:$D$18,0)),ISNUMBER(MATCH(L17,MasterData!$C$3:$C$18,0))), DATEDIF(E17,I17,"d"), DATEDIF(E17,TODAY(),"d")) -> 7 | R17: =IF($Q17>7,1,0) -> 0 | S17: =IF($Q17>15,1,0) -> 0 | T17: =IF($Q17>30,1,0) -> 0 | U17: =IF($Q17>60,1,0) -> 0
A18: 6000131438 | B18: INC42234456 | D18: 3003 | E18: 45701 | G18: Mario Beck (SRE DP PM EU / Z00109RY) | H18: Ramesh Itamsetti | I18: 45831 | J18: RFC_FITS | K18: 3: Medium | L18: Confirm_Closed | M18: S4P 100 VIM - Fehlermeldung bei WF-Freigabe | N18: SIE_S4P_RS Siemens S4P - Readsoft | Q18: =IF(OR(ISNUMBER(MATCH(L18,MasterData!$D$3:$D$18,0)),ISNUMBER(MATCH(L18,MasterData!$C$3:$C$18,0))), DATEDIF(E18,I18,"d"), DATEDIF(E18,TODAY(),"d")) -> 130 | R18: =IF($Q18>7,1,0) -> 1 | S18: =IF($Q18>15,1,0) -> 1 | T18: =IF($Q18>30,1,0) -> 1 | U18: =IF($Q18>60,1,0) -> 1
A19: 6000131514 | D19: 7092 | E19: 45702 | G19: Ulrich Rauch (IT ECP ERP-CP ARC2 / Z00060NO) | H19: Ulrich Rauch / 81739 Muenchen | I19: 45723 | J19: SAP SOLUTION MANAGER S1A | K19: 3: Medium | L19: Confirm_Closed | M19: VIM: VIM Authorization issue in Exceptions App (mid-term solution) | N19: SIE_S4P_RS Siemens S4P - Readsoft | Q19: =IF(OR(ISNUMBER(MATCH(L19,MasterData!$D$3:$D$18,0)),ISNUMBER(MATCH(L19,MasterData!$C$3:$C$18,0))), DATEDIF(E19,I19,"d"), DATEDIF(E19,TODAY(),"d")) -> 21 | R19: =IF($Q19>7,1,0) -> 1 | S19: =IF($Q19>15,1,0) -> 1 | T19: =IF($Q19>30,1,0) -> 0 | U19: =IF($Q19>60,1,0) -> 0
A20: 6000131715 | B20: INC42252236 | D20: 5975 | E20: 45705 | G20: Pavel Mego (GBS CEE P2P CZ AP 2 4 / Z001SCDJ) | H20: Ulrich Rauch / 81739 Muenchen | I20: 45713 | J20: RFC_FITS | K20: 4: Low | L20: Confirm_Closed | M20: duplicity check | N20: SIE_S4P_RS Siemens S4P - Readsoft | Q20: =IF(OR(ISNUMBER(MATCH(L20,MasterData!$D$3:$D$18,0)),ISNUMBER(MATCH(L20,MasterData!$C$3:$C$18,0))), DATEDIF(E20,I20,"d"), DATEDIF(E20,TODAY(),"d")) -> 8 | R20: =IF($Q20>7,1,0) -> 1 | S20: =IF($Q20>15,1,0) -> 0 | T20: =IF($Q20>30,1,0) -> 0 | U20: =IF($Q20>60,1,0) -> 0
A21: 6000132000 | B21: INC42270698 | D21: SRE | E21: 45707 | G21: Zdenek Cifka (GBS CEE P2P CZ AP 2 3 / Z003JPCS) | H21: Albert Galek | I21: 45735 | J21: RFC_FITS | K21: 3: Medium | L21: Confirm_Closed | M21: In VIM it is not possible to post the recurring documents, which contain multiple Profit Centers - VIM ID 3988 and 4340 | N21: SIE_S4P_RS Siemens S4P - Readsoft | Q21: =IF(OR(ISNUMBER(MATCH(L21,MasterData!$D$3:$D$18,0)),ISNUMBER(MATCH(L21,MasterData!$C$3:$C$18,0))), DATEDIF(E21,I21,"d"), DATEDIF(E21,TODAY(),"d")) -> 28 | R21: =IF($Q21>7,1,0) -> 1 | S21: =IF($Q21>15,1,0) -> 1 | T21: =IF($Q21>30,1,0) -> 0 | U21: =IF($Q21>60,1,0) -> 0
A22: 6000132651 | B22: INC42313692 | D22: 3003 | E22: 45714 | G22: Mario Beck (SRE DP PM EU / Z00109RY) | H22: Albert Galek | I22: 45723 | J22: RFC_FITS | K22: 4: Low | L22: Confirm_Closed | M22: S4P 100 VIM - #2777 can't be approved (new error message) | N22: SIE_S4P_RS Siemens S4P - Readsoft | Q22: =IF(OR(ISNUMBER(MATCH(L22,MasterData!$D$3:$D$18,0)),ISNUMBER(MATCH(L22,MasterData!$C$3:$C$18,0))), DATEDIF(E22,I22,"d"), DATEDIF(E22,TODAY(),"d")) -> 9 | R22: =IF($Q22>7,1,0) -> 1 | S22: =IF($Q22>15,1,0) -> 0 | T22: =IF($Q22>30,1,0) -> 0 | U22: =IF($Q22>60,1,0) -> 0
A23: 6000133013 | B23: INC42339428 | D23: 5975 | E23: 45719 | G23: Jitka Krnavkova (GBS CEE P2P CZ AP 2 4 / Z002HBHS) | H23: Ilona Splichalova | I23: 45734 | J23: RFC_FITS | K23: 4: Low | L23: Confirm_Closed | M23: Add user to ICFR group_READSOFT | N23: SIE_S4P_RS Siemens S4P - Readsoft | Q23: =IF(OR(ISNUMBER(MATCH(L23,MasterData!$D$3:$D$18,0)),ISNUMBER(MATCH(L23,MasterData!$C$3:$C$18,0))), DATEDIF(E23,I23,"d"), DATEDIF(E23,TODAY(),"d")) -> 15 | R23: =IF($Q23>7,1,0) -> 1 | S23: =IF($Q23>15,1,0) -> 0 | T23: =IF($Q23>30,1,0) -> 0 | U23: =IF($Q23>60,1,0) -> 0
A24: 6000133061 | B24: INC42342340 | D24: SRE | E24: 45719 | G24: Zdenek Cifka (GBS CEE P2P CZ AP 2 3 / Z003JPCS) | H24: Ilona Splichalova | I24: 45735 | J24: RFC_FITS | K24: 3: Medium | L24: Confirm_Closed | M24: VIM ID 1785 - approval workflow wasn't started but nevertheless is situated in VIM WP in My pending section | N24: SIE_S4P_RS Siemens S4P - Readsoft | Q24: =IF(OR(ISNUMBER(MATCH(L24,MasterData!$D$3:$D$18,0)),ISNUMBER(MATCH(L24,MasterData!$C$3:$C$18,0))), DATEDIF(E24,I24,"d"), DATEDIF(E24,TODAY(),"d")) -> 16 | R24: =IF($Q24>7,1,0) -> 1 | S24: =IF($Q24>15,1,0) -> 1 | T24: =IF($Q24>30,1,0) -> 0 | U24: =IF($Q24>60,1,0) -> 0
A25: 6000133063 | B25: INC42342645 | D25: 5220 | E25: 45719 | G25: Simona-Elena Kovar (CF R EEA PP PI / Z0046E1M) | H25: Ilona Splichalova | I25: 45778 | J25: RFC_FITS | K25: 4: Low | L25: Confirm_Closed | M25: GR posted, the payment block was removed in the background -> VIM workflow NOT completed | N25: SIE_S4P_RS Siemens S4P - Readsoft | Q25: =IF(OR(ISNUMBER(MATCH(L25,MasterData!$D$3:$D$18,0)),ISNUMBER(MATCH(L25,MasterData!$C$3:$C$18,0))), DATEDIF(E25,I25,"d"), DATEDIF(E25,TODAY(),"d")) -> 59 | R25: =IF($Q25>7,1,0) -> 1 | S25: =IF($Q25>15,1,0) -> 1 | T25: =IF($Q25>30,1,0) -> 1 | U25: =IF($Q25>60,1,0) -> 0
A26: 6000133075 | B26: INC42342669 | D26: 5220 | E26: 45719 | G26: Simona-Elena Kovar (CF R EEA PP PI / Z0046E1M) | H26: Albert Galek | I26: 45758 | J26: RFC_FITS | K26: 4: Low | L26: Confirm_Closed | M26: the document requires a technical approval although there is no price or quantity deviation | N26: SIE_S4P_RS Siemens S4P - Readsoft | Q26: =IF(OR(ISNUMBER(MATCH(L26,MasterData!$D$3:$D$18,0)),ISNUMBER(MATCH(L26,MasterData!$C$3:$C$18,0))), DATEDIF(E26,I26,"d"), DATEDIF(E26,TODAY(),"d")) -> 39 | R26: =IF($Q26>7,1,0) -> 1 | S26: =IF($Q26>15,1,0) -> 1 | T26: =IF($Q26>30,1,0) -> 1 | U26: =IF($Q26>60,1,0) -> 0
A27: 6000133085 | D27: 7092 | E27: 45719 | G27: Ulrich Rauch (IT ECP ERP-CP ARC2 / Z00060NO) | H27: Albert Galek | I27: 45731 | J27: SAP SOLUTION MANAGER S1A | K27: 3: Medium | L27: Confirm_Closed | M27: VIM: direct material PO: not able to choose non preferred approver | N27: SIE_S4P_RS Siemens S4P - Readsoft | Q27: =IF(OR(ISNUMBER(MATCH(L27,MasterData!$D$3:$D$18,0)),ISNUMBER(MATCH(L27,MasterData!$C$3:$C$18,0))), DATEDIF(E27,I27,"d"), DATEDIF(E27,TODAY(),"d")) -> 12 | R27: =IF($Q27>7,1,0) -> 1 | S27: =IF($Q27>15,1,0) -> 0 | T27: =IF($Q27>30,1,0) -> 0 | U27: =IF($Q27>60,1,0) -> 0
A28: 6000133086 | D28: 7092 | E28: 45719 | G28: Ulrich Rauch (IT ECP ERP-CP ARC2 / Z00060NO) | H28: Albert Galek | I28: 45773 | J28: SAP SOLUTION MANAGER S1A | K28: 3: Medium | L28: Confirm_Closed | M28: VIM ID 1785 and 5352 - approval workflow wasn't started but nevertheless is s | N28: SIE_S4P_RS Siemens S4P - Readsoft | Q28: =IF(OR(ISNUMBER(MATCH(L28,MasterData!$D$3:$D$18,0)),ISNUMBER(MATCH(L28,MasterData!$C$3:$C$18,0))), DATEDIF(E28,I28,"d"), DATEDIF(E28,TODAY(),"d")) -> 54 | R28: =IF($Q28>7,1,0) -> 1 | S28: =IF($Q28>15,1,0) -> 1 | T28: =IF($Q28>30,1,0) -> 1 | U28: =IF($Q28>60,1,0) -> 0
A29: 6000133087 | D29: 7092 | E29: 45719 | G29: Ulrich Rauch (IT ECP ERP-CP ARC2 / Z00060NO) | H29: Ilona Splichalova | I29: 45807 | J29: SAP SOLUTION MANAGER S1A | K29: 3: Medium | L29: Confirm_Closed | M29: VIM: different statuses in VIM Workplace and VIM Analytics | N29: SIE_S4P_RS Siemens S4P - Readsoft | Q29: =IF(OR(ISNUMBER(MATCH(L29,MasterData!$D$3:$D$18,0)),ISNUMBER(MATCH(L29,MasterData!$C$3:$C$18,0))), DATEDIF(E29,I29,"d"), DATEDIF(E29,TODAY(),"d")) -> 88 | R29: =IF($Q29>7,1,0) -> 1 | S29: =IF($Q29>15,1,0) -> 1 | T29: =IF($Q29>30,1,0) -> 1 | U29: =IF($Q29>60,1,0) -> 1
A30: 6000133442 | D30: 3003 | E30: 45722 | G30: Ilona Splichalova (DI IT ERP CZ FICO / Z002Z2VA) | H30: Ilona Splichalova | I30: 45786 | J30: SAP SOLUTION MANAGER S1A | K30: 3: Medium | L30: Confirm_Closed | M30: In VIM is not possible to cancel the invoice - DP 4288 | N30: SIE_S4P_RS Siemens S4P - Readsoft | Q30: =IF(OR(ISNUMBER(MATCH(L30,MasterData!$D$3:$D$18,0)),ISNUMBER(MATCH(L30,MasterData!$C$3:$C$18,0))), DATEDIF(E30,I30,"d"), DATEDIF(E30,TODAY(),"d")) -> 64 | R30: =IF($Q30>7,1,0) -> 1 | S30: =IF($Q30>15,1,0) -> 1 | T30: =IF($Q30>30,1,0) -> 1 | U30: =IF($Q30>60,1,0) -> 1
A31: 6000133644 | B31: INC42377517 | D31: 3014 | E31: 45723 | G31: Simon Kostovski (GBS CEE P2P CZ AP PE 2 / Z003DW1N) | H31: Albert Galek | I31: 45789 | J31: Ilona Splichalova | K31: 3: Medium | L31: In Process | M31: S4P Please adjust the VAT date to be identical with the invoice date for Company code 3014 | N31: SIE_S4P_RS Siemens S4P - Readsoft | Q31: =IF(OR(ISNUMBER(MATCH(L31,MasterData!$D$3:$D$18,0)),ISNUMBER(MATCH(L31,MasterData!$C$3:$C$18,0))), DATEDIF(E31,I31,"d"), DATEDIF(E31,TODAY(),"d")) -> 284 | R31: =IF($Q31>7,1,0) -> 1 | S31: =IF($Q31>15,1,0) -> 1 | T31: =IF($Q31>30,1,0) -> 1 | U31: =IF($Q31>60,1,0) -> 1
A32: 6000133647 | B32: INC42377569 | D32: 5975 | E32: 45723 | G32: Jan Binder (GBS CEE P2P CZ AP 2 2 / Z00435WC) | H32: Ilona Splichalova | I32: 45733 | J32: RFC_FITS | K32: 4: Low | L32: Confirm_Closed | M32: Receipt of invoices and posting in a different month/period. | N32: SIE_S4P_RS Siemens S4P - Readsoft | Q32: =IF(OR(ISNUMBER(MATCH(L32,MasterData!$D$3:$D$18,0)),ISNUMBER(MATCH(L32,MasterData!$C$3:$C$18,0))), DATEDIF(E32,I32,"d"), DATEDIF(E32,TODAY(),"d")) -> 10 | R32: =IF($Q32>7,1,0) -> 1 | S32: =IF($Q32>15,1,0) -> 0 | T32: =IF($Q32>30,1,0) -> 0 | U32: =IF($Q32>60,1,0) -> 0
A33: 6000133780 | B33: INC42386307 | D33: 3014 | E33: 45726 | G33: Andrei Vulpescu (DI MC GMC MF-EWN PU-BUZ FIN / Z00172BA) | H33: Albert Galek | I33: 45741 | J33: RFC_FITS | K33: 4: Low | L33: Confirm_Closed | M33: I cannot approve invoice release | N33: SIE_S4P_RS Siemens S4P - Readsoft | Q33: =IF(OR(ISNUMBER(MATCH(L33,MasterData!$D$3:$D$18,0)),ISNUMBER(MATCH(L33,MasterData!$C$3:$C$18,0))), DATEDIF(E33,I33,"d"), DATEDIF(E33,TODAY(),"d")) -> 15 | R33: =IF($Q33>7,1,0) -> 1 | S33: =IF($Q33>15,1,0) -> 0 | T33: =IF($Q33>30,1,0) -> 0 | U33: =IF($Q33>60,1,0) -> 0
A34: 6000133782 | B34: INC42386439 | D34: SRE | E34: 45726 | G34: Zdenek Cifka (GBS CEE P2P CZ AP 2 3 / Z003JPCS) | H34: Albert Galek | I34: 45735 | J34: RFC_FITS | K34: 3: Medium | L34: Confirm_Closed | M34: At VIM ID's 2977 and 1961 it's not possible to recall the approval workflow because they are situated in VIM WP in My co | N34: SIE_S4P_RS Siemens S4P - Readsoft | Q34: =IF(OR(ISNUMBER(MATCH(L34,MasterData!$D$3:$D$18,0)),ISNUMBER(MATCH(L34,MasterData!$C$3:$C$18,0))), DATEDIF(E34,I34,"d"), DATEDIF(E34,TODAY(),"d")) -> 9 | R34: =IF($Q34>7,1,0) -> 1 | S34: =IF($Q34>15,1,0) -> 0 | T34: =IF($Q34>30,1,0) -> 0 | U34: =IF($Q34>60,1,0) -> 0
A35: 6000133815 | B35: INC42387821 | D35: SRE | E35: 45726 | G35: Zdenek Cifka (GBS CEE P2P CZ AP 2 3 / Z003JPCS) | H35: Albert Galek | I35: 45748 | J35: RFC_FITS | K35: 3: Medium | L35: Confirm_Closed | M35: VIM ID 5033 - it's not possible to start the approval workflow manually for the specific person. | N35: SIE_S4P_RS Siemens S4P - Readsoft | Q35: =IF(OR(ISNUMBER(MATCH(L35,MasterData!$D$3:$D$18,0)),ISNUMBER(MATCH(L35,MasterData!$C$3:$C$18,0))), DATEDIF(E35,I35,"d"), DATEDIF(E35,TODAY(),"d")) -> 22 | R35: =IF($Q35>7,1,0) -> 1 | S35: =IF($Q35>15,1,0) -> 1 | T35: =IF($Q35>30,1,0) -> 0 | U35: =IF($Q35>60,1,0) -> 0
A36: 6000133897 | D36: 5975 | E36: 45727 | G36: Ilona Splichalova (DI IT ERP CZ FICO / Z002Z2VA) | H36: Albert Galek | I36: 45751 | J36: SAP SOLUTION MANAGER S1A | K36: 3: Medium | L36: Confirm_Closed | M36: VIM Table U-date Clarifications | N36: SIE_S4P_RS Siemens S4P - Readsoft | Q36: =IF(OR(ISNUMBER(MATCH(L36,MasterData!$D$3:$D$18,0)),ISNUMBER(MATCH(L36,MasterData!$C$3:$C$18,0))), DATEDIF(E36,I36,"d"), DATEDIF(E36,TODAY(),"d")) -> 24 | R36: =IF($Q36>7,1,0) -> 1 | S36: =IF($Q36>15,1,0) -> 1 | T36: =IF($Q36>30,1,0) -> 0 | U36: =IF($Q36>60,1,0) -> 0
A37: 6000134052 | B37: INC42401853 | D37: 3014 | E37: 45728 | G37: Ivana Tomisova (GBS CEE P2P CZ AP 3 2 / Z004PK7A) | H37: Mr. Silambarasan Vasu | I37: 45819 | K37: 4: Low | L37: Forwarded | M37: 3014 - ICC invoice not visible in VIM workplace | N37: MM - Materials Management | Q37: =IF(OR(ISNUMBER(MATCH(L37,MasterData!$D$3:$D$18,0)),ISNUMBER(MATCH(L37,MasterData!$C$3:$C$18,0))), DATEDIF(E37,I37,"d"), DATEDIF(E37,TODAY(),"d")) -> 279 | R37: =IF($Q37>7,1,0) -> 1 | S37: =IF($Q37>15,1,0) -> 1 | T37: =IF($Q37>30,1,0) -> 1 | U37: =IF($Q37>60,1,0) -> 1
A38: 6000134157 | B38: INC42406593 | D38: 5975 | E38: 45729 | G38: Pavel Mego (GBS CEE P2P CZ AP 2 4 / Z001SCDJ) | H38: Ilona Splichalova | I38: 45737 | J38: RFC_FITS | K38: 4: Low | L38: Confirm_Closed | M38: Stucked Webcycle | N38: SIE_S4P_RS Siemens S4P - Readsoft | Q38: =IF(OR(ISNUMBER(MATCH(L38,MasterData!$D$3:$D$18,0)),ISNUMBER(MATCH(L38,MasterData!$C$3:$C$18,0))), DATEDIF(E38,I38,"d"), DATEDIF(E38,TODAY(),"d")) -> 8 | R38: =IF($Q38>7,1,0) -> 1 | S38: =IF($Q38>15,1,0) -> 0 | T38: =IF($Q38>30,1,0) -> 0 | U38: =IF($Q38>60,1,0) -> 0
A39: 6000134167 | D39: 7092 | E39: 45729 | G39: Muskan Khanum Nagad (IT ECP ERP-CP / Z0053CPH) | H39: Albert Galek | I39: 45792 | J39: SAP SOLUTION MANAGER S1A | K39: 3: Medium | L39: Confirm_Closed | M39: Abap programming error in S4P | N39: SIE_S4P_RS Siemens S4P - Readsoft | Q39: =IF(OR(ISNUMBER(MATCH(L39,MasterData!$D$3:$D$18,0)),ISNUMBER(MATCH(L39,MasterData!$C$3:$C$18,0))), DATEDIF(E39,I39,"d"), DATEDIF(E39,TODAY(),"d")) -> 63 | R39: =IF($Q39>7,1,0) -> 1 | S39: =IF($Q39>15,1,0) -> 1 | T39: =IF($Q39>30,1,0) -> 1 | U39: =IF($Q39>60,1,0) -> 1
A40: 6000134304 | B40: INC42414880 | D40: 7011 | E40: 45729 | G40: Cosmin-Ovidiu Sarbu (DI MC GMC MF-EWN PU-BUZ FIN BC / Z0026A | H40: Ilona Splichalova | I40: 45782 | J40: RFC_FITS | K40: 4: Low | L40: Confirm_Closed | M40: Approval of invoices in VIM according to SAT | N40: SIE_S4P_RS Siemens S4P - Readsoft | Q40: =IF(OR(ISNUMBER(MATCH(L40,MasterData!$D$3:$D$18,0)),ISNUMBER(MATCH(L40,MasterData!$C$3:$C$18,0))), DATEDIF(E40,I40,"d"), DATEDIF(E40,TODAY(),"d")) -> 53 | R40: =IF($Q40>7,1,0) -> 1 | S40: =IF($Q40>15,1,0) -> 1 | T40: =IF($Q40>30,1,0) -> 1 | U40: =IF($Q40>60,1,0) -> 0
A41: 6000134423 | B41: INC42420961 | D41: 5975 | E41: 45730 | G41: Pavel Mego (GBS CEE P2P CZ AP 2 4 / Z001SCDJ) | H41: Ilona Splichalova | I41: 45748 | J41: RFC_FITS | K41: 4: Low | L41: Confirm_Closed | M41: readsoft messages | N41: SIE_S4P_RS Siemens S4P - Readsoft | Q41: =IF(OR(ISNUMBER(MATCH(L41,MasterData!$D$3:$D$18,0)),ISNUMBER(MATCH(L41,MasterData!$C$3:$C$18,0))), DATEDIF(E41,I41,"d"), DATEDIF(E41,TODAY(),"d")) -> 18 | R41: =IF($Q41>7,1,0) -> 1 | S41: =IF($Q41>15,1,0) -> 1 | T41: =IF($Q41>30,1,0) -> 0 | U41: =IF($Q41>60,1,0) -> 0
A42: 6000134460 | B42: INC42422286 | D42: 5975 | E42: 45730 | G42: Ivana Tomisova (GBS CEE P2P CZ AP 3 2 / Z004PK7A) | H42: Albert Galek | I42: 45748 | J42: RFC_FITS | K42: 4: Low | L42: Confirm_Closed | M42: 3014 - posting of inovices on mutiple POs | N42: SIE_S4P_RS Siemens S4P - Readsoft | Q42: =IF(OR(ISNUMBER(MATCH(L42,MasterData!$D$3:$D$18,0)),ISNUMBER(MATCH(L42,MasterData!$C$3:$C$18,0))), DATEDIF(E42,I42,"d"), DATEDIF(E42,TODAY(),"d")) -> 18 | R42: =IF($Q42>7,1,0) -> 1 | S42: =IF($Q42>15,1,0) -> 1 | T42: =IF($Q42>30,1,0) -> 0 | U42: =IF($Q42>60,1,0) -> 0
A43: 6000134543 | B43: INC42429350 | D43: 3014 | E43: 45733 | G43: Cristina Mariana Vega (DI MC GMC MF-EWN PU-BUZ FIN LOG / Z00 | H43: Albert Galek | I43: 45754 | J43: RFC_FITS | K43: 2: High | L43: Confirm_Closed | M43: Approval invoice not possible in Approval invoice Management app | N43: SIE_S4P_RS Siemens S4P - Readsoft | Q43: =IF(OR(ISNUMBER(MATCH(L43,MasterData!$D$3:$D$18,0)),ISNUMBER(MATCH(L43,MasterData!$C$3:$C$18,0))), DATEDIF(E43,I43,"d"), DATEDIF(E43,TODAY(),"d")) -> 21 | R43: =IF($Q43>7,1,0) -> 1 | S43: =IF($Q43>15,1,0) -> 1 | T43: =IF($Q43>30,1,0) -> 0 | U43: =IF($Q43>60,1,0) -> 0
A44: 6000134731 | B44: INC42441623 | D44: 5975 | E44: 45734 | G44: Pavel Mego (GBS CEE P2P CZ AP 2 4 / Z001SCDJ) | H44: Ilona Splichalova | I44: 45743 | J44: RFC_FITS | K44: 4: Low | L44: Confirm_Closed | M44: Webcycles with error | N44: SIE_S4P_RS Siemens S4P - Readsoft | Q44: =IF(OR(ISNUMBER(MATCH(L44,MasterData!$D$3:$D$18,0)),ISNUMBER(MATCH(L44,MasterData!$C$3:$C$18,0))), DATEDIF(E44,I44,"d"), DATEDIF(E44,TODAY(),"d")) -> 9 | R44: =IF($Q44>7,1,0) -> 1 | S44: =IF($Q44>15,1,0) -> 0 | T44: =IF($Q44>30,1,0) -> 0 | U44: =IF($Q44>60,1,0) -> 0
A45: 6000134816 | B45: INC42448216 | D45: 5220 | E45: 45735 | G45: Simona-Elena Kovar (CF R EEA PP PI / Z0046E1M) | H45: Ilona Splichalova | I45: 45762 | J45: RFC_FITS | K45: 4: Low | L45: Confirm_Closed | M45: Invoice in approval step but not visible in Approval Invoice Management application | N45: SIE_S4P_RS Siemens S4P - Readsoft | Q45: =IF(OR(ISNUMBER(MATCH(L45,MasterData!$D$3:$D$18,0)),ISNUMBER(MATCH(L45,MasterData!$C$3:$C$18,0))), DATEDIF(E45,I45,"d"), DATEDIF(E45,TODAY(),"d")) -> 27 | R45: =IF($Q45>7,1,0) -> 1 | S45: =IF($Q45>15,1,0) -> 1 | T45: =IF($Q45>30,1,0) -> 0 | U45: =IF($Q45>60,1,0) -> 0
A46: 6000134850 | B46: INC42449485 | D46: 3014 | E46: 45735 | G46: Juliana Batya Dora Ciupe (DI MC GMC MF-EWN PU-BUZ FIN BC / Z | H46: Albert Galek | I46: 45761 | J46: RFC_FITS | K46: 3: Medium | L46: Confirm_Closed | M46: Invoice with IDoc quantity incorect - issue in approval process | N46: SIE_S4P_RS Siemens S4P - Readsoft | Q46: =IF(OR(ISNUMBER(MATCH(L46,MasterData!$D$3:$D$18,0)),ISNUMBER(MATCH(L46,MasterData!$C$3:$C$18,0))), DATEDIF(E46,I46,"d"), DATEDIF(E46,TODAY(),"d")) -> 26 | R46: =IF($Q46>7,1,0) -> 1 | S46: =IF($Q46>15,1,0) -> 1 | T46: =IF($Q46>30,1,0) -> 0 | U46: =IF($Q46>60,1,0) -> 0
A47: 6000134958 | B47: INC42458439 | D47: 3003 | E47: 45736 | G47: Pavla Tothova (GBS CEE P2P CZ AP 2 3 / Z002NYHT) | H47: Ilona Splichalova | I47: 45750 | J47: RFC_FITS | K47: 3: Medium | L47: Confirm_Closed | M47: S4P/AUN 3003 VIM ID 5424 - the credit note was incorrectly booked as an invoice, nevertheless is situated in VIM WP in | N47: SIE_S4P_RS Siemens S4P - Readsoft | Q47: =IF(OR(ISNUMBER(MATCH(L47,MasterData!$D$3:$D$18,0)),ISNUMBER(MATCH(L47,MasterData!$C$3:$C$18,0))), DATEDIF(E47,I47,"d"), DATEDIF(E47,TODAY(),"d")) -> 14 | R47: =IF($Q47>7,1,0) -> 1 | S47: =IF($Q47>15,1,0) -> 0 | T47: =IF($Q47>30,1,0) -> 0 | U47: =IF($Q47>60,1,0) -> 0
A48: 6000135155 | B48: INC42469024 | D48: 7092 | E48: 45737 | G48: Dirk Eska (IT DF COL UC / Z0000X0D) | H48: Ilona Splichalova | I48: 45757 | J48: RFC_FITS | K48: 4: Low | L48: Confirm_Closed | M48: S4-line Service - Kein Zugang zum Webcycle Tool mehr | N48: SIE_S4P_RS Siemens S4P - Readsoft | Q48: =IF(OR(ISNUMBER(MATCH(L48,MasterData!$D$3:$D$18,0)),ISNUMBER(MATCH(L48,MasterData!$C$3:$C$18,0))), DATEDIF(E48,I48,"d"), DATEDIF(E48,TODAY(),"d")) -> 20 | R48: =IF($Q48>7,1,0) -> 1 | S48: =IF($Q48>15,1,0) -> 1 | T48: =IF($Q48>30,1,0) -> 0 | U48: =IF($Q48>60,1,0) -> 0
A49: 6000135247 | D49: SRE | E49: 45740 | G49: Ilona Splichalova (DI IT ERP CZ FICO / Z002Z2VA) | H49: Ilona Splichalova | I49: 45779 | J49: SAP SOLUTION MANAGER S1A | K49: 3: Medium | L49: Confirm_Closed | M49: VIM: Issue with items incorrectly placed in My Completed tab | N49: SIE_S4P_RS Siemens S4P - Readsoft | Q49: =IF(OR(ISNUMBER(MATCH(L49,MasterData!$D$3:$D$18,0)),ISNUMBER(MATCH(L49,MasterData!$C$3:$C$18,0))), DATEDIF(E49,I49,"d"), DATEDIF(E49,TODAY(),"d")) -> 39 | R49: =IF($Q49>7,1,0) -> 1 | S49: =IF($Q49>15,1,0) -> 1 | T49: =IF($Q49>30,1,0) -> 1 | U49: =IF($Q49>60,1,0) -> 0
A50: 6000135249 | B50: INC42467829 | D50: 3014 | E50: 45740 | G50: Andrei Vulpescu (DI MC GMC MF-EWN PU-BUZ FIN / Z00172BA) | H50: Ilona Splichalova | I50: 45782 | J50: RFC_FITS | K50: 3: Medium | L50: Confirm_Closed | M50: SAT / S4 approval step | N50: SIE_S4P_RS Siemens S4P - Readsoft | Q50: =IF(OR(ISNUMBER(MATCH(L50,MasterData!$D$3:$D$18,0)),ISNUMBER(MATCH(L50,MasterData!$C$3:$C$18,0))), DATEDIF(E50,I50,"d"), DATEDIF(E50,TODAY(),"d")) -> 42 | R50: =IF($Q50>7,1,0) -> 1 | S50: =IF($Q50>15,1,0) -> 1 | T50: =IF($Q50>30,1,0) -> 1 | U50: =IF($Q50>60,1,0) -> 0
A51: 6000135321 | B51: INC42480479 | D51: SRE | E51: 45740 | G51: Zdenek Cifka (GBS CEE P2P CZ AP 2 3 / Z003JPCS) | H51: Ilona Splichalova | I51: 45784 | J51: RFC_FITS | K51: 3: Medium | L51: Confirm_Closed | M51: it's not possible to post VIM ID 5242 on the account 65811000, because there an error is displayed | N51: SIE_S4P_RS Siemens S4P - Readsoft | Q51: =IF(OR(ISNUMBER(MATCH(L51,MasterData!$D$3:$D$18,0)),ISNUMBER(MATCH(L51,MasterData!$C$3:$C$18,0))), DATEDIF(E51,I51,"d"), DATEDIF(E51,TODAY(),"d")) -> 44 | R51: =IF($Q51>7,1,0) -> 1 | S51: =IF($Q51>15,1,0) -> 1 | T51: =IF($Q51>30,1,0) -> 1 | U51: =IF($Q51>60,1,0) -> 0
A52: 6000135513 | B52: INC42494408 | D52: 3003 | E52: 45742 | G52: Tobias Moest (SRE FIN AR 2 / Z000F12V) | I52: 45749 | J52: RFC_FITS | K52: 4: Low | L52: Confirm_Closed | M52: S4P VIM - Zahlungsbedingung falsch ermittelt? | N52: SIE_S4P_RS Siemens S4P - Readsoft | Q52: =IF(OR(ISNUMBER(MATCH(L52,MasterData!$D$3:$D$18,0)),ISNUMBER(MATCH(L52,MasterData!$C$3:$C$18,0))), DATEDIF(E52,I52,"d"), DATEDIF(E52,TODAY(),"d")) -> 7 | R52: =IF($Q52>7,1,0) -> 0 | S52: =IF($Q52>15,1,0) -> 0 | T52: =IF($Q52>30,1,0) -> 0 | U52: =IF($Q52>60,1,0) -> 0
A53: 6000135668 | B53: INC42504595 | D53: 5975 | E53: 45743 | G53: Simon Kostovski (GBS CEE P2P CZ AP PE 2 / Z003DW1N) | H53: Ulrich Rauch / 81739 Muenchen | I53: 45782 | J53: RFC_FITS | K53: 3: Medium | L53: Confirm_Closed | M53: S4P/3014- Invoices which have posted GR or adjusted prices and posted Invoices are stuck in approver’s workflow | N53: SIE_S4P_RS Siemens S4P - Readsoft | Q53: =IF(OR(ISNUMBER(MATCH(L53,MasterData!$D$3:$D$18,0)),ISNUMBER(MATCH(L53,MasterData!$C$3:$C$18,0))), DATEDIF(E53,I53,"d"), DATEDIF(E53,TODAY(),"d")) -> 39 | R53: =IF($Q53>7,1,0) -> 1 | S53: =IF($Q53>15,1,0) -> 1 | T53: =IF($Q53>30,1,0) -> 1 | U53: =IF($Q53>60,1,0) -> 0
A54: 6000135843 | D54: 7092 | E54: 45744 | G54: Ulrich Rauch (IT ECP ERP-CP ARC2 / Z00060NO) | H54: Ulrich Rauch / 81739 Muenchen | I54: 45759 | J54: SAP SOLUTION MANAGER S1A | K54: 3: Medium | L54: Confirm_Closed | M54: Fix missing purpose code JP in Readsoft GEN table | N54: SIE_S4P_RS Siemens S4P - Readsoft | Q54: =IF(OR(ISNUMBER(MATCH(L54,MasterData!$D$3:$D$18,0)),ISNUMBER(MATCH(L54,MasterData!$C$3:$C$18,0))), DATEDIF(E54,I54,"d"), DATEDIF(E54,TODAY(),"d")) -> 15 | R54: =IF($Q54>7,1,0) -> 1 | S54: =IF($Q54>15,1,0) -> 0 | T54: =IF($Q54>30,1,0) -> 0 | U54: =IF($Q54>60,1,0) -> 0
A55: 6000135916 | B55: INC42521355 | D55: 7092 | E55: 45747 | G55: Jonas Weber (IT DA DO PL / Z003DMKU) | H55: Ulrich Rauch / 81739 Muenchen | I55: 45754 | J55: RFC_FITS | K55: 4: Low | L55: Confirm_Closed | M55: Readsoft - Mailversand nach Query fehlt | N55: SIE_S4P_RS Siemens S4P - Readsoft | Q55: =IF(OR(ISNUMBER(MATCH(L55,MasterData!$D$3:$D$18,0)),ISNUMBER(MATCH(L55,MasterData!$C$3:$C$18,0))), DATEDIF(E55,I55,"d"), DATEDIF(E55,TODAY(),"d")) -> 7 | R55: =IF($Q55>7,1,0) -> 0 | S55: =IF($Q55>15,1,0) -> 0 | T55: =IF($Q55>30,1,0) -> 0 | U55: =IF($Q55>60,1,0) -> 0
A56: 6000135930 | B56: INC42521949 | D56: SRE | E56: 45747 | G56: Tobias Moest (SRE FIN AR 2 / Z000F12V) | H56: Ulrich Rauch / 81739 Muenchen | I56: 45758 | J56: RFC_FITS | K56: 4: Low | L56: Confirm_Closed | M56: S4P 100 - VIM: User erhält keine E-Mail zur Workflow Freigabe | N56: SIE_S4P_RS Siemens S4P - Readsoft | Q56: =IF(OR(ISNUMBER(MATCH(L56,MasterData!$D$3:$D$18,0)),ISNUMBER(MATCH(L56,MasterData!$C$3:$C$18,0))), DATEDIF(E56,I56,"d"), DATEDIF(E56,TODAY(),"d")) -> 11 | R56: =IF($Q56>7,1,0) -> 1 | S56: =IF($Q56>15,1,0) -> 0 | T56: =IF($Q56>30,1,0) -> 0 | U56: =IF($Q56>60,1,0) -> 0
A57: 6000136043 | D57: 7092 | E57: 45748 | G57: Ulrich Rauch (IT ECP ERP-CP ARC2 / Z00060NO) | H57: Kerstin Mueller / 81739 Muenchen | I57: 45786 | J57: SAP SOLUTION MANAGER S1A | K57: 3: Medium | L57: Confirm_Closed | M57: Readsoft: adaption tax code determination | N57: SIE_S4P_RS Siemens S4P - Readsoft | Q57: =IF(OR(ISNUMBER(MATCH(L57,MasterData!$D$3:$D$18,0)),ISNUMBER(MATCH(L57,MasterData!$C$3:$C$18,0))), DATEDIF(E57,I57,"d"), DATEDIF(E57,TODAY(),"d")) -> 38 | R57: =IF($Q57>7,1,0) -> 1 | S57: =IF($Q57>15,1,0) -> 1 | T57: =IF($Q57>30,1,0) -> 1 | U57: =IF($Q57>60,1,0) -> 0
A58: 6000136104 | B58: INC42532842 | D58: 3014 | E58: 45748 | G58: Alina Corina Maresi (DI MC GMC MF-EWN PU-BUZ FIN LOG 1-2 / Z | H58: Ulrich Rauch / 81739 Muenchen | I58: 45755 | J58: RFC_FITS | K58: 3: Medium | L58: Confirm_Closed | M58: No possible to approve the invoices because there is an error in determining the next approver | N58: SIE_S4P_RS Siemens S4P - Readsoft | Q58: =IF(OR(ISNUMBER(MATCH(L58,MasterData!$D$3:$D$18,0)),ISNUMBER(MATCH(L58,MasterData!$C$3:$C$18,0))), DATEDIF(E58,I58,"d"), DATEDIF(E58,TODAY(),"d")) -> 7 | R58: =IF($Q58>7,1,0) -> 0 | S58: =IF($Q58>15,1,0) -> 0 | T58: =IF($Q58>30,1,0) -> 0 | U58: =IF($Q58>60,1,0) -> 0
A59: 6000136206 | B59: INC42539676 | D59: 7411 | E59: 45749 | G59: Mona Sangl (DI MC GMC MF-EWN FIN LOG 1 2 / Z002Z0BD) | H59: Ilona Splichalova | I59: 45798 | J59: RFC_FITS | K59: 3: Medium | L59: Confirm_Closed | M59: Block reason "Over Limit" is not given | N59: SIE_S4P_RS Siemens S4P - Readsoft | Q59: =IF(OR(ISNUMBER(MATCH(L59,MasterData!$D$3:$D$18,0)),ISNUMBER(MATCH(L59,MasterData!$C$3:$C$18,0))), DATEDIF(E59,I59,"d"), DATEDIF(E59,TODAY(),"d")) -> 49 | R59: =IF($Q59>7,1,0) -> 1 | S59: =IF($Q59>15,1,0) -> 1 | T59: =IF($Q59>30,1,0) -> 1 | U59: =IF($Q59>60,1,0) -> 0
A60: 6000136305 | B60: INC42544021 | D60: 3011 | E60: 45749 | G60: Asma Meftah (DI SW EDA MNA / Z003U86H) | H60: Ulrich Rauch / 81739 Muenchen | I60: 45756 | J60: RFC_FITS | K60: 3: Medium | L60: Confirm_Closed | M60: KOFAX shows the following error: User Asma Meftah (Z003U86H) locked | N60: SIE_S4P_RS Siemens S4P - Readsoft | Q60: =IF(OR(ISNUMBER(MATCH(L60,MasterData!$D$3:$D$18,0)),ISNUMBER(MATCH(L60,MasterData!$C$3:$C$18,0))), DATEDIF(E60,I60,"d"), DATEDIF(E60,TODAY(),"d")) -> 7 | R60: =IF($Q60>7,1,0) -> 0 | S60: =IF($Q60>15,1,0) -> 0 | T60: =IF($Q60>30,1,0) -> 0 | U60: =IF($Q60>60,1,0) -> 0
A61: 6000136404 | B61: INC42552933 | D61: 3003 | E61: 45750 | G61: Pavla Tothova (GBS CEE P2P CZ AP 2 3 / Z002NYHT) | H61: Ilona Splichalova | I61: 45764 | J61: RFC_FITS | K61: 3: Medium | L61: Confirm_Closed | M61: S4P/AUN 3003 VIM ID 3471- the document cannot be cancelled | N61: SIE_S4P_RS Siemens S4P - Readsoft | Q61: =IF(OR(ISNUMBER(MATCH(L61,MasterData!$D$3:$D$18,0)),ISNUMBER(MATCH(L61,MasterData!$C$3:$C$18,0))), DATEDIF(E61,I61,"d"), DATEDIF(E61,TODAY(),"d")) -> 14 | R61: =IF($Q61>7,1,0) -> 1 | S61: =IF($Q61>15,1,0) -> 0 | T61: =IF($Q61>30,1,0) -> 0 | U61: =IF($Q61>60,1,0) -> 0
A62: 6000136413 | B62: INC42553406 | D62: SRE | E62: 45750 | G62: Pavla Tothova (GBS CEE P2P CZ AP 2 3 / Z002NYHT) | H62: Ilona Splichalova | I62: 45758 | J62: RFC_FITS | K62: 3: Medium | L62: Confirm_Closed | M62: S4P/7998 - DPs 2977 and 1961 - it's not possible to recall the approval workflows | N62: SIE_S4P_RS Siemens S4P - Readsoft | Q62: =IF(OR(ISNUMBER(MATCH(L62,MasterData!$D$3:$D$18,0)),ISNUMBER(MATCH(L62,MasterData!$C$3:$C$18,0))), DATEDIF(E62,I62,"d"), DATEDIF(E62,TODAY(),"d")) -> 8 | R62: =IF($Q62>7,1,0) -> 1 | S62: =IF($Q62>15,1,0) -> 0 | T62: =IF($Q62>30,1,0) -> 0 | U62: =IF($Q62>60,1,0) -> 0
A63: 6000136417 | B63: INC42553572 | D63: SRE | E63: 45750 | G63: Pavla Tothova (GBS CEE P2P CZ AP 2 3 / Z002NYHT) | H63: Albert Galek | I63: 45758 | J63: RFC_FITS | K63: 3: Medium | L63: Confirm_Closed | M63: S4P/7998 - VIM ID 5352 - approval workflow wasn't started. | N63: SIE_S4P_RS Siemens S4P - Readsoft | Q63: =IF(OR(ISNUMBER(MATCH(L63,MasterData!$D$3:$D$18,0)),ISNUMBER(MATCH(L63,MasterData!$C$3:$C$18,0))), DATEDIF(E63,I63,"d"), DATEDIF(E63,TODAY(),"d")) -> 8 | R63: =IF($Q63>7,1,0) -> 1 | S63: =IF($Q63>15,1,0) -> 0 | T63: =IF($Q63>30,1,0) -> 0 | U63: =IF($Q63>60,1,0) -> 0
A64: 6000136696 | B64: INC42571709 | D64: SRE | E64: 45755 | G64: Pavla Tothova (GBS CEE P2P CZ AP 2 3 / Z002NYHT) | H64: Ilona Splichalova | I64: 45763 | J64: RFC_FITS | K64: 3: Medium | L64: Confirm_Closed | M64: S4P/7998 - DP 2512 - it's not possible to recall the approval workflow | N64: SIE_S4P_RS Siemens S4P - Readsoft | Q64: =IF(OR(ISNUMBER(MATCH(L64,MasterData!$D$3:$D$18,0)),ISNUMBER(MATCH(L64,MasterData!$C$3:$C$18,0))), DATEDIF(E64,I64,"d"), DATEDIF(E64,TODAY(),"d")) -> 8 | R64: =IF($Q64>7,1,0) -> 1 | S64: =IF($Q64>15,1,0) -> 0 | T64: =IF($Q64>30,1,0) -> 0 | U64: =IF($Q64>60,1,0) -> 0
A65: 6000136707 | B65: INC42571588 | D65: SRE | E65: 45755 | G65: Pavla Tothova (GBS CEE P2P CZ AP 2 3 / Z002NYHT) | H65: Ilona Splichalova | I65: 45763 | J65: RFC_FITS | K65: 3: Medium | L65: Confirm_Closed | M65: S4P/7998 - DP 1032 - it's not possible to recall the approval workflow | N65: SIE_S4P_RS Siemens S4P - Readsoft | Q65: =IF(OR(ISNUMBER(MATCH(L65,MasterData!$D$3:$D$18,0)),ISNUMBER(MATCH(L65,MasterData!$C$3:$C$18,0))), DATEDIF(E65,I65,"d"), DATEDIF(E65,TODAY(),"d")) -> 8 | R65: =IF($Q65>7,1,0) -> 1 | S65: =IF($Q65>15,1,0) -> 0 | T65: =IF($Q65>30,1,0) -> 0 | U65: =IF($Q65>60,1,0) -> 0
A66: 6000136806 | D66: 7092 | E66: 45755 | G66: Ulrich Rauch (IT ECP FPS LV / Z00060NO) | H66: Ramesh Itamsetti | I66: 45789 | J66: SAP SOLUTION MANAGER S1A | K66: 3: Medium | L66: Confirm_Closed | M66: VIM: bugfix in GR Wait functionality | N66: SIE_S4P_RS Siemens S4P - Readsoft | Q66: =IF(OR(ISNUMBER(MATCH(L66,MasterData!$D$3:$D$18,0)),ISNUMBER(MATCH(L66,MasterData!$C$3:$C$18,0))), DATEDIF(E66,I66,"d"), DATEDIF(E66,TODAY(),"d")) -> 34 | R66: =IF($Q66>7,1,0) -> 1 | S66: =IF($Q66>15,1,0) -> 1 | T66: =IF($Q66>30,1,0) -> 1 | U66: =IF($Q66>60,1,0) -> 0
A67: 6000136916 | B67: INC42586578 | D67: SRE | E67: 45756 | G67: Pavla Tothova (GBS CEE P2P CZ AP 2 3 / Z002NYHT) | H67: Ilona Splichalova | I67: 45764 | J67: RFC_FITS | K67: 3: Medium | L67: Confirm_Closed | M67: S4P/7998 - problem with approval workflow - VIM ID 4984 und 4985 | N67: SIE_S4P_RS Siemens S4P - Readsoft | Q67: =IF(OR(ISNUMBER(MATCH(L67,MasterData!$D$3:$D$18,0)),ISNUMBER(MATCH(L67,MasterData!$C$3:$C$18,0))), DATEDIF(E67,I67,"d"), DATEDIF(E67,TODAY(),"d")) -> 8 | R67: =IF($Q67>7,1,0) -> 1 | S67: =IF($Q67>15,1,0) -> 0 | T67: =IF($Q67>30,1,0) -> 0 | U67: =IF($Q67>60,1,0) -> 0
A68: 6000137097 | B68: INC42596308 | D68: 7092 | E68: 45757 | G68: Nadine Huettl (LC IP LTA / Z0005Q3T) | H68: Ulrich Rauch / 81739 Muenchen | I68: 45765 | J68: RFC_FITS | K68: 4: Low | L68: Confirm_Closed | M68: Freigabe von Rechnungen nicht möglich (ARE 5811) | N68: SIE_S4P_RS Siemens S4P - Readsoft | Q68: =IF(OR(ISNUMBER(MATCH(L68,MasterData!$D$3:$D$18,0)),ISNUMBER(MATCH(L68,MasterData!$C$3:$C$18,0))), DATEDIF(E68,I68,"d"), DATEDIF(E68,TODAY(),"d")) -> 8 | R68: =IF($Q68>7,1,0) -> 1 | S68: =IF($Q68>15,1,0) -> 0 | T68: =IF($Q68>30,1,0) -> 0 | U68: =IF($Q68>60,1,0) -> 0
A69: 6000137324 | B69: INC42614440 | D69: 3014 | E69: 45761 | G69: Alina Corina Maresi (DI MC GMC MF-EWN PU-BUZ FIN LOG 1-2 / Z | H69: Ulrich Rauch / 81739 Muenchen | I69: 45771 | J69: RFC_FITS | K69: 2: High | L69: Confirm_Closed | M69: Error on approval invoices in "My inbox" VIM AUN 3014 | N69: SIE_S4P_RS Siemens S4P - Readsoft | Q69: =IF(OR(ISNUMBER(MATCH(L69,MasterData!$D$3:$D$18,0)),ISNUMBER(MATCH(L69,MasterData!$C$3:$C$18,0))), DATEDIF(E69,I69,"d"), DATEDIF(E69,TODAY(),"d")) -> 10 | R69: =IF($Q69>7,1,0) -> 1 | S69: =IF($Q69>15,1,0) -> 0 | T69: =IF($Q69>30,1,0) -> 0 | U69: =IF($Q69>60,1,0) -> 0
A70: 6000137341 | B70: INC42614781 | D70: 7092 | E70: 45761 | G70: Fabian Schmitzer (IT DA DO E / Z001WYFH) | H70: Ilona Splichalova | I70: 45768 | J70: RFC_FITS | K70: 4: Low | L70: Confirm_Closed | M70: No access to my S4P 100 / Webcycle list of documents | N70: SIE_S4P_RS Siemens S4P - Readsoft | Q70: =IF(OR(ISNUMBER(MATCH(L70,MasterData!$D$3:$D$18,0)),ISNUMBER(MATCH(L70,MasterData!$C$3:$C$18,0))), DATEDIF(E70,I70,"d"), DATEDIF(E70,TODAY(),"d")) -> 7 | R70: =IF($Q70>7,1,0) -> 0 | S70: =IF($Q70>15,1,0) -> 0 | T70: =IF($Q70>30,1,0) -> 0 | U70: =IF($Q70>60,1,0) -> 0
A71: 6000137533 | D71: 3008 | E71: 45762 | G71: Ulrich Rauch (IT ECP FPS LV / Z00060NO) | H71: Ilona Splichalova | I71: 45782 | J71: SAP SOLUTION MANAGER S1A | K71: 3: Medium | L71: Confirm_Closed | M71: VIM: DP 3924 block removed with single appr.step | N71: SIE_S4P_RS Siemens S4P - Readsoft | Q71: =IF(OR(ISNUMBER(MATCH(L71,MasterData!$D$3:$D$18,0)),ISNUMBER(MATCH(L71,MasterData!$C$3:$C$18,0))), DATEDIF(E71,I71,"d"), DATEDIF(E71,TODAY(),"d")) -> 20 | R71: =IF($Q71>7,1,0) -> 1 | S71: =IF($Q71>15,1,0) -> 1 | T71: =IF($Q71>30,1,0) -> 0 | U71: =IF($Q71>60,1,0) -> 0
A72: 6000137544 | B72: INC42625312 | D72: 3003 | E72: 45762 | G72: Tobias Moest (SRE FIN AR 2 / Z000F12V) | H72: Ulrich Rauch / 81739 Muenchen | I72: 45821 | J72: RFC_FITS | K72: 4: Low | L72: Confirm_Closed | M72: S4P 100 VIM - Selektion in VIM Analytics fehlerhaft | N72: SIE_S4P_RS Siemens S4P - Readsoft | Q72: =IF(OR(ISNUMBER(MATCH(L72,MasterData!$D$3:$D$18,0)),ISNUMBER(MATCH(L72,MasterData!$C$3:$C$18,0))), DATEDIF(E72,I72,"d"), DATEDIF(E72,TODAY(),"d")) -> 59 | R72: =IF($Q72>7,1,0) -> 1 | S72: =IF($Q72>15,1,0) -> 1 | T72: =IF($Q72>30,1,0) -> 1 | U72: =IF($Q72>60,1,0) -> 0
A73: 6000137636 | B73: INC42632582 | D73: 3014 | E73: 45763 | G73: Andrei Vulpescu (DI MC GMC MF-EWN PU-BUZ FIN / Z00172BA) | H73: Albert Galek | I73: 45782 | J73: RFC_FITS | K73: 2: High | L73: Confirm_Closed | M73: I cannot approve invoice due to error | N73: SIE_S4P_RS Siemens S4P - Readsoft | Q73: =IF(OR(ISNUMBER(MATCH(L73,MasterData!$D$3:$D$18,0)),ISNUMBER(MATCH(L73,MasterData!$C$3:$C$18,0))), DATEDIF(E73,I73,"d"), DATEDIF(E73,TODAY(),"d")) -> 19 | R73: =IF($Q73>7,1,0) -> 1 | S73: =IF($Q73>15,1,0) -> 1 | T73: =IF($Q73>30,1,0) -> 0 | U73: =IF($Q73>60,1,0) -> 0
A74: 6000137924 | B74: INC42657410 | D74: 5975 | E74: 45769 | G74: Libor Pas (GBS CEE P2P CZ SC 2 8 / Z004VCDA) | H74: Albert Galek | I74: 45782 | J74: RFC_FITS | K74: 4: Low | L74: Confirm_Closed | M74: proces blocked | N74: SIE_S4P_RS Siemens S4P - Readsoft | Q74: =IF(OR(ISNUMBER(MATCH(L74,MasterData!$D$3:$D$18,0)),ISNUMBER(MATCH(L74,MasterData!$C$3:$C$18,0))), DATEDIF(E74,I74,"d"), DATEDIF(E74,TODAY(),"d")) -> 13 | R74: =IF($Q74>7,1,0) -> 1 | S74: =IF($Q74>15,1,0) -> 0 | T74: =IF($Q74>30,1,0) -> 0 | U74: =IF($Q74>60,1,0) -> 0
A75: 6000138263 | D75: 3014 | E75: 45771 | G75: Albert Galek (IT ECP FPS LV / Z004W53N) | H75: Ilona Splichalova | I75: 45832 | J75: Ilona Splichalova | K75: 3: Medium | L75: In Process | M75: Please check below DPs ald close approval WF if needed | N75: SIE_S4P_RS Siemens S4P - Readsoft | Q75: =IF(OR(ISNUMBER(MATCH(L75,MasterData!$D$3:$D$18,0)),ISNUMBER(MATCH(L75,MasterData!$C$3:$C$18,0))), DATEDIF(E75,I75,"d"), DATEDIF(E75,TODAY(),"d")) -> 236 | R75: =IF($Q75>7,1,0) -> 1 | S75: =IF($Q75>15,1,0) -> 1 | T75: =IF($Q75>30,1,0) -> 1 | U75: =IF($Q75>60,1,0) -> 1
A76: 6000138316 | B76: INC42678209 | D76: SRE | E76: 45772 | G76: Pavla Tothova (GBS CEE P2P CZ AP 2 3 / Z002NYHT) | H76: Ilona Splichalova | I76: 45779 | J76: RFC_FITS | K76: 3: Medium | L76: Confirm_Closed | M76: S4P/7998 - VIM 6944 - it's not possible to recall the approval workflow and send it to a specific person | N76: SIE_S4P_RS Siemens S4P - Readsoft | Q76: =IF(OR(ISNUMBER(MATCH(L76,MasterData!$D$3:$D$18,0)),ISNUMBER(MATCH(L76,MasterData!$C$3:$C$18,0))), DATEDIF(E76,I76,"d"), DATEDIF(E76,TODAY(),"d")) -> 7 | R76: =IF($Q76>7,1,0) -> 0 | S76: =IF($Q76>15,1,0) -> 0 | T76: =IF($Q76>30,1,0) -> 0 | U76: =IF($Q76>60,1,0) -> 0
A77: 6000138428 | B77: INC42684362 | D77: SRE | E77: 45772 | G77: Pavla Tothova (GBS CEE P2P CZ AP 2 3 / Z002NYHT) | H77: Ulrich Rauch / 81739 Muenchen | I77: 45832 | J77: Ilona Splichalova | K77: 4: Low | L77: In Process | M77: S4P/7998 - VIM ID 6783 - approval workflow wasn't started | N77: SIE_S4P_RS Siemens S4P - Readsoft | Q77: =IF(OR(ISNUMBER(MATCH(L77,MasterData!$D$3:$D$18,0)),ISNUMBER(MATCH(L77,MasterData!$C$3:$C$18,0))), DATEDIF(E77,I77,"d"), DATEDIF(E77,TODAY(),"d")) -> 235 | R77: =IF($Q77>7,1,0) -> 1 | S77: =IF($Q77>15,1,0) -> 1 | T77: =IF($Q77>30,1,0) -> 1 | U77: =IF($Q77>60,1,0) -> 1
A78: 6000138437 | B78: INC42684231 | D78: SRE | E78: 45772 | G78: Pavla Tothova (GBS CEE P2P CZ AP 2 3 / Z002NYHT) | H78: Ilona Splichalova | I78: 45838 | J78: Ilona Splichalova | K78: 3: Medium | L78: Proposed Solution | M78: S4P/7998 - VIM ID 6829 - approval workflow wasn't started | N78: SIE_S4P_RS Siemens S4P - Readsoft | Q78: =IF(OR(ISNUMBER(MATCH(L78,MasterData!$D$3:$D$18,0)),ISNUMBER(MATCH(L78,MasterData!$C$3:$C$18,0))), DATEDIF(E78,I78,"d"), DATEDIF(E78,TODAY(),"d")) -> 66 | R78: =IF($Q78>7,1,0) -> 1 | S78: =IF($Q78>15,1,0) -> 1 | T78: =IF($Q78>30,1,0) -> 1 | U78: =IF($Q78>60,1,0) -> 1
